Workbook
Name HIT_1: 'Pool Index'!$G$46
Name HIT_19: 'Pool Index'!$R$70
Name PAGE_104_3133: '1928Rail'!$A$102
Name PAGE_104_3133: '1932Rail'!#REF!
Name PAGE_3_7131: '1928Rail'!$A$103
Name PAGE_3_7131: '1932Rail'!#REF!
Name PAGE_4_7131: '1928Rail'!#REF!
Name PAGE_4_7131: '1932Rail'!#REF!

Sheet Pool Index
A1: PoolID | B1: Technology | C1: Contract Location | D1: Collected Data? | E1: Given to RA | F1: Completed (X=yes, blank=no) | G1: Case Title(s) | H1: Vaughan Ref. | I1: Type of Document(s) | J1: Year pool formed | K1: First Litigation | L1: Final Litigation | M1: Grantbacks | N1: Foreign Firms | O1: Compulsory Licensing | P1: Licensees | Q1: Prior Litigation | R1: Notes
A2: 1919Equi | B2: Electrical Equipment | C2: NAR New York | D2: Y | F2: X | G2: United States v. General Electric Co., CCH 1952-53 Trade Cases 67,585 (D.C.N.J. Civil No. 45-75-C; Complaint, 1945; Final Consent Judgment, 1953). | H2: 164 | I2: CO, FJ | J2: 1919 | L2: 1953 | N2: Y | O2: RR | P2: 0 | R2: 600+ patents RR
A3: 1921Cast | B3: Cast Iron Pipes | C3: NAR New York | D3: Y | F3: X | G3: United States v. United States Pipe and Foundry Co., CCH 1948-49 Trade Cases 62,285 (D.N.J. Civil No. 10772; Complaint, 1947; Consent Decree, 1948). | H3: 123 | I3: CO, FJ | J3: 1929 | K3: 1947 | L3: 1948 | N3: N | O3: DP | P3: 4
A4: 1924Brak | B4: Braking Systems | C4: NAR New York | D4: Y | F4: X | G4: United States v. Bendix Aviation Corp., Westinghouse Air Brake Co., et al., CCH 1948-49 Trade Cases 62,349 (S.D.N.Y. Civil No. 44-284; Complaint , 1947; Consent Judgment re Westinghouse, 1948). | H4: 96-97 | I4: CO, FJ, LA | J4: 1924 | K4: 1947 | L4: 1948 | N4: N | O4: RF, RR | P4: 21
A5: 1924Sand | B5: Sand Spun Pipes | C5: NAR New York | D5: Y | F5: X | G5: United States v. Sand Spun Patents Corp., 1948-1949 Trade Cases 62,462 (D.N.J. Civil No. 125-49; Complaint, 1949; Consent Judgment, 1949). | H5: 123-24 | I5: CO, FJ | J5: 1924 | L5: 1949 | N5: N | O5: DP | P5: 0
A6: 1925Vent | B6: Ventilating Air Filters | C6: NAR Atlanta | D6: Y | F6: X | G6: United States v. American Air Filter Co., CCH 1946-47 Trade Cases 57,492 (W.D. Ky. Civil No. 574; Complaint, 1943; Consent Judgment, 1946). | H6: 92-93 | I6: FJ | J6: 1925 | L6: 1946 | N6: N | O6: DP, RR | P6: 4
A7: 1926Food | B7: Peach Pitting Machinery | C7: NAR San Francisco | D7: Y | F7: X | G7: United States v. Food Machinery and Chemical Corp. (N.D. Calif. Civil No. 29308-G; Complaint, 1949). | H7: 61 | I7: WO | J7: 1926 | L7: 1954 | N7: N | O7: RR | P7: 0
A8: 1927Airc | B8: Air-conditioning Equipment | C8: NAR New York | D8: Y | F8: X | G8: United States v. Auditorium Conditioning Corp., CCH 1944-45 Trade Cases 57,428 (S.D.N.Y. Civil No. 22-200; Complaint, 1943; Final Judgment, 1945). | H8: 55-56 | I8: CO, FJ, LA | J8: 1927 | K8: 1943 | L8: 1945 | N8: N | O8: DP | P8: 7
A9: 1927Flur | B9: Glass Lamps | C9: NAR New York | D9: Y | F9: X | G9: United States v. General Electric Co., Corning Glass Works, et al., CCH 1946-47 Trade Cases 57,448 (D.N.J. Civil No. 2590; Complaint, 1942; Consent Decree re Corning, 1946). | H9: 125-26 | I9: CO, FJ | J9: 1927 | L9: 1954 | N9: Y | O9: RF | P9: 11 | R9: Need to google search for Corning patents
A10: 1928Rail | B10: Rail Joint Bars | C10: NAR Chicago | D10: Y | F10: X | G10: United States v. Rail Joint Co., CCH 1946-47 Trade Cases ¶ 57,469, (N. D. Ill. Civil No. 43-C-1295; Complaint, 1943; Final Judgment, 1944); McKenna Process Company of Illinois, Appellee, v. Blatchford Corporation, Appellant, Gen. No. 9,464, APPELLATE COURT OF ILLINOIS, SECOND DISTRICT, 304 Ill. App. 101; 25 N.E.2d 916; 1940 Ill. App. LEXIS 921. | H10: 55 | I10: CO, FJ | J10: 1928 | L10: 1944 | N10: N | O10: DP | P10: 10 | R10: Think all of the patents are dedicated to public
A11: 1930Cabl | B11: High-Tension Cables | C11: NAR New York | D11: Y | F11: X | G11: United States v. General Cable Corp., CCH 1948-49 Trade Cases 62,300 (S.D.N.Y. Civil No. 40-76; Complaint, 1947; Consent Judgment, 1948). | H11: 58-59 | I11: CO, FJ, LA | J11: 1930 | L11: 1948 | M11: 1 | N11: Y | O11: RR, RF | P11: 0 | Q11: 0
A12: 1930Wate | B12: Water Conditioning Apparatus | C12: NAR New York | D12: Y | F12: X | G12: United States v. The Permutit Company and W. Spencer Robertson, CCH 1950-51 Trade Cases 62,888 (S.D.N.Y. Civil No. 32-394; Complaint, 1945; Consent Judgment, 1951). | H12: 163 | I12: CO, FJ, LA | J12: 1930 | L12: 1951 | M12: 1 | N12: Y | O12: RF, RR | P12: 0 | Q12: 0
A13: 1931Fuel | B13: Fuel Injection Equipment | C13: NAR New York | D13: Y | F13: X | G13: United States v. American Bosch Corp., CCH 1948-49 Trade Cases 62,284 (S.D.N.Y. Civil No. 20-164; Complaint and Consent Decree, Dec. 29, 1942). | H13: 158 | I13: CO, FJ | J13: 1931 | L13: 1942 | M13: 1 | N13: Y | O13: RR | P13: 0 | Q13: 1
A14: 1931Mill | B14: Milling Machines | C14: NAR Chicago | D14: Y | F14: X | G14: United States v. Cincinnati Milling Machine Co., CCH 1953-54 Trade Cases 67,733 (E.D. Mich Civil No. 13401; Complaint and Consent Judgment, April 19, 1954). | H14: 126 | I14: CO, FJ | J14: 1931 | L14: 1954 | N14: N | O14: RR | P14: 2
A15: 1932Phar | B15: Pharmaceuticals | C15: NAR New York | D15: Y | F15: X | G15: United States v. Merck and Co., CCH 1944-45 Trade Cases 57,416 (D.C.N.J. Civil No. 3159; Complaint, 1943; Consent Decree, 1945). | H15: 157-58 | I15: CO, FJ, LA | J15: 1932 | K15: 1943 | L15: 1945 | M15: 1 | N15: Y | O15: RF, DP | P15: 0 | Q15: 0
A16: 1932Rail | B16: Railroad Springs | C16: NAR Chicago | D16: Y | F16: X | G16: United States v. American Locomotive Co., CCH 1945-47 Trade Cases ¶ 57,621 (N.D. Ind. Civil No. 545; Complaint, 1945; Consent Judgment, 1947). | H16: 192 | I16: CO, FJ, LA | J16: 1932 | L16: 1947 | M16: 1 | N16: N | O16: RR, DP | P16: 9 | Q16: 0
A17: 1932Text | B17: Hosiery Machinery | C17: NAR New York | D17: Y | F17: X | G17: United States v. Textile Machine Works, CCH 1950-51 Trade Cases 62,709 (S.D.N.Y. Civil No. 43-671; Complaint, 1947; Fina; Judgment, 1950). | H17: 98 | I17: CO, FJ | J17: 1932 | K17: 1947 | L17: 1950 | M17: 0 | N17: N | O17: RR, DP | P17: 0 | Q17: 0 | R17: Patent pool?
A18: 1933Hydr | B18: Hydraulic Oil Pumps | C18: NADC | D18: N | F18: X | G18: Kobe, Inc. v. Dempsey Pump Co., 198 F.2d 416 (10th Cir. 1952); United States v. Kobe (N.D. Okla. Civil No. 2865; Complaint, 1951); also Civ. No. 2350. | H18: 61 | I18: FJ | J18: 1933 | K18: 1952 | L18: 1952 | M18: 1 | N18: N | P18: 0 | Q18: 0 | R18: ** Final judgments? Did not grant licenses to third parties after 1934.
A19: 1933Mach | B19: Machine Tools | C19: NAR Chicago | D19: Y | F19: X | G19: United States v. Associated Patents, 134 F. Supp. 74 (E.D. Mich., 1955). | H19: 61 | I19: FJ, LA | J19: 1933 | L19: 1955 | M19: 1 | N19: N | P19: 0 | Q19: 0
A20: 1933Phil | B20: Phillips Screws | C20: NAR Chicago | D20: Y | F20: X | G20: United States v. Phillips Screw Co., 1949 Trade Cas. (C.C.H.) ¶62,394 (N.D. Ill.) | H20: 124 | I20: CO, FJ, LA | J20: 1933 | K20: . | L20: 1949 | M20: 1 | N20: N | O20: RR | P20: 28 | Q20: 0
A21: 1934Colo | B21: Color Film | C21: NAR Riverside (LA) | D21: Y | F21: X | G21: United States v. Technicolor, Inc., CCH 1950-51 Trade Cases 2,586 (S.D. Calif. Civil No. 7507-M; Complaint, 1947; Consent Judgments, 1948 and 1950). | H21: 274-75 | I21: CO, LA, FJ | J21: 1934 | L21: 1950 | M21: 1 | N21: N | O21: RF, RR | P21: 0 | Q21: 0
A22: 1934Dry | B22: Dry Ice | C22: NAR New York | D22: Y | F22: X | G22: United States v. The Liquid Carbonic Corp., CCH Trade Cases 67,248 (E.D.N.Y. Civil No. 9179; Complaint, 1948; Final Judgment, 1952). | H22: 98-99 | I22: WO | J22: 1934 | L22: 1952 | M22: 1 | N22: N | O22: RR | P22: 0 | Q22: 0
A23: 1934Elec | B23: Electric Generators | C23: NAR New York | D23: Y | F23: X | G23: United States v. Westinghouse Electric Mfg. Co., CCH Current Trade Cases 67,501 (D.C.N.J. Civil No. 5152; Complaint, 1945; Consent Judgment, 1953). | H23: 163-64 | I23: LA | J23: 1934 | K23: 1953 | L23: 1953 | M23: 1 | N23: Y | O23: DP | P23: 0 | Q23: 0 | R23: ** Photocopy final judgment
A24: 1934Leci | B24: Lecithin | C24: NAR Chicago | D24: Y | F24: X | G24: United States v. American Lecithin Co., CCH 1946-47 Trade Cases 57,542 (N.D. Ohio Civil No. 24115; Complaint, 1946; Consent Judgment, 1947). | H24: 58 | I24: WO, LA, CO | J24: 1934 | L24: 1947 | M24: 1 | N24: Y | O24: RF, RR | P24: 1 | Q24: 0
A25: 1934Vari | B25: Variable Condensers | C25: NAR New York | D25: Y | F25: X | G25: United States v. General Instrument Corp., 87 F. Supp. 157, 194 (D.N.J. 1949); United States v. General Instrument Corp., 115 F. Supp. 582 (D.N.J. 1953). | H25: 52 | I25: LA, WO | J25: 1934 | K25: 1949 | L25: 1953 | M25: 1 | N25: N | O25: RR | P25: 3 | Q25: 1
A26: 1935Airc | B26: Aircraft Instruments and Parts | C26: NAR New York | D26: Y | F26: X | G26: United States v. Bendix Aviation Corporation, CCH 1946-47 Trade Cases 57,444 (D.C.N.J. Civil No. 2531; Complaint, 1942, Consent Decree, 1946). | H26: 158 | I26: CO, WO | J26: 1935 | K26: 1942 | L26: 1946 | M26: 1 | N26: Y | O26: RR, DP | P26: 0 | Q26: 0
A27: 1937Male | B27: Male Hormones | C27: NAR New York | D27: Y | F27: X | G27: United States v. Schering Corp., CCH Trade Regulation Reports, Supp. 1941-43, 52,729 (D.C.N.J. Civil No. 1919; Complaint and Consent Decree, Dec. 17, 1941). | H27: 157 | I27: CO, FJ, LA | J27: 1937 | K27: 1941 | L27: 1941 | N27: Y | P27: 0 | R27: No compulsory licensing
A28: 1937Park | B28: Parking Meters | C28: NAR Atlanta | D28: Y | F28: X | G28: United States v. Vehicular Parking, 54 F. Supp. 828, 831 (D. Delaware 1944); CCH 1944-45 Trade Cases 57,226. | H28: 89 | I28: FJ | J28: 1937 | K28: 1944 | L28: 1946 | N28: N | O28: RR | P28: 4
A29: 1937Stam | B29: Stamped Metal Wheels | C29: NAR Chicago | D29: Y | F29: X | G29: United States v. Kelsey-Hayes Wheel Co. (E.D.Mich. Civil No. 10-655; Complaint, 1951). | H29: 61 | I29: ME | J29: 1937 | L29: 1955 | M29: 0 | N29: N | O29: RR | P29: 11 | Q29: 1
A30: 1937Wrin | B30: Wrinkle Finishes | C30: NAR Chicago | D30: Y | F30: X | G30: United States v. New Wrinkle, Inc., 1955 Trade Cases (C.C.H.) ¶ 68,203 (S.D. Ohio). | H30: 122 | I30: LA, WO | J30: 1937 | K30: 1952 | L30: 1955 | M30: 0 | N30: N | P30: 200 | Q30: 1
A31: 1938Drop | B31: Dropout Cutouts | C31: NAR Chicago | D31: Y | F31: X | G31: United States v. Line Material Co., 333 U.S. 287, 305 (1948). | H31: 51-52 | I31: ME, WO | J31: 1938 | K31: 1948 | L31: 1948 | M31: 0 | N31: N | O31: RR | P31: 10 | Q31: 0
A32: 1938Opht | B32: Ophthalmic Frames | C32: NAR Kansas City | D32: Y | F32: X | G32: United States v. American Optical Co., CCH 1948-49 Trade Cases 62,308 (S.D.N.Y. Civil No. 10-391; Complaint, 1940; Final Consent Judgment, 1948). | H32: 59-60 | I32: WO | J32: 1938 | L32: 1948 | M32: 0 | N32: N | O32: RR | P32: 14 | Q32: 1
A33: 1938Slip | B33: Furniture Slip Covers | C33: NADC | D33: Y | F33: X | G33: United States v. Krasnov, 143 F. Supp. 184 (E.D. Penn., 1956). | H33: 61 | I33: WO | J33: 1938 | K33: 1954 | L33: 1954 | M33: 0 | N33: N | P33: 2 | Q33: 1 | R33: Was forced to grant licenses.
A34: 1942Tele | B34: Television | C34: NAR New York | D34: Y | F34: X | G34: United States v. Scophony Corp., CCH 1948-49 Trade Cases 62,238, 62,356, and 62,463 (S.D.N.Y. Civil No. 34-184; Complaint, 1945; Consent Decree, 1948 and 1949). | H34: 162 | I34: CO, FJ | J34: 1942 | L34: 1949 | N34: Y | O34: RR | P34: 0
A35: 1946Dayl | B35: Daylight Fluorescent Pigments | C35: NADC | D35: N | F35: X | G35: United States v. Switzer Brothers, Inc., Gantner & Mattern Co., The Firelure Corporation, The Sherwin-Williams Company, The Sherwin-Williams Company of California, Aberfoyle Manufacturing Company, Lawter Chemicals, Inc., Robert C. Switzer, Joseph L. Switzer, John O. Gantner, Jr., Eugene Burns, Gerald D. Stratford, and W. Bruce Beckley. | H35: 124-25 | I35: . | J35: 1949 | K35: 1953 | L35: 1953 | N35: N | O35: RR, RF | P35: 0 | R35: Need to obtain these documents again from chicago
A36: 1946Elas | B36: Elastic-Top Hosiery and Machinery | C36: NAR New York | D36: Y | F36: X | G36: United States v. The Davis Co., CCH 1952 Trade Cases 67,403 (S.D.N.Y. Civil No. 54-357; Complaint, 1949; Consent Judgment, 1952). See also: Baker-Cammack v. Davis., 181 F.2d 550 (1950). | H36: 60 | I36: CO, FJ | J36: 1946 | K36: 1949 | L36: 1952 | N36: N | O36: DP, RR | P36: 0
A37: 1948Trac | B37: Tractor Cabs | C37: NAR Chicago | D37: N | F37: X | G37: United States v. Bearing Distributors Co., CCH 1952-53 Trade Cases 67,595 (W.D. Mo. Civil No. 6895; Complaint, 1951; Consent Decree, 1953). | H37: 60-61 | I37: WO | J37: 1948 | K37: 1951 | L37: 1953 | N37: N | O37: RR | P37: 0
D39: =COUNTIF(D2:D34,"Y") -> 32 | E39: =COUNTIF(E2:E37,"Y") -> 0 | F39: =COUNTIF(F2:F37,"X") -> 36 | J39: =AVERAGE(J2:J37) -> 1933.2778 | L39: =AVERAGE(L2:L37) -> 1949.6944 | O39: =36-COUNTBLANK(O2:O37) -> 31
A40: Notes
A41: Document type abbreviations: LA=License Agreement; FJ/WO=Final Judgment; ME=Memorandum; CC=CCH Written Opinion, CO=Complaint
A42: RR=reasonable royalty basis; RF=royalty free, DP=dedicated to public
A44: Do not use/cannot find
A45: 1856Sewi | B45: Sewing Machines | C45: Wisconsin State Historical Society | H45: 41 | I45: LA | J45: 1856 | K45: . | L45: . | R45: Pre-1917
A46: 1890Toot | B46: Tooth Harrows | C46: . | G46: Bement v. National Harrow Co., 186 U.S. 70, 85 (1902); National Harrow Co. v. E. Bement and Sons, 47 N.Y.S. 462 (1897). | H46: 41-43 | I46: http://books.google.com/books?id=r-8GAAAAYAAJ&pg=RA3-PA751&lpg=RA3-PA751&dq=%22National+Harrow+Company%22&source=bl&ots=vCQKnNJHG-&sig=fZQBC1Krh6d9PqdyGbnwRwqkoUc&hl=en&ei=4MktS-vFJoresgPM5_G-BA&sa=X&oi=book_result&ct=result&resnum=4&ved=0CBkQ6AEwAw#v=onepage&q=%22National%20Harrow%20Company%22&f=false, also http://74.125.155.132/search?q=cache:D9fI_WInQO8J:www.keionline.org/misc-docs/ds-patentpools.pdf+%22patent+pools%22+hartford+empire&cd=3&hl=en&ct=clnk&gl=us&client=firefox-a | J46: 1890 | K46: 1902 | R46: Pre-1917
A47: 1895Pneu | B47: Pneumatic Straw Stackers | C47: NAR Chicago | G47: Indiana Mfg. Co. v. J. I. Case Threshing Mach. Co., 54 F. 365 (1907). | H47: . | I47: WO, LA | J47: 1895 | K47: 1907 | R47: Pre-1917
A48: 1912Dupl | B48: Duplicating Machines | C48: NAR Chicago | H48: . | I48: LA | J48: 1912 | L48: 1936 | R48: Pre-1917. Initial patent issued on 1912. Improvements were granted back. Does not appear to meet requirements of a pool. May be incorrect pool.
A49: 1916Dave | B49: Davenport Beds | C49: . | G49: WALTER E. KRAMER, EXECUTOR, ESTATE OF JULIUS KRAMER, DECEASED, PETITIONER, v. COMMISSIONER OF INTERNAL REVENUE, RESPONDENT. OLGA R. KRAMER, PETITIONER, v. COMMISSIONER OF INTERNAL REVENUE, RESPONDENT. JACOB L. SCHNADIG, PETITIONER, v. COMMISSIONER OF INTERNAL REVENUE, RESPONDENT., 27 B.T.A. 1043 (1933). | H49: . | I49: WO | R49: Pre-1917
A50: 1924Plat | B50: Plate Glass | C50: NAR Chicago | D50: N | G50: United States v. Hartford-Empire Co., 46 F. Supp. 541 (N.D. Ohio, 1942); Hartford-Empire Co. v. United States, 333 U.S. 386, 400 (Jan., 1945). | H50: 82 | I50: WO, ME | J50: 1924 | K50: 1942 | L50: 1945 | N50: N | R50: No list available; would need to search Google patents
A51: 1925Pris | B51: Prismatic Glassware | C51: NAR Ohio? | D51: N | G51: United States v. Holophane Co., 119 F. Supp. 114 (S.D. Ohio 1954). Civil Action No. 2659. | H51: . | I51: WO | J51: 1923 | L51: 1954 | N51: Y | R51: In Ohio?
A52: 1929Gyps | B52: Gypsum Boards | C52: Columbia | D52: N | G52: United States v. United States Gypsum Co., 333 U.S. 364, 368-69 (1948). | H52: 117-18 | I52: FJ , LA | J52: 1929 | K52: 1940 | L52: 1948 | N52: N | R52: Documents from District of Columbia
A53: 1929Coat | B53: Coated Abrasives | C53: NAR Boston | D53: Y | G53: United States v. Minnesota Mining and Mfg. Co., 92 F. Supp. 947, 964 (D. Mass. 1950). | H53: 155 | I53: WO | J53: 1929 | K53: 1950 | N53: Y | R53: Cannot obtain list from Boston
A54: 1931Grin | B54: Grinding Hobs | C54: . | H54: . | J54: 1931 | L54: 1943 | R54: Appears to be one firm only. Not sure why Lerner lists it as 3. Similar license agreements were granted to Tool companies.
A55: 1933Tele | B55: Television Apparatus | C55: . | R55: Australian firms only.
A56: 1934Stai | B56: Stainless Steel | C56: NAR New York | D56: Y | G56: United States v. Allegheny Ludlum Steel Corp., CCH 1948-49 Trade Cases 62,330 (D.N.J. Civil No. 45-83; Complaint, 1945; Consent Judgment, 1949). | H56: 124 | I56: CO, FJ | J56: 1934 | K56: 1945 | L56: 1948 | N56: N | O56: RR | P56: Y | R56: Not a patent pool; 18 companies licensed 4 patents from same company after 1937 (though illegal practices began in 1934 using patents licensed from another firm)
A57: 19??Acry | B57: Acrylic Acid | C57: NAR New York | G57: United States v. Imperial Chemical Industries, Ltd., 100 F. Supp. 504, 516 (S.D.N.Y. 1951). | H57: 155 | I57: WO | J57: 1907/1913 | L57: 1951 | R57: Pre-1917
A58: 1938Pour | B58: Pour Deppressants | C58: NAR (???) | R58: Can't find details
A59: 1938Indu | B59: Inductive Heat Treatments | C59: NAR Chicago | D59: Y | F59: X | G59: United States v. The Ohio Crankshaft Co., CCH 1958 Trade Cases 69,020 (N.D. Ohio). Civil No. 28299. | H59: 61 | I59: LA, WO | J59: 1938 | K59: . | L59: . | N59: N | O59: ? | P59: Y | R59: Will need to figure out the list of patents. This is difficult; there were three agreements: Ajax/Budd, Ohio/Budd, Ohio/Ajax (?) This pool was *not* broken up by litigation.
A60: 1943Tele | B60: Television/Radio Apparatus | C60: NAR (???) | R60: Can't find details
A61: 1947Algi | B61: Alginate (Dental) Impression Powder | C61: NADC | G61: . | I61: . | R61: Court found "no pooling of patents" so not a patent pool. Basically 1 patent is at the center of this.
A62: 1948Plas | B62: Plastic Artificial Eyes | C62: NAR (???) | R62: Maybe not pool - have requested the complaint from Chicago Archives
A63: 1948Tele | B63: Television Apparatus | C63: NAR (???) | R63: Can't find details
A64: 1956Glas | B64: Glass Fibers | C64: NAR (???) | R64: Can't find details
A65: 1956Sewi | B65: Sewing Machines | C65: NAR New York | G65: United States v. The Singer Manufacturing Co. | H65: . | I65: LA, WO | J65: 1956 | R65: Post-1950
A66: 1964Synt | B66: Synthetic Filmanent Yarns | C66: South Carolina | G66: Duplan Corp. v. Deering Milliken, Inc., 444 F. Supp 648 (D.S.C. 1977); 1981-2 Trade Cas. (CCH) P64,214 | H66: . | I66: WO | J66: 1964 | L66: 19XX | R66: Post-1950
A67: 1968Carp | B67: Carpet Seaming | C67: NAR (???) | G67: Carpet Seaming Tape Licensing Corp. v. Best Seam Inc., 694 F.2d 570 (1982). | H67: . | I67: WO | J67: 1968 | L67: 19XX | R67: Post-1950
A68: 1992Lase | B68: Laser Eye Surgery | C68: . | G68: FTC Docket No. 9286 (http://www.ftc.gov/os/1998/03/summit.cmp.htm) | H68: . | I68: WO | J68: 1992 | L68: 1998 | R68: Post-1950
A69: 19XXRubb | B69: Rubber | C69: . | G69: United States v. E. I. du Pont de Nemours and Co., et al., 26 F. Supp. 235 (1954). | H69: 61 | I69: WO | J69: 19XX | R69: "The Government has failed to prove conspiracy, monopolization, a restraint of trade, or any reasonable probability of a restraint, and for those reasons the Amended Complaint should be dismissed."
A70: 19XXFree | B70: Freeze-dried Drugs | C70: NAR (???) | G70: Cutter Laboratories, Inc. v. LyophileCryochem Corporation, 179 F.2d 80; 1949 | H70: . | I70: WO | J70: 19XX | L70: 19XX | R70: Reichel Reissue Patent No. Re. 20,969 and Flosdorf et al, Patent No. 2,345,548; "There was no evidence of restrictive practices by appellees in the granting of licenses." Other patents: Elser Patent No. 1,970,956, original Reichel patent No. 2,066,302. From Gilber (2004).
A71: 19XXPool | B71: Pools | C71: NAR San Francisco | G71: King v. Anthony Pools, 202 F. Supp. 426 (1962). | H71: . | I71: WO | J71: 19XX | L71: 19XX | R71: "The pooling of patents and cross-licensing, which are open equally to the public on the same terms, do not fall within the interdiction. Unlawful monopoly would arise only if the agreement were accompanied by the purpose of intent to exclude competition."

Sheet pool_chars.csv
A1: pool_id | B1: start_year | C1: end_year | D1: Duration | E1: pool_members | F1: foreign | G1: licensees | H1: num_pats | I1: lic_rest | J1: num_inital_pats | K1: grantbacks | L1: added | M1: prior_litigation
A2: ='Pool Index'!A2 -> 1919Equi | B2: ='Pool Index'!J2 -> 1919 | C2: ='Pool Index'!L2 -> 1953 | D2: =C2-B2 -> 34 | E2: =18-COUNTBLANK(Firms!B2:S2) -> 10 | F2: ='Pool Index'!N2 -> Y | G2: ='Pool Index'!P2 -> 0 | H2: =COUNTIF('all_pats.csv'!A:A,'pool_chars.csv'!A2) -> 0 | I2: . | J2: =COUNTIF('pre_pool_pats.csv'!A:A,'pool_chars.csv'!A2) -> 0 | K2: . | M2: ='Pool Index'!Q2 -> 0
A3: ='Pool Index'!A3 -> 1921Cast | B3: ='Pool Index'!J3 -> 1929 | C3: ='Pool Index'!L3 -> 1948 | D3: =C3-B3 -> 19 | E3: =18-COUNTBLANK(Firms!B3:S3) -> 2 | F3: ='Pool Index'!N3 -> N | G3: ='Pool Index'!P3 -> 4 | H3: =COUNTIF('all_pats.csv'!A:A,'pool_chars.csv'!A3) -> 0 | I3: 1 | J3: =COUNTIF('pre_pool_pats.csv'!A:A,'pool_chars.csv'!A3) -> 0 | K3: . | M3: ='Pool Index'!Q3 -> 0
A4: ='Pool Index'!A4 -> 1924Brak | B4: ='Pool Index'!J4 -> 1924 | C4: ='Pool Index'!L4 -> 1948 | D4: =C4-B4 -> 24 | E4: =18-COUNTBLANK(Firms!B4:S4) -> 6 | F4: ='Pool Index'!N4 -> N | G4: ='Pool Index'!P4 -> 21 | H4: =COUNTIF('all_pats.csv'!A:A,'pool_chars.csv'!A4) -> 0 | I4: 1 | J4: =COUNTIF('pre_pool_pats.csv'!A:A,'pool_chars.csv'!A4) -> 0 | K4: . | M4: ='Pool Index'!Q4 -> 0
A5: ='Pool Index'!A5 -> 1924Sand | B5: ='Pool Index'!J5 -> 1924 | C5: ='Pool Index'!L5 -> 1949 | D5: =C5-B5 -> 25 | E5: =18-COUNTBLANK(Firms!B5:S5) -> 3 | F5: ='Pool Index'!N5 -> N | G5: ='Pool Index'!P5 -> 0 | H5: =COUNTIF('all_pats.csv'!A:A,'pool_chars.csv'!A5) -> 0 | I5: 1 | J5: =COUNTIF('pre_pool_pats.csv'!A:A,'pool_chars.csv'!A5) -> 0 | K5: . | M5: ='Pool Index'!Q5 -> 0
A6: ='Pool Index'!A6 -> 1925Vent | B6: ='Pool Index'!J6 -> 1925 | C6: ='Pool Index'!L6 -> 1946 | D6: =C6-B6 -> 21 | E6: =18-COUNTBLANK(Firms!B6:S6) -> 2 | F6: ='Pool Index'!N6 -> N | G6: ='Pool Index'!P6 -> 4 | H6: =COUNTIF('all_pats.csv'!A:A,'pool_chars.csv'!A6) -> 0 | I6: 0 | J6: =COUNTIF('pre_pool_pats.csv'!A:A,'pool_chars.csv'!A6) -> 0 | K6: . | M6: ='Pool Index'!Q6 -> 0
A7: ='Pool Index'!A7 -> 1926Food | B7: ='Pool Index'!J7 -> 1926 | C7: ='Pool Index'!L7 -> 1954 | D7: =C7-B7 -> 28 | E7: =18-COUNTBLANK(Firms!B7:S7) -> 6 | F7: ='Pool Index'!N7 -> N | G7: ='Pool Index'!P7 -> 0 | H7: =COUNTIF('all_pats.csv'!A:A,'pool_chars.csv'!A7) -> 0 | I7: 0 | J7: =COUNTIF('pre_pool_pats.csv'!A:A,'pool_chars.csv'!A7) -> 0 | K7: . | M7: ='Pool Index'!Q7 -> 0
A8: ='Pool Index'!A8 -> 1927Airc | B8: ='Pool Index'!J8 -> 1927 | C8: ='Pool Index'!L8 -> 1945 | D8: =C8-B8 -> 18 | E8: =18-COUNTBLANK(Firms!B8:S8) -> 4 | F8: ='Pool Index'!N8 -> N | G8: ='Pool Index'!P8 -> 7 | H8: =COUNTIF('all_pats.csv'!A:A,'pool_chars.csv'!A8) -> 0 | I8: 0 | J8: =COUNTIF('pre_pool_pats.csv'!A:A,'pool_chars.csv'!A8) -> 0 | K8: . | M8: ='Pool Index'!Q8 -> 0
A9: ='Pool Index'!A9 -> 1927Flur | B9: ='Pool Index'!J9 -> 1927 | C9: ='Pool Index'!L9 -> 1954 | D9: =C9-B9 -> 27 | E9: =18-COUNTBLANK(Firms!B9:S9) -> 4 | F9: ='Pool Index'!N9 -> Y | G9: ='Pool Index'!P9 -> 11 | H9: =COUNTIF('all_pats.csv'!A:A,'pool_chars.csv'!A9) -> 0 | I9: . | J9: =COUNTIF('pre_pool_pats.csv'!A:A,'pool_chars.csv'!A9) -> 0 | K9: . | M9: ='Pool Index'!Q9 -> 0
A10: ='Pool Index'!A10 -> 1928Rail | B10: ='Pool Index'!J10 -> 1928 | C10: ='Pool Index'!L10 -> 1944 | D10: =C10-B10 -> 16 | E10: =18-COUNTBLANK(Firms!B10:S10) -> 3 | F10: ='Pool Index'!N10 -> N | G10: ='Pool Index'!P10 -> 10 | H10: =COUNTIF('all_pats.csv'!A:A,'pool_chars.csv'!A10) -> 0 | I10: 0 | J10: =COUNTIF('pre_pool_pats.csv'!A:A,'pool_chars.csv'!A10) -> 0 | K10: . | M10: ='Pool Index'!Q10 -> 0
A11: ='Pool Index'!A11 -> 1930Cabl | B11: ='Pool Index'!J11 -> 1930 | C11: ='Pool Index'!L11 -> 1948 | D11: =C11-B11 -> 18 | E11: =18-COUNTBLANK(Firms!B11:S11) -> 6 | F11: ='Pool Index'!N11 -> Y | G11: ='Pool Index'!P11 -> 0 | H11: =COUNTIF('all_pats.csv'!A:A,'pool_chars.csv'!A11) -> 294 | I11: 0 | J11: =COUNTIF('pre_pool_pats.csv'!A:A,'pool_chars.csv'!A11) -> 73 | K11: ='Pool Index'!M11 -> 1 | L11: =H11-J11 -> 221 | M11: ='Pool Index'!Q11 -> 0
A12: ='Pool Index'!A12 -> 1930Wate | B12: ='Pool Index'!J12 -> 1930 | C12: ='Pool Index'!L12 -> 1951 | D12: =C12-B12 -> 21 | E12: =18-COUNTBLANK(Firms!B12:S12) -> 4 | F12: ='Pool Index'!N12 -> Y | G12: ='Pool Index'!P12 -> 0 | H12: =COUNTIF('all_pats.csv'!A:A,'pool_chars.csv'!A12) -> 130 | I12: 0 | J12: =COUNTIF('pre_pool_pats.csv'!A:A,'pool_chars.csv'!A12) -> 4 | K12: ='Pool Index'!M12 -> 1 | L12: =H12-J12 -> 126 | M12: ='Pool Index'!Q12 -> 0
A13: ='Pool Index'!A13 -> 1931Fuel | B13: ='Pool Index'!J13 -> 1931 | C13: ='Pool Index'!L13 -> 1942 | D13: =C13-B13 -> 11 | E13: =18-COUNTBLANK(Firms!B13:S13) -> 4 | F13: ='Pool Index'!N13 -> Y | G13: ='Pool Index'!P13 -> 0 | H13: =COUNTIF('all_pats.csv'!A:A,'pool_chars.csv'!A13) -> 171 | I13: 1 | J13: =COUNTIF('pre_pool_pats.csv'!A:A,'pool_chars.csv'!A13) -> 22 | K13: ='Pool Index'!M13 -> 1 | L13: =H13-J13 -> 149 | M13: ='Pool Index'!Q13 -> 1
A14: ='Pool Index'!A14 -> 1931Mill | K14: . | M14: ='Pool Index'!Q14 -> 0
A15: ='Pool Index'!A15 -> 1932Phar | B15: ='Pool Index'!J15 -> 1932 | C15: ='Pool Index'!L15 -> 1945 | D15: =C15-B15 -> 13 | E15: =18-COUNTBLANK(Firms!B15:S15) -> 2 | F15: ='Pool Index'!N15 -> Y | G15: ='Pool Index'!P15 -> 0 | H15: =COUNTIF('all_pats.csv'!A:A,'pool_chars.csv'!A15) -> 110 | I15: 0 | J15: =COUNTIF('pre_pool_pats.csv'!A:A,'pool_chars.csv'!A15) -> 5 | K15: ='Pool Index'!M15 -> 1 | L15: =H15-J15 -> 105 | M15: ='Pool Index'!Q15 -> 0
A16: ='Pool Index'!A16 -> 1932Rail | B16: ='Pool Index'!J16 -> 1932 | C16: ='Pool Index'!L16 -> 1947 | D16: =C16-B16 -> 15 | E16: =18-COUNTBLANK(Firms!B16:S16) -> 3 | F16: ='Pool Index'!N16 -> N | G16: ='Pool Index'!P16 -> 9 | H16: =COUNTIF('all_pats.csv'!A:A,'pool_chars.csv'!A16) -> 13 | I16: 1 | J16: =COUNTIF('pre_pool_pats.csv'!A:A,'pool_chars.csv'!A16) -> 6 | K16: ='Pool Index'!M16 -> 1 | L16: =H16-J16 -> 7 | M16: ='Pool Index'!Q16 -> 0
A17: ='Pool Index'!A17 -> 1932Text | B17: ='Pool Index'!J17 -> 1932 | C17: ='Pool Index'!L17 -> 1950 | D17: =C17-B17 -> 18 | E17: =18-COUNTBLANK(Firms!B17:S17) -> 2 | F17: ='Pool Index'!N17 -> N | G17: ='Pool Index'!P17 -> 0 | H17: =COUNTIF('all_pats.csv'!A:A,'pool_chars.csv'!A17) -> 218 | I17: 0 | J17: =COUNTIF('pre_pool_pats.csv'!A:A,'pool_chars.csv'!A17) -> 39 | K17: ='Pool Index'!M17 -> 0 | L17: =H17-J17 -> 179 | M17: ='Pool Index'!Q17 -> 0
A18: ='Pool Index'!A18 -> 1933Hydr | B18: ='Pool Index'!J18 -> 1933 | C18: ='Pool Index'!L18 -> 1952 | D18: =C18-B18 -> 19 | E18: =18-COUNTBLANK(Firms!B18:S18) -> 2 | F18: ='Pool Index'!N18 -> N | G18: ='Pool Index'!P18 -> 0 | H18: =COUNTIF('all_pats.csv'!A:A,'pool_chars.csv'!A18) -> 46 | I18: . | J18: =COUNTIF('pre_pool_pats.csv'!A:A,'pool_chars.csv'!A18) -> 3 | K18: ='Pool Index'!M18 -> 1 | L18: =H18-J18 -> 43 | M18: ='Pool Index'!Q18 -> 0
A19: ='Pool Index'!A19 -> 1933Mach | B19: ='Pool Index'!J19 -> 1933 | C19: ='Pool Index'!L19 -> 1955 | D19: =C19-B19 -> 22 | E19: =18-COUNTBLANK(Firms!B19:S19) -> 5 | F19: ='Pool Index'!N19 -> N | G19: ='Pool Index'!P19 -> 0 | H19: =COUNTIF('all_pats.csv'!A:A,'pool_chars.csv'!A19) -> 9 | I19: . | J19: =COUNTIF('pre_pool_pats.csv'!A:A,'pool_chars.csv'!A19) -> 3 | K19: ='Pool Index'!M19 -> 1 | L19: =H19-J19 -> 6 | M19: ='Pool Index'!Q19 -> 0
A20: ='Pool Index'!A20 -> 1933Phil | B20: ='Pool Index'!J20 -> 1933 | C20: ='Pool Index'!L20 -> 1949 | D20: =C20-B20 -> 16 | E20: =18-COUNTBLANK(Firms!B20:S20) -> 2 | F20: ='Pool Index'!N20 -> N | G20: ='Pool Index'!P20 -> 28 | H20: =COUNTIF('all_pats.csv'!A:A,'pool_chars.csv'!A20) -> 26 | I20: 1 | J20: =COUNTIF('pre_pool_pats.csv'!A:A,'pool_chars.csv'!A20) -> 2 | K20: ='Pool Index'!M20 -> 1 | L20: =H20-J20 -> 24 | M20: ='Pool Index'!Q20 -> 0
A21: ='Pool Index'!A21 -> 1934Colo | B21: ='Pool Index'!J21 -> 1934 | C21: ='Pool Index'!L21 -> 1950 | D21: =C21-B21 -> 16 | E21: =18-COUNTBLANK(Firms!B21:S21) -> 2 | F21: ='Pool Index'!N21 -> N | G21: ='Pool Index'!P21 -> 0 | H21: =COUNTIF('all_pats.csv'!A:A,'pool_chars.csv'!A21) -> 162 | I21: 1 | J21: =COUNTIF('pre_pool_pats.csv'!A:A,'pool_chars.csv'!A21) -> 59 | K21: ='Pool Index'!M21 -> 1 | L21: =H21-J21 -> 103 | M21: ='Pool Index'!Q21 -> 0
A22: ='Pool Index'!A22 -> 1934Dry | B22: ='Pool Index'!J22 -> 1934 | C22: ='Pool Index'!L22 -> 1952 | D22: =C22-B22 -> 18 | E22: =18-COUNTBLANK(Firms!B22:S22) -> 4 | F22: ='Pool Index'!N22 -> N | G22: ='Pool Index'!P22 -> 0 | H22: =COUNTIF('all_pats.csv'!A:A,'pool_chars.csv'!A22) -> 58 | I22: 0 | J22: =COUNTIF('pre_pool_pats.csv'!A:A,'pool_chars.csv'!A22) -> 37 | K22: ='Pool Index'!M22 -> 1 | L22: =H22-J22 -> 21 | M22: ='Pool Index'!Q22 -> 0
A23: ='Pool Index'!A23 -> 1934Elec | B23: ='Pool Index'!J23 -> 1934 | C23: ='Pool Index'!L23 -> 1953 | D23: =C23-B23 -> 19 | E23: =18-COUNTBLANK(Firms!B23:S23) -> 2 | F23: ='Pool Index'!N23 -> Y | G23: ='Pool Index'!P23 -> 0 | H23: =COUNTIF('all_pats.csv'!A:A,'pool_chars.csv'!A23) -> 222 | I23: . | J23: =COUNTIF('pre_pool_pats.csv'!A:A,'pool_chars.csv'!A23) -> 30 | K23: ='Pool Index'!M23 -> 1 | L23: =H23-J23 -> 192 | M23: ='Pool Index'!Q23 -> 0
A24: ='Pool Index'!A24 -> 1934Leci | B24: ='Pool Index'!J24 -> 1934 | C24: ='Pool Index'!L24 -> 1947 | D24: =C24-B24 -> 13 | E24: =18-COUNTBLANK(Firms!B24:S24) -> 5 | F24: ='Pool Index'!N24 -> Y | G24: ='Pool Index'!P24 -> 1 | H24: =COUNTIF('all_pats.csv'!A:A,'pool_chars.csv'!A24) -> 63 | I24: 0 | J24: =COUNTIF('pre_pool_pats.csv'!A:A,'pool_chars.csv'!A24) -> 36 | K24: ='Pool Index'!M24 -> 1 | L24: =H24-J24 -> 27 | M24: ='Pool Index'!Q24 -> 0
A25: ='Pool Index'!A25 -> 1934Vari | B25: ='Pool Index'!J25 -> 1934 | C25: ='Pool Index'!L25 -> 1953 | D25: =C25-B25 -> 19 | E25: =18-COUNTBLANK(Firms!B25:S25) -> 3 | F25: ='Pool Index'!N25 -> N | G25: ='Pool Index'!P25 -> 3 | H25: =COUNTIF('all_pats.csv'!A:A,'pool_chars.csv'!A25) -> 74 | I25: 0 | J25: =COUNTIF('pre_pool_pats.csv'!A:A,'pool_chars.csv'!A25) -> 60 | K25: ='Pool Index'!M25 -> 1 | L25: =H25-J25 -> 14 | M25: ='Pool Index'!Q25 -> 1
A26: ='Pool Index'!A26 -> 1935Airc | B26: ='Pool Index'!J26 -> 1935 | C26: ='Pool Index'!L26 -> 1946 | D26: =C26-B26 -> 11 | E26: =18-COUNTBLANK(Firms!B26:S26) -> 18 | F26: ='Pool Index'!N26 -> Y | G26: ='Pool Index'!P26 -> 0 | H26: =COUNTIF('all_pats.csv'!A:A,'pool_chars.csv'!A26) -> 272 | I26: . | J26: =COUNTIF('pre_pool_pats.csv'!A:A,'pool_chars.csv'!A26) -> 92 | K26: ='Pool Index'!M26 -> 1 | L26: =H26-J26 -> 180 | M26: ='Pool Index'!Q26 -> 0
A27: ='Pool Index'!A27 -> 1937Male | K27: . | M27: ='Pool Index'!Q27 -> 0
A28: ='Pool Index'!A28 -> 1937Park | K28: . | M28: ='Pool Index'!Q28 -> 0
A29: ='Pool Index'!A29 -> 1937Stam | B29: ='Pool Index'!J29 -> 1937 | C29: ='Pool Index'!L29 -> 1955 | D29: =C29-B29 -> 18 | E29: =18-COUNTBLANK(Firms!B29:S29) -> 3 | F29: ='Pool Index'!N29 -> N | G29: ='Pool Index'!P29 -> 11 | H29: =COUNTIF('all_pats.csv'!A:A,'pool_chars.csv'!A29) -> 189 | I29: 1 | J29: =COUNTIF('pre_pool_pats.csv'!A:A,'pool_chars.csv'!A29) -> 90 | K29: ='Pool Index'!M29 -> 0 | L29: =H29-J29 -> 99 | M29: ='Pool Index'!Q29 -> 1
A30: ='Pool Index'!A30 -> 1937Wrin | B30: ='Pool Index'!J30 -> 1937 | C30: ='Pool Index'!L30 -> 1955 | D30: =C30-B30 -> 18 | E30: =18-COUNTBLANK(Firms!B30:S30) -> 2 | F30: ='Pool Index'!N30 -> N | G30: ='Pool Index'!P30 -> 200 | H30: =COUNTIF('all_pats.csv'!A:A,'pool_chars.csv'!A30) -> 77 | I30: . | J30: =COUNTIF('pre_pool_pats.csv'!A:A,'pool_chars.csv'!A30) -> 20 | K30: ='Pool Index'!M30 -> 0 | L30: =H30-J30 -> 57 | M30: ='Pool Index'!Q30 -> 1
A31: ='Pool Index'!A31 -> 1938Drop | B31: ='Pool Index'!J31 -> 1938 | C31: ='Pool Index'!L31 -> 1948 | D31: =C31-B31 -> 10 | E31: =18-COUNTBLANK(Firms!B31:S31) -> 2 | F31: ='Pool Index'!N31 -> N | G31: ='Pool Index'!P31 -> 10 | H31: =COUNTIF('all_pats.csv'!A:A,'pool_chars.csv'!A31) -> 2 | I31: 0 | J31: =COUNTIF('pre_pool_pats.csv'!A:A,'pool_chars.csv'!A31) -> 2 | K31: ='Pool Index'!M31 -> 0 | L31: =H31-J31 -> 0 | M31: ='Pool Index'!Q31 -> 0
A32: ='Pool Index'!A32 -> 1938Opht | B32: ='Pool Index'!J32 -> 1938 | C32: ='Pool Index'!L32 -> 1948 | D32: =C32-B32 -> 10 | E32: =18-COUNTBLANK(Firms!B32:S32) -> 4 | F32: ='Pool Index'!N32 -> N | G32: ='Pool Index'!P32 -> 14 | H32: =COUNTIF('all_pats.csv'!A:A,'pool_chars.csv'!A32) -> 22 | I32: 0 | J32: =COUNTIF('pre_pool_pats.csv'!A:A,'pool_chars.csv'!A32) -> 21 | K32: ='Pool Index'!M32 -> 0 | L32: =H32-J32 -> 1 | M32: ='Pool Index'!Q32 -> 1
A33: ='Pool Index'!A33 -> 1938Slip | B33: ='Pool Index'!J33 -> 1938 | C33: ='Pool Index'!L33 -> 1954 | D33: =C33-B33 -> 16 | E33: =18-COUNTBLANK(Firms!B33:S33) -> 2 | F33: ='Pool Index'!N33 -> N | G33: ='Pool Index'!P33 -> 2 | H33: =COUNTIF('all_pats.csv'!A:A,'pool_chars.csv'!A33) -> 2 | I33: . | J33: =COUNTIF('pre_pool_pats.csv'!A:A,'pool_chars.csv'!A33) -> 2 | K33: ='Pool Index'!M33 -> 0 | L33: =H33-J33 -> 0 | M33: ='Pool Index'!Q33 -> 1
A34: ='Pool Index'!A34 -> 1942Tele | B34: ='Pool Index'!J34 -> 1942 | C34: ='Pool Index'!L34 -> 1949 | D34: =C34-B34 -> 7 | E34: =18-COUNTBLANK(Firms!B34:S34) -> 3 | F34: ='Pool Index'!N34 -> Y | G34: ='Pool Index'!P34 -> 0 | H34: =COUNTIF('all_pats.csv'!A:A,'pool_chars.csv'!A34) -> 0 | I34: 0 | J34: =COUNTIF('pre_pool_pats.csv'!A:A,'pool_chars.csv'!A34) -> 0 | K34: . | M34: ='Pool Index'!Q34 -> 0
A35: ='Pool Index'!A35 -> 1946Dayl | B35: ='Pool Index'!J35 -> 1949 | C35: ='Pool Index'!L35 -> 1953 | D35: =C35-B35 -> 4 | E35: =18-COUNTBLANK(Firms!B35:S35) -> 6 | F35: ='Pool Index'!N35 -> N | G35: ='Pool Index'!P35 -> 0 | H35: =COUNTIF('all_pats.csv'!A:A,'pool_chars.csv'!A35) -> 0 | I35: 1 | J35: =COUNTIF('pre_pool_pats.csv'!A:A,'pool_chars.csv'!A35) -> 0 | K35: . | M35: ='Pool Index'!Q35 -> 0
A36: ='Pool Index'!A36 -> 1946Elas | B36: ='Pool Index'!J36 -> 1946 | C36: ='Pool Index'!L36 -> 1952 | D36: =C36-B36 -> 6 | E36: =18-COUNTBLANK(Firms!B36:S36) -> 3 | F36: ='Pool Index'!N36 -> N | G36: ='Pool Index'!P36 -> 0 | H36: =COUNTIF('all_pats.csv'!A:A,'pool_chars.csv'!A36) -> 0 | I36: 0 | J36: =COUNTIF('pre_pool_pats.csv'!A:A,'pool_chars.csv'!A36) -> 0 | K36: . | M36: ='Pool Index'!Q36 -> 0
A37: ='Pool Index'!A37 -> 1948Trac | B37: ='Pool Index'!J37 -> 1948 | C37: ='Pool Index'!L37 -> 1953 | D37: =C37-B37 -> 5 | E37: =18-COUNTBLANK(Firms!B37:S37) -> 3 | F37: ='Pool Index'!N37 -> N | G37: ='Pool Index'!P37 -> 0 | H37: =COUNTIF('all_pats.csv'!A:A,'pool_chars.csv'!A37) -> 0 | I37: 0 | J37: =COUNTIF('pre_pool_pats.csv'!A:A,'pool_chars.csv'!A37) -> 0 | K37: . | M37: ='Pool Index'!Q37 -> 0
A39: Average | B39: =AVERAGE(B11:B33) -> 1933.95 | C39: =AVERAGE(C11:C33) -> 1950 | D39: =AVERAGE(D11:D33) -> 16.05 | E39: =AVERAGE(E11:E33) -> 3.85 | G39: =AVERAGE(G11:G33) -> 13.9 | H39: =AVERAGE(H11:H33) -> 108 | I39: =AVERAGE(I11:I33) -> 0.35714286 | J39: =AVERAGE(J11:J33) -> 30.3 | K39: =AVERAGE(K11:K33) -> 0.7 | L39: =AVERAGE(L11:L33) -> 77.7
A40: Median | B40: =MEDIAN(B11:B33) -> 1934 | C40: =MEDIAN(C11:C33) -> 1950 | D40: =MEDIAN(D11:D33) -> 17 | E40: =MEDIAN(E11:E33) -> 3 | G40: =MEDIAN(G11:G33) -> 0 | H40: =MEDIAN(H11:H33) -> 75.5 | I40: =MEDIAN(I11:I33) -> 0 | J40: =MEDIAN(J11:J33) -> 21.5 | K40: =MEDIAN(K11:K33) -> 1 | L40: =MEDIAN(L11:L33) -> 50

Sheet antitrust violations
A1: PoolID | B1: Technology | C1: Antitrust Violations | D1: Remedies | E1: Case
A2: 1919Equi | B2: Electrical Equipment | E2: ='Pool Index'!G2 -> United States v. General Electric Co., CCH 1952-53 Trade Cases 67,585 (D.C.N.J. Civil No. 45-75-C; Complaint, 1945; Final Consent Judgment, 1953).
A3: 1921Cast | B3: Cast Iron Pipes | E3: ='Pool Index'!G3 -> United States v. United States Pipe and Foundry Co., CCH 1948-49 Trade Cases 62,285 (D.N.J. Civil No. 10772; Complaint, 1947; Consent Decree, 1948).
A4: 1924Brak | B4: Braking Systems | E4: ='Pool Index'!G4 -> United States v. Bendix Aviation Corp., Westinghouse Air Brake Co., et al., CCH 1948-49 Trade Cases 62,349 (S.D.N.Y. Civil No. 44-284; Complaint , 1947; Consent Judgment re Westinghouse, 1948).
A5: 1924Sand | B5: Sand Spun Pipes | E5: ='Pool Index'!G5 -> United States v. Sand Spun Patents Corp., 1948-1949 Trade Cases 62,462 (D.N.J. Civil No. 125-49; Complaint, 1949; Consent Judgment, 1949).
A6: 1925Vent | B6: Ventilating Air Filters | E6: ='Pool Index'!G6 -> United States v. American Air Filter Co., CCH 1946-47 Trade Cases 57,492 (W.D. Ky. Civil No. 574; Complaint, 1943; Consent Judgment, 1946).
A7: 1926Food | B7: Peach Pitting Machinery | E7: ='Pool Index'!G7 -> United States v. Food Machinery and Chemical Corp. (N.D. Calif. Civil No. 29308-G; Complaint, 1949).
A8: 1927Airc | B8: Air-conditioning Equipment | E8: ='Pool Index'!G8 -> United States v. Auditorium Conditioning Corp., CCH 1944-45 Trade Cases 57,428 (S.D.N.Y. Civil No. 22-200; Complaint, 1943; Final Judgment, 1945).
A9: 1927Flur | B9: Glass Lamps | E9: ='Pool Index'!G9 -> United States v. General Electric Co., Corning Glass Works, et al., CCH 1946-47 Trade Cases 57,448 (D.N.J. Civil No. 2590; Complaint, 1942; Consent Decree re Corning, 1946).
A10: 1928Rail | B10: Rail Joint Bars | E10: ='Pool Index'!G10 -> United States v. Rail Joint Co., CCH 1946-47 Trade Cases ¶ 57,469, (N. D. Ill. Civil No. 43-C-1295; Complaint, 1943; Final Judgment, 1944); McKenna Process Company of Illinois, Appellee, v. Blatchford Corporation, Appellant, Gen. No. 9,464, APPELLATE COURT OF ILLINOIS, SECOND DISTRICT, 304 Ill. App. 101; 25 N.E.2d 916; 1940 Ill. App. LEXIS 921.
A11: 1930Cabl | B11: High-Tension Cables | C11: Price-fixing; Denied licenses to competitors; Divided world markets | D11: Restrictive agreements cancelled; Compulsory RAND licensing | E11: ='Pool Index'!G11 -> United States v. General Cable Corp., CCH 1948-49 Trade Cases 62,300 (S.D.N.Y. Civil No. 40-76; Complaint, 1947; Consent Judgment, 1948).
A12: 1930Wate | B12: Water Conditioning Apparatus | C12: Denied licenses to competitors; Divided world markets | D12: Restrictive agreements cancelled; Ccompulsory RAND and royalty-free licensing | E12: ='Pool Index'!G12 -> United States v. The Permutit Company and W. Spencer Robertson, CCH 1950-51 Trade Cases 62,888 (S.D.N.Y. Civil No. 32-394; Complaint, 1945; Consent Judgment, 1951).
A13: 1931Fuel | B13: Fuel Injection Equipment | C13: Denied licenses to competitors; Divided world markets; | D13: Restricitve agreements cancelled; Compulsory RAND licensing | E13: ='Pool Index'!G13 -> United States v. American Bosch Corp., CCH 1948-49 Trade Cases 62,284 (S.D.N.Y. Civil No. 20-164; Complaint and Consent Decree, Dec. 29, 1942).
A14: 1931Mill | B14: Milling Machines | E14: ='Pool Index'!G14 -> United States v. Cincinnati Milling Machine Co., CCH 1953-54 Trade Cases 67,733 (E.D. Mich Civil No. 13401; Complaint and Consent Judgment, April 19, 1954).
A15: 1932Phar | B15: Pharmaceuticals | C15: Price-fixing; Divided world markets | D15: Restrictive agreements cancelled; Compulsory royalty-free licensing | E15: ='Pool Index'!G15 -> United States v. Merck and Co., CCH 1944-45 Trade Cases 57,416 (D.C.N.J. Civil No. 3159; Complaint, 1943; Consent Decree, 1945).
A16: 1932Rail | B16: Railroad Springs | C16: Price-fixing; Allocating customers to specific manufacturers through bid-rigging | D16: Restrictive agreements cancelled; Ccompulsory RAND and royalty-free licensing | E16: ='Pool Index'!G16 -> United States v. American Locomotive Co., CCH 1945-47 Trade Cases ¶ 57,621 (N.D. Ind. Civil No. 545; Complaint, 1945; Consent Judgment, 1947).
A17: 1932Text | B17: Hosiery Machinery | C17: Denied sales of machinery to competitors of a pool member; Destroyed competing second-hand machinery | D17: Compulsory RAND and royalty-free licensing | E17: ='Pool Index'!G17 -> United States v. Textile Machine Works, CCH 1950-51 Trade Cases 62,709 (S.D.N.Y. Civil No. 43-671; Complaint, 1947; Fina; Judgment, 1950).
A18: 1933Hydr | B18: Hydraulic Oil Pumps | C18: Price-fixing; Denied licenses to competitors | D18: Triple damages awarded to a competitor, and alleged infringer, due to violation of Sherman Act | E18: ='Pool Index'!G18 -> Kobe, Inc. v. Dempsey Pump Co., 198 F.2d 416 (10th Cir. 1952); United States v. Kobe (N.D. Okla. Civil No. 2865; Complaint, 1951); also Civ. No. 2350.
A19: 1933Mach | B19: Machine Tools | C19: Allocated specific fields to pool members; Denied licenses to competitors | D19: None: pool dissolved by pool members due to internal litigation over the terms of their agreement | E19: ='Pool Index'!G19 -> United States v. Associated Patents, 134 F. Supp. 74 (E.D. Mich., 1955).
A20: 1933Phil | B20: Phillips Screws | C20: Price-fixing; Prevented licensees from producing competing screws | D20: Restrictive agreements cancelled; Compulsory RAND licensing | E20: ='Pool Index'!G20 -> United States v. Phillips Screw Co., 1949 Trade Cas. (C.C.H.) ¶62,394 (N.D. Ill.)
A21: 1934Colo | B21: Color Film | C21: Allocating color film production to Technicolor only | D21: Restrictive agreements cancelled; Ccompulsory RAND and royalty-free licensing | E21: ='Pool Index'!G21 -> United States v. Technicolor, Inc., CCH 1950-51 Trade Cases 2,586 (S.D. Calif. Civil No. 7507-M; Complaint, 1947; Consent Judgments, 1948 and 1950).
A22: 1934Dry | B22: Dry Ice | C22: Price-fixing; Allocated territories; Denied licenses to competitors; Conducted price wars against competitors | D22: Restrictive practices enjoined; Compulsory RAND licensing | E22: ='Pool Index'!G22 -> United States v. The Liquid Carbonic Corp., CCH Trade Cases 67,248 (E.D.N.Y. Civil No. 9179; Complaint, 1948; Final Judgment, 1952).
A23: 1934Elec | B23: Electric Generators | C23: Price-fixing; Divided world markets | D23: Restrictive agreements cancelled; Compulsory royalty-free licensing | E23: ='Pool Index'!G23 -> United States v. Westinghouse Electric Mfg. Co., CCH Current Trade Cases 67,501 (D.C.N.J. Civil No. 5152; Complaint, 1945; Consent Judgment, 1953).
A24: 1934Leci | B24: Lecithin | C24: Allocated domestic market shares; Divided world markets; Threatened competitors with litigation | D24: Restrictive agreements cancelled; Ccompulsory RAND and royalty-free licensing | E24: ='Pool Index'!G24 -> United States v. American Lecithin Co., CCH 1946-47 Trade Cases 57,542 (N.D. Ohio Civil No. 24115; Complaint, 1946; Consent Judgment, 1947).
A25: 1934Vari | B25: Variable Condensers | C25: Price-fixing; Denied licenses to competitors | D25: Dissolution of pool; Compulsory royalty-free licensing | E25: ='Pool Index'!G25 -> United States v. General Instrument Corp., 87 F. Supp. 157, 194 (D.N.J. 1949); United States v. General Instrument Corp., 115 F. Supp. 582 (D.N.J. 1953).
A26: 1935Airc | B26: Aircraft Instruments and Parts | C26: Divided world markets | D26: Restrictive agreements cancelled; Ccompulsory RAND and royalty-free licensing | E26: ='Pool Index'!G26 -> United States v. Bendix Aviation Corporation, CCH 1946-47 Trade Cases 57,444 (D.C.N.J. Civil No. 2531; Complaint, 1942, Consent Decree, 1946).
A27: 1937Male | B27: Male Hormones | E27: ='Pool Index'!G27 -> United States v. Schering Corp., CCH Trade Regulation Reports, Supp. 1941-43, 52,729 (D.C.N.J. Civil No. 1919; Complaint and Consent Decree, Dec. 17, 1941).
A28: 1937Park | B28: Parking Meters | E28: ='Pool Index'!G28 -> United States v. Vehicular Parking, 54 F. Supp. 828, 831 (D. Delaware 1944); CCH 1944-45 Trade Cases 57,226.
A29: 1937Stam | B29: Stamped Metal Wheels | C29: Price-fixing; Allocating distributors to manufacturers | D29: Restrictive practices enjoined; Compulsory RAND licensing | E29: ='Pool Index'!G29 -> United States v. Kelsey-Hayes Wheel Co. (E.D.Mich. Civil No. 10-655; Complaint, 1951).
A30: 1937Wrin | B30: Wrinkle Finishes | C30: Price-fixing | D30: Restricitve agreements cancelled; Compulsory RAND licensing | E30: ='Pool Index'!G30 -> United States v. New Wrinkle, Inc., 1955 Trade Cases (C.C.H.) ¶ 68,203 (S.D. Ohio).
A31: 1938Drop | B31: Dropout Cutouts | C31: Price-fixing | D31: Restrictive contracts cancelled; Compulsory RAND licensing | E31: ='Pool Index'!G31 -> United States v. Line Material Co., 333 U.S. 287, 305 (1948).
A32: 1938Opht | B32: Ophthalmic Frames | C32: Price-fixing; Restricting the sale of frames to certain wholesalers | D32: Restrictive agreements cancelled; Ccompulsory RAND and royalty-free licensing | E32: ='Pool Index'!G32 -> United States v. American Optical Co., CCH 1948-49 Trade Cases 62,308 (S.D.N.Y. Civil No. 10-391; Complaint, 1940; Final Consent Judgment, 1948).
A33: 1938Slip | B33: Furniture Slip Covers | C33: Price-fixing; Denied licenses to competitors unless forced to | D33: None: agreements dissolved prior to suit due to disagreement among pool members | E33: ='Pool Index'!G33 -> United States v. Krasnov, 143 F. Supp. 184 (E.D. Penn., 1956).
A34: 1942Tele | B34: Television | E34: ='Pool Index'!G34 -> United States v. Scophony Corp., CCH 1948-49 Trade Cases 62,238, 62,356, and 62,463 (S.D.N.Y. Civil No. 34-184; Complaint, 1945; Consent Decree, 1948 and 1949).
A35: 1946Dayl | B35: Daylight Fluorescent Pigments | E35: ='Pool Index'!G35 -> United States v. Switzer Brothers, Inc., Gantner & Mattern Co., The Firelure Corporation, The Sherwin-Williams Company, The Sherwin-Williams Company of California, Aberfoyle Manufacturing Company, Lawter Chemicals, Inc., Robert C. Switzer, Joseph L. Switzer, John O. Gantner, Jr., Eugene Burns, Gerald D. Stratford, and W. Bruce Beckley.
A36: 1946Elas | B36: Elastic-Top Hosiery and Machinery | E36: ='Pool Index'!G36 -> United States v. The Davis Co., CCH 1952 Trade Cases 67,403 (S.D.N.Y. Civil No. 54-357; Complaint, 1949; Consent Judgment, 1952). See also: Baker-Cammack v. Davis., 181 F.2d 550 (1950).
A37: 1948Trac | B37: Tractor Cabs | E37: ='Pool Index'!G37 -> United States v. Bearing Distributors Co., CCH 1952-53 Trade Cases 67,595 (W.D. Mo. Civil No. 6895; Complaint, 1951; Consent Decree, 1953).

Sheet Firms
A1: PoolID | B1: Firm 1 | C1: Firm 2 | D1: Firm 3 | E1: Firm 4 | F1: Firm 5 | G1: Firm 6 | H1: Firm 7 | I1: Firm 8 | J1: Firm 9 | K1: Firm 10
A2: ='Pool Index'!A2 -> 1919Equi | B2: GE/IGE | C2: Allgemeine Elektricitaets Gesellschaft | D2: Compagnie Francaise Pour l'Exploitations des Procedes Thomson-Houston (CFTH) | E2: Associated Electrical Industries (BTH a the time) | F2: Tokyo Shibaura Denki Kabushiki Kaisha | G2: Societe d'Electricite et de Mecanique | H2: Campagnia Generale di Elettricita | I2: Usines Carels Freres (Belgian firm) | J2: Franco Tosi Societa Anonima (Italian firm, acquired by Campagnia Generale di Elettricita later in 1919) | K2: French competitor of CFTH (together with CFTH and IGE organized a new company, Societe General de Constructions Electriques et Mecaniques which assumed rights of CFTH under 1919)
A3: ='Pool Index'!A3 -> 1921Cast | B3: U.S. Pipe and Foundry | C3: Centrifugal Pipe Corporation
A4: ='Pool Index'!A4 -> 1924Brak | B4: Bendix (formerly Bendix Corporation) | C4: GM | D4: Hydraulic Brake Company | F4: Wagner | G4: duPont | H4: Westinghouse
A5: ='Pool Index'!A5 -> 1924Sand | B5: American Cast Iron Pipe Company | C5: Florence Pipe Foundry and Machine Company | D5: Warren Foundry & Pipe Corporation
A6: ='Pool Index'!A6 -> 1925Vent | B6: Metal Textile Corporation | C6: Reed Air Filter Company
A7: ='Pool Index'!A7 -> 1926Food | B7: California Packing Corporation | C7: Anderson-Barngrover Manufacturing | D7: Mark Ewald | E7: Federal Pitter Company | F7: Benton Ballou Company | G7: Libby, McNeil & Libby
A8: ='Pool Index'!A8 -> 1927Airc | B8: Carrier Engineering Corporation | C8: Cooling & Air Conditioning Corporation (Sturtevant) | D8: American Blower | E8: York
A9: ='Pool Index'!A9 -> 1927Flur | B9: General Electric | C9: Westinghouse | D9: Corning Glass Works | E9: N.V. Phillips Gloeilampenfabriekan
A10: ='Pool Index'!A10 -> 1928Rail | B10: Woodings-Verona | C10: Rail Joint Company | D10: McKenna Process Company
A11: ='Pool Index'!A11 -> 1930Cabl | B11: GE | C11: General Cable Corporation | D11: Okonite-Callender Cable Company | E11: Phelps Dodge (own Phelps Dodge) | F11: Pirelli | G11: Protona
A12: ='Pool Index'!A12 -> 1930Wate | B12: Permutit Company | C12: United Water Softener | D12: Permutit Aktiengesellschaft | E12: Societe Anonyme Establishments Phillips
A13: ='Pool Index'!A13 -> 1931Fuel | B13: American Bosch Corporation | C13: Robert Bosch GMBH | D13: CAV Bosch | E13: Ateliers de Construction Lavelette
A14: ='Pool Index'!A14 -> 1931Mill | B14: Cincinnati Milling Machine Company | C14: Ingersoll | D14: Kearney
A15: ='Pool Index'!A15 -> 1932Phar | B15: Merck & Co. | C15: E. Merck
A16: ='Pool Index'!A16 -> 1932Rail | B16: American Locomotive Company | C16: Symington-Gould Corporation | D16: Universal Draft Gear Attachment Company
A17: ='Pool Index'!A17 -> 1932Text | B17: Textile Machine Works | C17: Berkshire Knitting Mills
A18: ='Pool Index'!A18 -> 1933Hydr | B18: Rodless (also held patents from Paul Yungling and Granville Knox, also secured a license under the Ira Humphreys and R. Crum patents) / Rodless Pump Company | C18: Old Kobe (President was Clarence J. Coberly)
A19: ='Pool Index'!A19 -> 1933Mach | B19: Lodge and Shipley Machine Tool Company | C19: Brown & Sharpe Manufacturing Company | D19: Lucas Machine Tool Company (became Mac Investment Company) | E19: Carlton Machine Tool Company | F19: Charles B. DeVlieg (DeVlieg Engineering Company)
A20: ='Pool Index'!A20 -> 1933Phil | B20: Henry Phillips | C20: American Screw Company
A21: ='Pool Index'!A21 -> 1934Colo | B21: Technicolor Motion Picture Corporation | C21: Eastman Kodak Company
A22: ='Pool Index'!A22 -> 1934Dry | B22: Liquid Carbonic Corporation | C22: Air Reduction Company/Pure | D22: Wyandotte Chemicals Corporation | E22: International Carbonic Engineering
A23: ='Pool Index'!A23 -> 1934Elec | B23: Siemens | C23: Westinhouse Electric & Manufacting Company
A24: ='Pool Index'!A24 -> 1934Leci | B24: Archer-Daniels-Midland | C24: Glidden Company | D24: Hansa | E24: Aarhus | F24: Ross and Rowe
A25: ='Pool Index'!A25 -> 1934Vari | B25: Radio Condenser Company | C25: General Instrument Corporation | D25: Dejur-Amsco Corporation
A26: ='Pool Index'!A26 -> 1935Airc | B26: Bendix Aviation Corporation | C26: Siemens A.M. | D26: Hakenfelde | E26: Ottico | F26: Tokyo Keiki Seisakusho | G26: Mitsui Bussan Kaishi | H26: Societe Generale des Carburateurs (Swiss firm) | I26: Zenith Carbureter Company (UK firm) | J26: Societe du Carbureteur Zenith (France) | K26: Societe Anonima Carburators Zenith (Italy) | L26: Solex Ltd (UK) | M26: Societe Anonyme Solex (French firm) | N26: Societa Anonima Carburatore Zenith (Italian firm) | O26: S. Smith & Sons | P26: Robert Bosch G.m.b.H. | Q26: Societe Anonyme Air-Equipment | R26: Joseph Lucas, Ltd (Rotax, Ltd) | S26: Northern Electric Company
A27: ='Pool Index'!A27 -> 1937Male | B27: Schering Corporation | C27: Roche-Organon | D27: Ciba Pharmaceutical Products | E27: Rare Chemicals | F27: Schering A.G. (German firm) | G27: N. V. Organon (Dutch firm)
A28: ='Pool Index'!A28 -> 1937Park | B28: Karpark (Joynt, Taylor, & Symington) | C28: Parkrite | D28: Dual
A29: ='Pool Index'!A29 -> 1937Stam | B29: Kelsey-Hayes Wheel Company | C29: The Budd Company | D29: Motor Wheel Corporation
A30: ='Pool Index'!A30 -> 1937Wrin | B30: The Kay & Ess Company / Kay & Ess Chemical Corporation | C30: Chadeloid Chemical Company
A31: ='Pool Index'!A31 -> 1938Drop | B31: Southern States Equipment Corporation | C31: Line Material Company
A32: ='Pool Index'!A32 -> 1938Opht | B32: American Optical | C32: Bausch & Lomb | D32: Ful-Vue Sales Company | E32: Uhlemann Optical
A33: ='Pool Index'!A33 -> 1938Slip | B33: Sure-Fit (Joseph A. Krasnov, Samuel Krasnov, and Seymour Krasnov) | C33: Comfy Manufacturing Company
A34: ='Pool Index'!A34 -> 1942Tele | B34: General Precision Equipment | C34: Television Productions | D34: Scophony Ltd.
A35: ='Pool Index'!A35 -> 1946Dayl | B35: Switzer Brothers | C35: Ganter & Mattern Co. | D35: Aberfoyle Manufacturing | E35: Gabbs Supply Co. | F35: Sherwin Williams | G35: Lawter Chemicals
A36: ='Pool Index'!A36 -> 1946Elas | B36: Davis & Son | C36: Scott & Williams | D36: Interwoven Stocking Company
A37: ='Pool Index'!A37 -> 1948Trac | B37: Cab-Ette Company | C37: Fort Dodge Tent and Awning Company | D37: Bearing Distributor Company

Sheet 1919Equi
A1: PoolID | B1: Listed under | C1: Patent | D1: Serial No. | E1: Application Date | F1: Application Date II | G1: Grant Date | H1: Assignee (if not, inventor name) | I1: Inventor Name | J1: Filed in country | K1: Filing date | L1: Comment
A2: 1919Equip | B2: Acquired Patents Exhibit "A" | C2: 2060672 | E2: 11340 | G2: 12002 | H2: General Electric Company | I2: Hugo Heymann | J2: Germany | K2: 11000
A3: 1919Equip | B3: Acquired Patents Exhibit "A" | C3: 2061410 | E3: 10812 | G3: 12009 | H3: General Electric Company | I3: Wilhelm Stäblein | J3: Germany | K3: 10463
A4: 1919Equip | B4: Acquired Patents Exhibit "A" | C4: 2062097 | E4: 11058 | G4: 12016 | H4: General Electric Company | I4: Herbert A. Lingard | J4: Great Britain | K4: 10702
A5: 1919Equip | B5: Acquired Patents Exhibit "A" | C5: 2064652 | E5: 11638 | G5: 12037 | H5: General Electric Company | I5: Cedric H. Flurscheim | J5: Great Britain | K5: 11297
A6: 1919Equip | B6: Acquired Patents Exhibit "A" | C6: 2068557 | E6: 11093 | G6: 12072 | H6: General Electric Company | I6: Maurice Masnou | J6: France | K6: 10738
A7: 1919Equip | B7: Acquired Patents Exhibit "A" | C7: 2068575 | E7: 11247 | G7: 12072 | H7: General Electric Company | I7: Georg Stark | J7: Germany | K7: 11016
A8: 1919Equip | B8: Acquired Patents Exhibit "A" | C8: 2070498 | E8: 11668 | G8: 12093 | H8: General Electric Company | I8: Herman Antoine Tournier | J8: France | K8: 11409
A9: 1919Equip | B9: Acquired Patents Exhibit "A" | C9: 2071176 | E9: 11715 | G9: 12100 | H9: General Electric Company | I9: Othmar Pollok | J9: Germany | K9: 11392
A10: 1919Equip | B10: Acquired Patents Exhibit "A" | C10: 2071965 | E10: 11197 | G10: 12107 | H10: General Electric Company | I10: Josef Biermanns | J10: Germany | K10: 10888
A11: 1919Equip | B11: Acquired Patents Exhibit "A" | C11: 2071967 | E11: 11917 | G11: 12107 | H11: General Electric Company | I11: Wilhelm Büngner | J11: Germany | K11: 11553
A12: 1919Equip | B12: Acquired Patents Exhibit "A" | C12: 2072733 | E12: 10211 | G12: 12114 | H12: General Electric Company | I12: Günther Dobke | J12: Germany | K12: 9854
A13: 1919Equip | B13: Acquired Patents Exhibit "A" | C13: 2075709 | E13: 10014 | G13: 12142 | H13: General Electric Company | I13: Jean Fallou | J13: France | K13: 9652
... A52: 1919Equip | B52: Acquired Patents Exhibit "A" | C52: 2095106 | E52: 12108 | G52: 12331 | H52: General Electric Company | I52: Max Stöhr | J52: Germany | K52: 11750
A53: 1919Equip | B53: Acquired Patents Exhibit "A" | C53: 2095120 | E53: 11844 | F53: (RN) 1937/7/29 | G53: 12331 | H53: General Electric Company | I53: Georges Belfils, Pierre G. Laurent | J53: France | K53: 11501
A54: 1919Equip | B54: Acquired Patents Exhibit "A" | C54: 2095132 | E54: 11750 | G54: 12331 | H54: General Electric Company | I54: Karl Hoffmann | J54: Germany | K54: 11390
A55: 1919Equip | B55: Acquired Patents Exhibit "A" | C55: 2095818 | E55: 11900 | G55: 12338 | H55: General Electric Company | I55: Tsutomu Kurokochi, Isao Miyamoto | J55: Japan | K55: 11565
A56: 1919Equip | B56: Acquired Patents Exhibit "A" | C56: 2095820 | E56: 11532 | G56: 12338 | H56: General Electric Company | I56: Walter Lenz | J56: Germany | K56: 11192
A57: 1919Equip | B57: Acquired Patents Exhibit "A" | C57: 2095821 | E57: 12156 | G57: 12338 | H57: General Electric Company | I57: Arnold Maas | J57: Germany | K57: 11799
A58: 1919Equip | B58: Acquired Patents Exhibit "A" | C58: 2096614 | E58: 11837 | G58: 12345 | H58: General Electric Company | I58: Friedrich Lehmhaus | J58: Germany | K58: 11490
A59: 1919Equip | B59: Acquired Patents Exhibit "A" | C59: 2098029 | E59: 10980 | G59: 12359 | H59: General Electric Company | I59: Herbert Dallmann | J59: Germany | K59: 10645
A60: 1919Equip | B60: Acquired Patents Exhibit "A" | C60: 2098035 | E60: 11981 | G60: 12359 | H60: General Electric Company | I60: Komao Fukushima | J60: Japan | K60: 11663
A61: 1919Equip | B61: Acquired Patents Exhibit "A" | C61: 2098064 | E61: 11196 | G61: 12359 | H61: General Electric Company | I61: Joachim Pfaffenberger | J61: Germany | K61: 10863
A62: 1919Equip | B62: Acquired Patents Exhibit "A" | C62: 2098212 | D62: (O) 111990 (Di) 139792 | E62: 12013 | F62: 12172 | G62: 12359 | H62: General Electric Company | I62: Kenneth J. R. Wilkinson | J62: Great Britain | K62: 11626
A63: 1919Equip | B63: Acquired Patents Exhibit "A" | C63: 2098804 | E63: 11870 | G63: 12366 | H63: General Electric Company | I63: Herbert Hootz | J63: Germany | K63: 11512
A64: 1919Equip | B64: Acquired Patents Exhibit "A" | C64: 2099568 | E64: 11662 | G64: 12373 | H64: General Electric Company | I64: Friedrich Metzger | J64: Germany | K64: 11306
A65: 1919Equip | B65: Acquired Patents Exhibit "A" | C65: 2099576 | E65: 11918 | G65: 12373 | H65: General Electric Company | I65: Carl Schiebeler | J65: Germany | K65: 11585
A66: 1919Equip | B66: Acquired Patents Exhibit "A" | C66: 2100833 | E66: 11735 | G66: 12387 | H66: General Electric Company | I66: Waldemar Brückel, Karl Haas | J66: Germany | K66: 11381
A67: 1919Equip | B67: Acquired Patents Exhibit "A" | C67: 2101676 | E67: 11908 | G67: 12394 | H67: General Electric Company | I67: Werner Guilhauman | J67: Germany | K67: 11584
A68: 1919Equip | B68: Acquired Patents Exhibit "A" | C68: 2102400 | E68: 11331 | G68: 12401 | H68: General Electric Company | I68: Otto Wünsche | J68: Germany | K68: 10986
A69: 1919Equip | B69: Acquired Patents Exhibit "A" | C69: 2102768 | E69: 11694 | G69: 12408 | H69: General Electric Company | I69: Henry Trencham, Harold Ernest Cox | J69: Great Britain | K69: 11329
A70: 1919Equip | B70: Acquired Patents Exhibit "A" | C70: 2104629 | E70: 12607 | G70: 12422 | H70: General Electric Company | I70: Raoul Willheim, Gerhard Frühauf | J70: Germany | K70: 11921
A71: 1919Equip | B71: Acquired Patents Exhibit "A" | C71: 2105362 | E71: 11533 | G71: 12429 | H71: General Electric Company | I71: Paul Nowak, Hermann Hofmeier | J71: Germany | K71: 11168
A72: 1919Equip | B72: Acquired Patents Exhibit "A" | C72: 2105363 | E72: 11604 | G72: 12429 | H72: General Electric Company | I72: Paul Nowak, Hermann Hofmeier | J72: Germany | K72: 11261
A73: 1919Equip | B73: Acquired Patents Exhibit "A" | C73: 2106582 | E73: 11759 | G73: 12443 | H73: General Electric Company | I73: George Wall | J73: Great Britain | K73: 11407
A74: 1919Equip | B74: Acquired Patents Exhibit "A" | C74: 2106692 | E74: 11891 | G74: 12443 | H74: General Electric Company | I74: Rowland Embleton | J74: Great Britain | K74: 11529
... A131: 1919Equip | B131: Acquired Patents Exhibit "A" | C131: 2135313 | E131: 12276 | G131: 12723 | H131: General Electric Company | I131: Ludwig Nolte | J131: Germany | K131: 11942
A132: 1919Equip | B132: Acquired Patents Exhibit "A" | C132: 2136227 | E132: 11501 | F132: (RN) 1938/5/19 | G132: 12730 | H132: General Electric Company | I132: Jean Augier, Pierre Gabriel Laurent | J132: France | K132: 11142
A133: 1919Equip | B133: Acquired Patents Exhibit "A" | C133: 2137133 | E133: 11126 | G133: 12737 | H133: General Electric Company | I133: Herbert Dallmann | J133: Germany | K133: 10771
A134: 1919Equip | B134: Acquired Patents Exhibit "A" | C134: 2137177 | E134: 12012 | G134: 12737 | H134: General Electric Company | I134: Paul Melchior | J134: Germany | K134: 11647
A135: 1919Equip | B135: Acquired Patents Exhibit "A" | C135: 2137831 | E135: 12199 | G135: 12744 | H135: General Electric Company | I135: Fritz Brunke | J135: Germany | K135: 11852
A136: 1919Equip | B136: Acquired Patents Exhibit "A" | C136: 2137877 | E136: 12103 | G136: 12744 | H136: General Electric Company | I136: Werner Krämer | J136: Germany | K136: 11830
A137: 1919Equip | B137: Acquired Patents Exhibit "A" | C137: 2137878 | E137: 12253 | G137: 12744 | H137: General Electric Company | I137: Werner Krämer | J137: Germany | K137: 11968
A138: 1919Equip | B138: Acquired Patents Exhibit "A" | C138: 2138652 | E138: 11861 | F138: (RN) 1938/3/17 | G138: 12751 | H138: General Electric Company | I138: Josef Biermanns | J138: Germany | K138: 11513
A139: 1919Equip | B139: Acquired Patents Exhibit "A" | C139: 2138658 | E139: 12290 | G139: 12751 | H139: General Electric Company | I139: Tatsuo Hongo | J139: Japan | K139: 12008
A140: 1919Equip | B140: Acquired Patents Exhibit "A" | C140: 2139494 | E140: 12356 | G140: 12758 | H140: General Electric Company | I140: William Train Gray | J140: Great Britain | K140: 11992
A141: 1919Equip | B141: Acquired Patents Exhibit "A" | C141: 2139522 | E141: 12297 | G141: 12758 | H141: General Electric Company | I141: Thomas C.R. Shepherd | J141: Great Britain | K141: 11948
A142: 1919Equip | B142: Acquired Patents Exhibit "A" | C142: 2140378 | E142: 12016 | G142: 12765 | H142: General Electric Company | I142: Josef Biermanns, Otto Mayr | J142: Germany | K142: 11661
A143: 1919Equip | B143: Acquired Patents Exhibit "A" | C143: 2140380 | E143: 12485 | G143: 12765 | H143: General Electric Company | I143: Herbert Gawehn | J143: Germany | K143: 12510
A144: 1919Equip | B144: Acquired Patents Exhibit "A" | C144: 2141316 | E144: 12036 | G144: 12779 | H144: General Electric Company | I144: Arnold Mitchell Roberts | J144: Great Britain | K144: 11695
A145: 1919Equip | B145: Acquired Patents Exhibit "A" | C145: 2141319 | E145: 11785 | G145: 12779 | H145: General Electric Company | I145: Takeo Sato | J145: Japan | K145: 11512
A146: 1919Equip | B146: Acquired Patents Exhibit "A" | C146: 2141898 | E146: 12046 | G146: 12779 | H146: General Electric Company | I146: Anton Bellm | J146: Germany | K146: 11691
A147: 1919Equip | B147: Acquired Patents Exhibit "A" | C147: 2141928 | E147: 12036 | G147: 12779 | H147: General Electric Company | I147: March Rudolph Moritz, Ian Claude | J147: Great Britain | K147: 11695
A148: 1919Equip | B148: Acquired Patents Exhibit "A" | C148: 2141929 | E148: 12036 | G148: 12779 | H148: General Electric Company | I148: March Rudolph Moritz, Ian Claude | J148: Great Britain | K148: 11695
A149: 1919Equip | B149: Acquired Patents Exhibit "A" | C149: 2141938 | E149: 12036 | G149: 12779 | H149: General Electric Company | I149: Thomas C.R. Shepherd | J149: Great Britain | K149: 11695
A150: 1919Equip | B150: Acquired Patents Exhibit "A" | C150: 2142840 | E150: 12515 | G150: 12786 | H150: General Electric Company | I150: Vitaly Grosse | J150: Germany | K150: 12233
... A152: 1919Equip | B152: Acquired Patents Exhibit "A" | C152: 2142861 | E152: 10693 | G152: 12786 | H152: General Electric Company | I152: Hans Schuhmann | J152: Germany | K152: 12202
A153: 1919Equip | B153: Acquired Patents Exhibit "A" | C153: 2143031 | E153: 11751 | F153: (RN) 1938/3/30 | G153: 12793 | H153: General Electric Company | I153: Nicolaus Rapp | J153: Germany | K153: 11388
A154: 1919Equip | B154: Acquired Patents Exhibit "A" | C154: 2144546 | E154: 12800 | G154: 12800 | H154: General Electric Company | I154: Rudolf Reese, Hans Hüttig | J154: Germany | K154: 12178
A155: 1919Equip | B155: Acquired Patents Exhibit "A" | C155: 2145182 | E155: 11947 | G155: 12807 | H155: General Electric Company | I155: Ernst Kirch | J155: Germany | K155: 11620
A156: 1919Equip | B156: Acquired Patents Exhibit "A" | C156: 2145706 | E156: 12404 | G156: 12814 | H156: General Electric Company | I156: Fritz Brann | J156: Germany | K156: 12058
A157: 1919Equip | B157: Acquired Patents Exhibit "A" | C157: 2145707 | E157: 12445 | G157: 12814 | H157: General Electric Company | I157: Josef Biermanns | J157: Germany | K157: 12066
A158: 1919Equip | B158: Acquired Patents Exhibit "A" | C158: 2145712 | E158: 11733 | G158: 12814 | H158: General Electric Company | I158: Otto Dahl, Franz Pawlek | J158: Germany | K158: 11392
A159: 1919Equip | B159: Acquired Patents Exhibit "A" | C159: 2145741 | E159: 12340 | G159: 12814 | H159: General Electric Company | I159: Wilhelm Stäblein, Raoul Willheim, Werner Uebermuth | J159: Germany | K159: 11990
A160: 1919Equip | B160: Acquired Patents Exhibit "A" | C160: 2146571 | E160: 12631 | G160: 12821 | H160: General Electric Company | I160: Wolfgang Günther | J160: Germany | K160: 12205
A161: 1919Equip | B161: Acquired Patents Exhibit "A" | C161: 2146608 | E161: 12002 | G161: 12821 | H161: General Electric Company | I161: Otto Welle | J161: Germany | K161: 11672
A162: 1919Equip | B162: Acquired Patents Exhibit "A" | C162: 2147481 | E162: 11934 | G162: 12828 | H162: General Electric Company | I162: Andrew Beetlestone, Frank Waterton | J162: Great Britain | K162: 11607
A163: 1919Equip | B163: Acquired Patents Exhibit "A" | C163: 2147484 | E163: 12108 | G163: 12828 | H163: General Electric Company | I163: Günther Dobke | J163: Germany | K163: 11845
A164: 1919Equip | B164: Acquired Patents Exhibit "A" | C164: 2148297 | E164: 12314 | G164: 12835 | H164: General Electric Company | I164: Leopold Janisch (by William A. Dodge) | J164: Germany | K164: 11950
A165: 1919Equip | B165: Acquired Patents Exhibit "A" | C165: 2148300 | E165: 11877 | G165: 12835 | H165: General Electric Company | I165: Oskar Krines | J165: Germany | K165: 11584
... A185: 1919Equip | B185: Acquired Patents Exhibit "A" | C185: 2157883 | E185: 12515 | G185: 12912 | H185: General Electric Company | I185: Rudolf Auerbach, Dahlewitz Hoppegarten, Hermann Burmeister | J185: Germany | K185: 12150
A186: 1919Equip | B186: Acquired Patents Exhibit "A" | C186: 2157906 | E186: 11861 | F186: (RN) 1935/6/24 | G186: 12912 | H186: General Electric Company | I186: Karl August Lohausen | J186: Germany | K186: 11497
A187: 1919Equip | B187: Acquired Patents Exhibit "A" | C187: 2157907 | E187: 11652 | G187: 12912 | H187: General Electric Company | I187: Karl August Lohausen | J187: Germany | K187: 11302
A188: 1919Equip | B188: Acquired Patents Exhibit "A" | C188: 2157929 | E188: 12366 | G188: 12912 | H188: General Electric Company | I188: Richard Tröger | J188: Germany | K188: 12017
A189: 1919Equip | B189: Acquired Patents Exhibit "A" | C189: 2158846 | E189: 12088 | G189: 12919 | H189: General Electric Company | I189: Georges Balachowsky | J189: France | K189: 11745
A190: 1919Equip | B190: Acquired Patents Exhibit "A" | C190: 2158859 | E190: 12381 | G190: 12919 | H190: General Electric Company | I190: Shinichiro Horikoshi | J190: Japan | K190: 12020
A191: 1919Equip | B191: Acquired Patents Exhibit "A" | C191: 2158880 | E191: 12440 | G191: 12919 | H191: General Electric Company | I191: Paul Mathews | J191: Great Britain | K191: 12270
A192: 1919Equip | B192: Acquired Patents Exhibit "A" | C192: 2159742 | E192: 11701 | G192: 12926 | H192: General Electric Company | I192: Ernst Kirch | J192: Germany | K192: 11341
A193: 1919Equip | B193: Acquired Patents Exhibit "A" | C193: 2160587 | E193: 12145 | G193: 12933 | H193: General Electric Company | I193: Martin Gieseler | J193: Germany | K193: 11893
A194: 1919Equip | B194: Acquired Patents Exhibit "A" | C194: 2160635 | E194: 12428 | G194: 12933 | H194: General Electric Company | I194: Franz Arndt, August Rausch, Wilhelm Staffel | J194: Germany | K194: 12067
A195: 1919Equip | B195: Acquired Patents Exhibit "A" | C195: 2160687 | E195: 12361 | G195: 12933 | H195: General Electric Company | I195: Albert Stubbs | J195: Great Britain | K195: 11994
A196: 1919Equip | B196: Acquired Patents Exhibit "A" | C196: 2162569 | E196: 11987 | G196: 12947 | H196: General Electric Company | I196: Kuno Bauerschmidt | J196: Germany | K196: 11633
A197: 1919Equip | B197: Acquired Patents Exhibit "A" | C197: 2163393 | E197: 12212 | G197: 12954 | H197: General Electric Company | I197: Fritz Brunke, Werner Koch | J197: Germany | K197: 11852
A198: 1919Equip | B198: Acquired Patents Exhibit "A" | C198: 2165119 | E198: 12547 | G198: 12968 | H198: General Electric Company | I198: Otto Wünsche | J198: Germany | K198: 12186
... A259: 1919Equip | B259: Acquired Patents Exhibit "A" | C259: 2195116 | E259: 12571 | G259: 13234 | H259: General Electric Company | I259: Richard Modlinger | J259: Germany | K259: 12218
A260: 1919Equip | B260: Acquired Patents Exhibit "A" | C260: 2195245 | E260: 12079 | F260: (RN) 1939/8/24 | G260: 13234 | H260: General Electric Company | I260: August Glaser, Werner Koch, Hans Neidhardt, Fritz Brunke | J260: Germany | K260: 11722
A261: 1919Equip | B261: Acquired Patents Exhibit "A" | C261: 2196034 | E261: 12851 | G261: 13241 | H261: General Electric Company | I261: Richard Schulze | J261: Germany | K261: 12501
A262: 1919Equip | B262: Acquired Patents Exhibit "A" | C262: 2196820 | E262: 12849 | G262: 13248 | H262: General Electric Company | I262: Hansheinrich Verse | J262: Germany | K262: 12129
A263: 1919Equip | B263: Acquired Patents Exhibit "A" | C263: 2196824 | E263: 11910 | G263: 13248 | H263: General Electric Company | I263: Otto Dahl, Joachim Pfaffenberger, Paul Melchior | J263: Germany | K263: 11546
A264: 1919Equip | B264: Acquired Patents Exhibit "A" | C264: 2196855 | E264: 11548 | G264: 13248 | H264: General Electric Company | I264: Walter Dietloff | J264: Germany | K264: 11247
A265: 1919Equip | B265: Acquired Patents Exhibit "A" | C265: 2196868 | E265: 12566 | G265: 13248 | H265: General Electric Company | I265: Werner Krämer | J265: Germany | K265: 12249
A266: 1919Equip | B266: Acquired Patents Exhibit "A" | C266: 2197635 | E266: 12366 | G266: 13255 | H266: General Electric Company | I266: Hermann R. Eggers | J266: Germany | K266: 12008
A267: 1919Equip | B267: Acquired Patents Exhibit "A" | C267: 2197651 | E267: 13002 | G267: 13255 | H267: General Electric Company | I267: Arthur Rosch | J267: Germany | K267: 12739
A268: 1919Equip | B268: Acquired Patents Exhibit "A" | C268: 2201829 | E268: 12759 | G268: 13290 | H268: General Electric Company | I268: Kurt Heinrich | J268: Germany | K268: 12408
A269: 1919Equip | B269: Acquired Patents Exhibit "A" | C269: 2201864 | E269: 12024 | G269: 13290 | H269: General Electric Company | I269: Friedrich Kostka | J269: Germany | K269: 11666
A270: 1919Equip | B270: Acquired Patents Exhibit "A" | C270: 2201873 | E270: 10758 | G270: 13290 | H270: General Electric Company | I270: Hansheinrich Verse | J270: Germany | K270: 12225
A271: 1919Equip | B271: Acquired Patents Exhibit "A" | C271: 2202719 | E271: 12776 | G271: 13297 | H271: General Electric Company | I271: Alfred M. Schmidt | J271: Germany | K271: 12111
A272: 1919Equip | B272: Acquired Patents Exhibit "A" | C272: 2202720 | E272: 12597 | G272: 13297 | H272: General Electric Company | I272: Walter Spielhagen | J272: Germany | K272: 12243
... A322: 1919Equip | B322: Acquired Patents Exhibit "A" | C322: 2227134 | E322: 12772 | G322: 13514 | H322: General Electric Company | I322: Ei Hara | J322: Japan | K322: 12475
A323: 1919Equip | B323: Acquired Patents Exhibit "A" | C323: 2227380 | G323: 13521 | L323: must be wrong; data do not match
...

Sheet 1921Cast
A1: PoolID | B1: Patent | C1: Type of Compulsory Licensing | D1: Application Date | E1: Grant Date | F1: Assignee (Inventor)
A2: Patents listed in Exhibit A of Final Judgment, United States v. United States Pipe and Foundry Co., CCH 1948-49 Trade Cases 62,285 (D.N.J. Civil No. 10772; Complaint, 1947; Consent Decree, 1948):
A3: 1921Cast | B3: 1833025 | C3: DP | D3: 7151 | E3: 10189 | F3: Langenberg
A4: 1921Cast | B4: 1856863 | C4: DP | D4: 9114 | E4: 10350 | F4: Clark
A5: 1921Cast | B5: 1834128 | C5: DP | D5: 9129 | E5: 10196 | F5: Langenberg
A6: 1921Cast | B6: 1856874 | C6: DP | D6: 9531 | E6: 10350 | F6: Langenberg
A7: 1921Cast | B7: 1849072 | C7: DP | D7: 9650 | E7: 10301 | F7: Clark
A8: 1921Cast | B8: 1856890 | C8: DP | D8: 9828 | E8: 10350 | F8: Stokes
A9: 1921Cast | B9: 1845127 | C9: DP | D9: 9839 | E9: 10273 | F9: Clark
A10: 1921Cast | B10: 1897631 | C10: DP | D10: 9990 | E10: 10637 | F10: Clark
A11: 1921Cast | B11: 1899383 | C11: DP | D11: 9990 | E11: 10651 | F11: Clark
A12: 1921Cast | B12: 1890498 | C12: DP | D12: 10014 | E12: 10574 | F12: Daniel
A13: 1921Cast | B13: 1903220 | C13: DP | D13: 10190 | E13: 10679 | F13: Lemert
A14: 1921Cast | B14: 1953180 | C14: DP | D14: 10459 | E14: 11050 | F14: Langenberg
... A49: 1921Cast | B49: 2346861 | C49: DP | D49: 14402 | E49: 14718 | F49: Montgomery
A51: 1921Cast | B51: SN585467 | F51: Koch
A52: 1921Cast | B52: SN729219 | F52: Koch
A53: 1921Cast | B53: SN22375 | F53: Kurtz
A55: Notes
A56: Vaughan (pp. 123-24): "U.S. Pipe and Foundry, founded in 1899 as a consolidation of the old Addyston Pipe and Steel Company and other companies, became in 1931 the exclusive licensee in the United States for the centrifugal method of making cast-iron pipes. Between 1922 and 1946, it entered into lease-license agreements with four other companies under which it leased machines for producing centrifugal pipe and granted licenses to use the patents covering them...A consent decree in 1948 required the discontinuance of these restrictions, the transfer of title to pipe-manufacturing machines, and the dedication of fifty patents to the public."
A58: Firms: U.S. Pipe and Foundry, Centrifugal Pipe Corporation, International DeLavaud Manufacturing Corporation (wholly-owned subsidiary of Centrifugal), .
A59: Foreign firms: Yes
A60: Start year: 1921
A61: End year: 1948
A62: Grantbacks: Yes
A63: Independent licensing:
A64: Open licensing:
A65: Number of licensees: 4
A66: Compulsory licensing: DP
A67: Patent holding company: No
... A78: Licensees (though they were obliged to contribute patents):
A79: James B. Clow and Sons (National Cast Iron Pipe Company was acquired by Chow in 1929) | B79: 1922
A80: Lynchburg Foundry Company | B80: 1930
A81: Glamorgan Pipe and Foundry Company | B81: 1944
A82: McWane Cast Iron Pipe Company | B82: 1946
A84: Licensing restrictions
A85: Yes, see above: "each agreement involved the licensee assigning to U.S. Pipe all patents acquired by, not to manufacture any kind of pipe other than cast iron pipe."

Sheet 1924Brak
A1: PoolID | B1: Patent | C1: Type of Compulsory Licensing | D1: Serial No. | E1: Application Date | F1: Grant Date | G1: Assignee (if not, inventor name) | H1: Inventor Name
A2: These patents are listed in Schedule A of the Final Judgment, reasonable royalties:
A3: 1924Brak | B3: 1801818 | C3: RF | E3: 8268 | F3: 9972 | G3: The Westinghouse Air Brake Company | H3: Andrew C. Mathieson
A4: 1924Brak | B4: 1805655 | C4: RF | E4: 8457 | F4: 10000 | G4: The Westinghouse Air Brake Company | H4: Sidney G. Down
A5: 1924Brak | B5: 1879719 | C5: RF | E5: 8655 | F5: 10497 | G5: The Westinghouse Air Brake Company | H5: Carlton D. Stewart
A6: 1924Brak | B6: 1797395 | C6: RF | E6: 8681 | F6: 9944 | G6: The Westinghouse Air Brake Company | H6: Eugene L. Beecher
A7: 1924Brak | B7: 1895456 | C7: RF | E7: 8811 | F7: 10623 | G7: The Westinghouse Air Brake Company | H7: Clyde C. Farmer
A8: 1924Brak | B8: 1801823 | C8: RF | E8: 8839 | F8: 9972 | G8: The Westinghouse Air Brake Company | H8: Frank B. Thomas
A9: 1924Brak | B9: 1797431 | C9: RF | E9: 8846 | F9: 9944 | G9: The Westinghouse Air Brake Company | H9: Andrew C. Mathieson
A10: 1924Brak | B10: 1824062 | C10: RF | E10: 8980 | F10: 10126 | G10: The Westinghouse Air Brake Company | H10: Harry J. Winter
A11: 1924Brak | B11: 1786195 | C11: RF | E11: 9070 | F11: 9853 | G11: The Westinghouse Air Brake Company | H11: Jules Marie Joseph Dormoy
A12: 1924Brak | B12: 1887583 | C12: RF | E12: 9083 | F12: 10546 | G12: The Westinghouse Air Brake Company | H12: Sidney G. Down
A13: 1924Brak | B13: 1816076 | C13: RF | E13: 9141 | F13: 10070 | G13: The Westinghouse Air Brake Company | H13: Sidney G. Down
A14: 1924Brak | B14: 1824034 | C14: RF | E14: 9196 | F14: 10126 | G14: The Westinghouse Air Brake Company | H14: William M. Cady
... A34: 1924Brak | B34: 2426063 | C34: RF | E34: 14053 | F34: 15936 | G34: The Westinghouse Air Brake Company | H34: Roy R. Stevens
A35: 1924Brak | B35: 2426064 | C35: RF | D35: (O) 448167 (Di) 492987 | E35: 14053 | F35: 15936 | G35: The Westinghouse Air Brake Company | H35: Roy R. Stevens
A36: 1924Brak | B36: 2358643 | C36: RF | E36: 14090 | F36: 14872 | G36: The Westinghouse Air Brake Company | H36: Cecil S. Kelley
A37: 1924Brak | B37: 2366020 | C37: RF | D37: (O) 452950 (Di) 485115 | E37: 14090 | F37: 14970 | G37: The Westinghouse Air Brake Company | H37: John N. Good
A38: 1924Brak | B38: 2395180 | C38: RF | D38: (O) 452950 (Di) 512007 | E38: 14090 | F38: 15390 | G38: The Westinghouse Air Brake Company | H38: John N. Good
A39: 1924Brak | B39: 2407877 | C39: RF | E39: 14090 | F39: 15600 | G39: The Westinghouse Air Brake Company | H39: John N. Good
A40: 1924Brak | B40: 2355758 | C40: RF | D40: (O) 463892 (Di) 504702 | E40: 14181 | F40: 14837 | G40: The Westinghouse Air Brake Company | H40: Roy R. Stevens
A41: 1924Brak | B41: 2383278 | C41: RF | E41: 14181 | F41: 15208 | G41: The Westinghouse Air Brake Company | H41: Roy R. Stevens
A42: 1924Brak | B42: 2396448 | C42: RF | D42: (O) 463792 - 2383278(Di) 504701 | E42: 14181 | F42: 15411 | G42: The Westinghouse Air Brake Company | H42: Roy R. Stevens
A43: 1924Brak | B43: 2389058 | C43: RF | D43: (O) 463915 (Di) 580258 | E43: 14182 | F43: 15292 | G43: The Westinghouse Air Brake Company | H43: Cecil S. Kelley
A44: 1924Brak | B44: 2411732 | C44: RF | E44: 14182 | F44: 15670 | G44: The Westinghouse Air Brake Company | H44: Cecil S. Kelley
A45: 1924Brak | B45: 2402400 | C45: RF | E45: 14244 | F45: 15509 | G45: The Westinghouse Air Brake Company | H45: Ellis E. Hewitt, Robert E. Watson
A46: 1924Brak | B46: 2418129 | C46: RF | E46: 14244 | F46: 15796 | G46: The Westinghouse Air Brake Company | H46: Arthur G. Larson
A47: 1924Brak | B47: 2388357 | C47: RF | E47: 14273 | F47: 15285 | G47: The Westinghouse Air Brake Company | H47: Ellis E. Hewitt
A48: 1924Brak | B48: 2343661 | C48: RF | E48: 14334 | F48: 14676 | G48: The Westinghouse Air Brake Company | H48: William H. Glass
A49: 1924Brak | B49: 2381222 | C49: RF | D49: (O) 485114 (Di) 523656 | E49: 14364 | F49: 15194 | G49: The Westinghouse Air Brake Company | H49: Harry C. May
A50: 1924Brak | B50: 2438410 | C50: RF | E50: 14364 | F50: 16153 | G50: The Westinghouse Air Brake Company | H50: Harry C. May, East McKeesport
A51: 1924Brak | B51: 2382899 | C51: RF | D51: 485116 | E51: 14364 | F51: 15201 | G51: Universal Oil Products Company | H51: Robert J. Newman
A52: 1924Brak | B52: 2406264 | C52: RF | E52: 14386 | F52: 15572 | G52: The Westinghouse Air Brake Company | H52: Roy R. Stevens
A53: 1924Brak | B53: 2457610 | C53: RF | D53: 488040 | E53: 14386 | F53: 16433 | G53: The Westinghouse Air Brake Company | H53: Roy R. Stevens
A54: 1924Brak | B54: 2428457 | C54: RF | E54: 14425 | F54: 15985 | G54: The Westinghouse Air Brake Company | H54: Claude M. Hines
A55: 1924Brak | B55: 2402419 | C55: RF | E55: 14475 | F55: 15509 | G55: The Westinghouse Air Brake Company | H55: Arthur G. Larson
A56: 1924Brak | B56: 2398903 | C56: RF | D56: (O) 500630 (Di) 544584 | E56: 14487 | F56: 15453 | G56: The Westinghouse Air Brake Company | H56: Arthur G. Larson
A57: 1924Brak | B57: 2398903 | C57: RF | D57: (O) 500630 (Di) 544584 | E57: 14487 | F57: 15453 | G57: The Westinghouse Air Brake Company | H57: Arthur G. Larson
A58: 1924Brak | B58: 2454509 | C58: RF | E58: 14490 | F58: 16398 | G58: The Westinghouse Air Brake Company | H58: Ellis E. Hewitt
A59: 1924Brak | B59: 2482274 | C59: RF | D59: (O) 541218 - 2454509 (Di) 541218 | E59: 14490 | F59: 16699 | G59: The Westinghouse Air Brake Company | H59: Ellis E. Hewitt, Arthur G. Larson
A60: 1924Brak | B60: 2379306 | C60: RF | E60: 14501 | F60: 15152 | G60: The Westinghouse Air Brake Company | H60: Arthur G. Larson, Cecil S. Kelley
A61: 1924Brak | B61: 2376490 | C61: RF | E61: 14601 | F61: 15117 | G61: The Westinghouse Air Brake Company | H61: Cecil S. Kelley
A62: 1924Brak | B62: 2395202 | C62: RF | E62: 14638 | F62: 15390 | G62: The Westinghouse Air Brake Company | H62: Roy R. Stevens
A63: 1924Brak | B63: 2433916 | C63: RF | D63: (O) 521798 (Di) 570103 | E63: 14650 | F63: 16076 | G63: The Westinghouse Air Brake Company | H63: Harry C. May, East McKeesport, Roy R. Stevens
A64: 1924Brak | B64: 2433916 | C64: RF | D64: (O) 521798 (Di) 570103 | E64: 14650 | F64: 16076 | G64: The Westinghouse Air Brake Company | H64: Harry C. May, Roy R. Stevens
A65: 1924Brak | B65: 2418037 | C65: RF | D65: (O) 528691 (Di) 580223 | E65: 14699 | F65: 15789 | G65: The Westinghouse Air Brake Company | H65: Arthur G. Larson
A66: 1924Brak | B66: 2431759 | C66: RF | E66: 14699 | F66: 16041 | G66: The Westinghouse Air Brake Company | H66: Arthur G. Larson
A67: 1924Brak | B67: 2404545 | C67: RF | D67: (O) 533145 (Di) 589640 | E67: 14728 | F67: 15544 | G67: The Westinghouse Air Brake Company | H67: Roy R. Stevens
A68: 1924Brak | B68: 2444273 | C68: RF | E68: 14728 | F68: 16251 | G68: The Westinghouse Air Brake Company | H68: Roy R. Stevens
A69: 1924Brak | B69: 2404545 | C69: RF | D69: (O) 533145 (Di) 589640 | E69: 14728 | F69: 15544 | G69: The Westinghouse Air Brake Company | H69: Roy R. Stevens
A70: 1924Brak | B70: 2413390 | C70: RF | E70: 14761 | F70: 15705 | G70: The Westinghouse Air Brake Company | H70: Roy R. Stevens
A71: 1924Brak | B71: 2477836 | C71: RF | D71: 551804 | E71: 14852 | F71: 16650 | G71: The Westinghouse Air Brake Company | H71: Roy R. Stevens
A72: 1924Brak | B72: 2464986 | C72: RF | D72: 565913 | E72: 14944 | F72: 16517 | G72: The Westinghouse Air Brake Company | H72: Raymond E. Miller
A73: 1924Brak | B73: 2580372 | C73: RF | D73: 596765 | E73: 15125 | F73: 17525 | G73: The Westinghouse Air Brake Company | H73: Ralph T. Whitney
A74: 1924Brak | B74: 2550931 | C74: RF | D74: 602290 | E74: 15155 | F74: 17287 | G74: The Westinghouse Air Brake Company | H74: Harry M. Linhart
A75: 1924Brak | B75: 2540765 | C75: RF | D75: 613628 | E75: 15217 | F75: 17203 | G75: The Westinghouse Air Brake Company | H75: Roy R. Stevens
A76: 1924Brak | B76: 2438427 | C76: RF | E76: 15328 | F76: 16153 | G76: The Westinghouse Air Brake Company | H76: Ralph T. Whitney
A77: 1924Brak | B77: 2524487 | C77: RF | D77: 669723 | E77: 15474 | F77: 17077 | G77: The Westinghouse Air Brake Company | H77: Roy R. Stevens
A79: 1924Brak | C79: RF | D79: 494612 | E79: 14439
A80: 1924Brak | C80: RF | D80: 570104 | E80: 14972
A82: Notes
A83: Vaughan (pp. 96-97): "There was a shift, mostly during the thirties, from mechanical to hydraulic brakes for automotive passenger vehicles. The manufacture and sale of braking systems was carried out by seven companies - Bendix Aviation, Genereal Motors, Hydraulic Brake, Wagner Electric, Du Pont, Bendix-Westinghouse, and Westinghouse-and the allegations of a 1947 government complaint indicate the concentration of patents in this field...a district court in a final judgment against Westinghouse in 1948, restricted its control over Bendix-Westinghouse, enjoined its action for infringement of any braking system prior to this date, and ordered royalty-free licenses under seventy-seven patents and patent applications and licenses at reasonable royalties under all its other braking system patents outstanding and issued or applied for within five years."
A85: Firms: Bendix Aviation Corporation, Hydraulic Brake Company, Wagner Electric Corporation, E. I. duPont de Nemours & Company, General Motors Corporation (owns 20% of Bendix voting stock), Bendix-Westinghouse Automotive Air Brake Company, Westinghouse Air Brake Company.
A86: Foreign firms: No
A87: Start year: 1924
A88: End year: 1948
A89: Grantbacks:
A90: Independent licensing:
A91: Open licensing:
A92: Number of licensees: 21+ (complaint, p. 9)
A93: Compulsory licensing: RF
A94: Patent holding company: No
... A103: Pool members (added patents):
A104: Bendix (formerly Bendix Corporation) | B104: 1929 (organized Bendix with GM)
A105: GM | B105: 1929 (organized Bendix with Bendix Corporation to take over all of the assets of Bendix Corporation and certain assets of GM including all of the latter's patents relating to mechanical braking systems)
A106: Hydraulic Brake Company | B106: 1924 (hydraulic brakes)
A107: Wagner | B107: 1924 (hydraulic brakes)
A108: Bendix | B108: 1930 (purchased substantially all the capital stock of Hydraulic Brake to expand from mechanical to hydraulic brakes)
A109: duPont | B109: 1935 (brake fluid)
A110: Bendix | B110: 1930 (purchased capital stock in Bragg-Kleisrath Coporation to enter market for vacuum boosters)
A111: Westinghouse | B111: 1930 (agreement with Bendix over air braking systems)
A113: Licensees (did not contribute patents):
A114: 21 automobile manufacturers (listed on p. 13 of Exhibit A) | B114: 1924
A115: GM | B115: 1930
A116: Ford Motor Company | B116: 1930
A117: Packard Motor Company | B117: 1930

Sheet 1924Sand
A1: PoolID | B1: Patent | C1: Type of Compulsory Licensing | D1: Application Date | E1: Grant Date | F1: Assignee (Inventor)
A2: Patents listed in United States v. Sand Spun Patents Corp., 1948-1949 Trade Cases 62,462 (D.N.J. Civil No. 125-49; Complaint, 1949; Consent Judgement, 1949):
A3: 1924Sand | B3: 1958672 | C3: DP | D3: 8921 | E3: 11092 | F3: Moore, Morgan
A4: 1924Sand | B4: 1911106 | C4: DP | D4: 9987 | E4: 10735 | F4: Camerota
A5: 1924Sand | B5: 1873227 | C5: DP | D5: 10099 | E5: 10462 | F5: Smith
A6: 1924Sand | B6: 1873176 | C6: DP | D6: 10127 | E6: 10462 | F6: Barr
A7: 1924Sand | B7: 1906511 | C7: DP | D7: 10127 | E7: 10714 | F7: Barr, Moxley, Houghton
A8: 1924Sand | B8: 1916296 | C8: DP | D8: 10127 | E8: 10777 | F8: Barr, Moxley
A9: 1924Sand | B9: 1902301 | C9: DP | D9: 10188 | E9: 10672 | F9: Camerota
A10: 1924Sand | B10: 1926034 | C10: DP | D10: 10209 | E10: 10847 | F10: Camerota
A11: 1924Sand | B11: 1959227 | C11: DP | D11: 10231 | E11: 11092 | F11: Barr, Moxley
A12: 1924Sand | B12: 1960366 | C12: DP | D12: 10231 | E12: 11106 | F12: Barr, Moxley, Cooper
A13: 1924Sand | B13: 1983431 | C13: DP | D13: 10238 | E13: 11295 | F13: Barr, Moxley
A14: 1924Sand | B14: 1912361 | C14: DP | D14: 10239 | E14: 10749 | F14: Camerota
... A21: 1924Sand | B21: 2043956 | C21: DP | D21: 11361 | E21: 11848 | F21: Camerota
A23: License not at National Archives in New York
A25: Notes
A26: Vaughan (pp. 123-24): "Sand Spun, the owner or exclusive licensee of nineteen patents concerning the centrifugal method of making pipes, granted licenses under these patents on conditions which sought to perpetuate its control of patents, production of pipe, and allocation of markets. A consent judgement of 1949 dissolved Sand Spun, enjoined the restrictive agreements, and dedicated its nineteen patents to the public."
A28: Firms: American Cast Iron Pipe Company, Florence Pipe Foundry and Machine Company, Warren Foundry & Pipe Corporation, and Sand Spun Patents (patent holding company).
A29: Foreign firms: No
A30: Start year: 1924
A31: End year: 1949
A32: Grantbacks:
A33: Independent licensing:
A34: Open licensing: No
A35: Number of licensees: 0
A36: Compulsory licensing: DP
... A44: Pool members (added patents):
A45: American Cast Iron Pipe Company | B45: 1924
A46: Florence Pipe Foundry and Machine Company | B46: 1924
A47: Warren Foundry & Pipe Corporation | B47: 1924

Sheet 1925Vent
A1: PoolID | B1: Patent | C1: Type of Compulsory Licensing | D1: Application Date | E1: Grant Date | F1: Assignee (Inventor)
A2: Patents listed in United States v. American Air Filter Co., CCH 1946-47 Trade Cases 57,492 (W.D. Ky. Civil No. 574; Complaint, 1943; Consent Judgment, 1946):
A3: Schedule A from Final Judgment:
A4: 1925Vent | B4: 1521575 | D4: 6214 | E4: 7669 | F4: Wittemeier
A5: 1925Vent | B5: 1521577 | D5: 6214 | E5: 7669 | F5: Wittemeier
A6: 1925Vent | B6: 1521578 | D6: 6214 | E6: 7669 | F6: Wittemeier
A7: 1925Vent | B7: 1632813 | D7: 6214 | E7: 8572 | F7: Wittemeier
A8: 1925Vent | B8: 1416381 | D8: 6223 | E8: 43235 | F8: Reed
A9: 1925Vent | B9: 1589803 | D9: 6449 | E9: 8208 | F9: Haring
A10: 1925Vent | B10: 1588402 | D10: 6475 | E10: 8201 | F10: Frohlich
A11: 1925Vent | B11: 1426196 | D11: 6557 | E11: 6801 | F11: Jordahl
A12: 1925Vent | B12: 1443134 | D12: 6620 | E12: 6962 | F12: Klug
A13: 1925Vent | B13: 1500128 | D13: 6664 | E13: 7494 | F13: Harrison
A14: 1925Vent | B14: 1511764 | D14: 6889 | E14: 7592 | F14: Jordahl
A15: 1925Vent | B15: 1489831 | D15: 6980 | E15: 7403 | F15: Jordahl
... A42: 1925Vent | B42: 1577703 | D42: 7960 | E42: 8117 | F42: Fedeler
A44: Schedule B from Final Judgment - patents to be dedicated to the public:
A45: 1925Vent | B45: 1743675 | C45: DP | D45: 6999 | E45: 9510 | F45: Jordahl
A46: 1925Vent | B46: 1771639 | C46: DP | D46: 7008 | E46: 9706 | F46: Jordahl
A47: 1925Vent | B47: 1807983 | C47: DP | D47: 7376 | E47: 10014 | F47: Hegan
A48: 1925Vent | B48: 1788164 | C48: DP | D48: 7472 | E48: 9867 | F48: Lederer
A49: 1925Vent | B49: 1807984 | C49: DP | D49: 7563 | E49: 10014 | F49: Hegan
A50: 1925Vent | B50: 1786208 | C50: DP | D50: 7658 | E50: 9853 | F50: Jordahl
A51: 1925Vent | B51: 1747694 | C51: DP | D51: 7759 | E51: 9545 | F51: Birkholz
A52: 1925Vent | B52: 1895642 | C52: DP | D52: 8032 | E52: 10623 | F52: Preble
A53: 1925Vent | B53: 1841536 | C53: DP | D53: 8093 | E53: 10245 | F53: Jordahl
A54: 1925Vent | B54: 1746283 | C54: DP | D54: 8097 | E54: 9538 | F54: Reed
A55: 1925Vent | B55: 1816854 | C55: DP | D55: 8161 | E55: 10077 | F55: Jordahl
A56: 1925Vent | B56: 1794115 | C56: DP | D56: 8165 | E56: 9916 | F56: Klaff
... A93: 1925Vent | B93: 2220347 | C93: DP | D93: 12512 | E93: 13458 | F93: Nutting
A94: 1925Vent | B94: 1577703 | C94: DP | D94: 7960 | E94: 8117 | F94: Fedeler | G94: Reissue 18328
A96: Schedule C from Final Judgment - reasonable royalty:
A97: 1925Vent | B97: 1708065 | C97: RR | D97: 7301 | E97: 9230 | F97: Jordahl
A98: 1925Vent | B98: 1760986 | C98: RR | D98: 7445 | E98: 9650 | F98: Jordahl
A99: 1925Vent | B99: 1788171 | C99: RR | D99: 8002 | E99: 9867 | F99: Preble
A100: 1925Vent | B100: 1821202 | C100: RR | D100: 8622 | E100: 10105 | F100: Birkholz
A101: 1925Vent | B101: 1893048 | C101: RR | D101: 8622 | E101: 10595 | F101: Birkholz
A102: 1925Vent | B102: 1886927 | C102: RR | D102: 8652 | E102: 10539 | F102: Williams
A103: 1925Vent | B103: 1843182 | C103: RR | D103: 8718 | E103: 10259 | F103: Strindberg
A104: 1925Vent | B104: 1897976 | C104: RR | D104: 8729 | E104: 10637 | F104: Birkholz
A105: 1925Vent | B105: 1789625 | C105: RR | D105: 8737 | E105: 9881 | F105: Goodloe
A106: 1925Vent | B106: 1783181 | C106: RR | D106: 8757 | E106: 9832 | F106: Birkholz
A107: 1925Vent | B107: 1926924 | C107: RR | D107: 8886 | E107: 10847 | F107: Sylvan
A108: 1925Vent | B108: 1899029 | C108: RR | D108: 8937 | E108: 10651 | F108: Gagen
... A124: 1925Vent | B124: 2335144 | C124: RR | D124: 13944 | E124: 14571 | F124: Dahlman
A125: 1925Vent | B125: 2415579 | C125: RR | D125: 14707 | E125: 15747 | F125: Dahlman | G125: SN 529,977
A126: 1925Vent | B126: 2405293 | C126: RR | D126: 14707 | E126: 15558 | F126: Dahlman | G126: SN 529,978
A128: From Schedule B:
A129: 1925Vent | B129: SN442,742 | E129: 14012
A132: Notes
A133: Vaughan (pp. 92-93): "In 1925, two companies created the American Air Filter Company, assigning it their patents and receiving licenses in return…A consent decreee of September, 1946, required American Air Filter and another company to dedicate fifty-one air-filter patents to the public and to license thirty additional patents at reasonable royalties."
A135: Firms: Metal Textile Corporation, Reed Air Filter Company, American Air Filter Company (patent holding company).
A136: Foreign firms: No
A137: Start year: 1925
A138: End year: 1946 (consent decree)
A139: Grantbacks:
A140: Independent licensing:
A141: Open licensing:
A142: Number of licensees: 4 (American Air Filter granted other companies, particularly after unsuccessful attempts to purchase them, licenses with restrictions as to types of filter, price, territory, and purchase of mesh and other supplies)
A143: Compulsory licensing: DP, RR
A144: Patent holding company: Yes (American Air Filter Company)
... A153: Pool members (added patents):
A154: Metal Textile Corporation | B154: 1925
A155: Reed Air Filter Company | B155: 1925
A157: Companies acquired by patent holding company:
A158: General Air Filters Corp. | B158: 1929
A159: Drying Systems Inc. | B159: 1929
A160: Spraco | B160: 1929
A161: Spray Engineering Company | B161: 1929
A162: American Air Filtration Corporation | B162: 1929
A163: Hines Air Filter | B163: 1930
A164: National Air Filter Company | B164: 1930
A165: Holland Furnace Company | B165: 1931
A166: Fred Kling | B166: 1932
A167: Freyn Engineering Company | B167: 1932
A168: Kimberly-Clark Corporation | B168: 1933
A169: Richtor | B169: 1934
... A174: Kurly Kate Filters | B174: 1940
A176: Licensees (did not add patents):
A177: Independent Air Filter Co. | B177: 1933
A178: B. V. Vinson Company | B178: 1934
A179: Owens-Illinois Glass Company | B179: 1935
A180: Staynew Filter Corporation | B180: 1936

Sheet 1926Food
A1: PoolID | B1: Patent | C1: Type of Compulsory Licensing | D1: Application Date | E1: Grant Date | F1: Assignee (Inventor)
A2: These patents were obtained from Google patent search for "Pacific Machinery Company" in assignees, and the word "pitter". Included patents issued on or after 1940. No patents with word "pitter" issued to Food Machinery and Chemical Company.
A3: 1926Food | B3: 2192444 | C3: RR | D3: 11575 | E3: 13213 | F3: Pacific Machinery Company
A4: 1926Food | B4: 2309321 | C4: RR | D4: 12583 | E4: 14270 | F4: Pacific Machinery Company
A5: 1926Food | B5: 2226664 | C5: RR | D5: 12731 | E5: 13514 | F5: Pacific Machinery Company
A6: 1926Food | B6: 2324470 | C6: RR | D6: 13745 | E6: 14445 | F6: Pacific Machinery Company
A7: 1926Food | B7: 2380530 | C7: RR | D7: 14374 | E7: 15187 | F7: Pacific Machinery Company
A8: 1926Food | B8: 2581785 | C8: RR | D8: 15607 | E8: 17539 | F8: Pacific Machinery Company
A9: 1926Food | B9: 2569331 | C9: RR | D9: 15886 | E9: 17434 | F9: Pacific Machinery Company
A11: Notes
A12: Vaughan (p. 61): "Four companies pooled and purchased competing patents on peach-pitting machinery, issued restrictive licenses, acquired competitive machinery, and thus monopolized and restrained trade in the manufacture and use of such machinery."
A15: Firms: California Packing Corporation, Anderson-Barngrover Manufacturing (acquired by Food Machinery and Chemical Corporation), Pacific Machinery (patent holding company), Mark Ewald, Federal Pitter Company, Benton Ballou Company, and Libby, McNeil & Libby.
A16: Foreign firms: No
A17: Start year: 1926
A18: End year: 1954 (consent decree, final judgment)
A19: Grantbacks:
A20: Independent licensing:
A21: Open licensing: No (complaint, p. 8)
A22: Number of licensees: 0
A23: Compulsory licensing: Yes, RR
A24: Patent holding company: Yes (Pacific Machinery)
A25: Technology: | B25: Peach canners maintain processing and canning establishments, known as caneries. The peaches processed and canned in the said canneries are sold, shopping, and transported to purchasers. The use of peach pitters is essential to the successful operation of a peach cannery. Peach pitters extract the pits or stones from fresh peaches prior to their being canned.
A26: Google search: "peach pitter"
A28: Notes from complaint:
A29: Three types of patents on peach pitting machinery (Duncan, Dunkley, and Thompson). Thompson were owned by Anderson-Barngrover. California Packing acquired the Dunkley patents in 1928 and the Duncan patents in 1928 (pages 5 and 9).
A31: Notes from judgment:
A32: Defendants Pacific and Food Machinery are each ordered and directed to grant to any applicant making written request…a nonexclusive license to manufacture, use and vend peach pitters under any, some or all United States patents owned or controlled by said defendant during the entire term of said United States patents...a reasonable nondiscriminatory royalty may be charged.
A33: Not clear about restrictive licensing: tried to obtain all the patents in the field of peach-pitting and prevent competition.
A35: Pool members (contributed patents):
A36: California Packing Corporation | B36: 1926
A37: Anderson-Barngrover Manufacturing | B37: 1926
A38: Mark Ewald | B38: 1930
A39: Federal Pitter Company | B39: 1934
A40: Benton Ballou Company | B40: 1935
A41: Libby, McNeil & Libby | B41: 1936

Sheet 1927Airc
A1: PoolID | B1: Patent | C1: Type of Compulsory Licensing | D1: Application Date | E1: Grant Date | F1: Assignee (Inventor) | G1: Primary Class A | H1: Primary Subclass | I1: Secondary Subclass 1a | J1: Secondary Subclass 2a | K1: Secondary Subclass 3a | L1: Secondary Subclass 4a | M1: Secondary Subclass 5a | N1: Secondary Subclass 6a | O1: Secondary Subclass 7a | P1: Secondary Subclass 8a | Q1: Secondary Subclass 9a | R1: Secondary Subclass 10a | S1: Secondary Class B | T1: Secondary Subclass 1b | U1: Secondary Subclass 2b | V1: Secondary Subclass 3b | W1: Secondary Subclass 4b | X1: Secondary Subclass 5b | Y1: Secondary Subclass 6b | Z1: Secondary Class C | AA1: Secondary Subclass 1c | AB1: Secondary Subclass 2c | AC1: Secondary Subclass 3c | AD1: Secondary Subclass 4c | AE1: Secondary Subclass 5c | AF1: Secondary Subclass 6c | AG1: Secondary Subclass 7c | AH1: Secondary Class D | AI1: Secondary Subclass 1d | AJ1: Secondary Subclass 2d | AK1: Secondary Subclass 3d | AL1: Secondary Subclass 4d | AM1: Secondary Subclass 5d | AN1: Secondary Subclass 6d | AO1: Secondary Subclass 7d | AP1: Secondary Subclass 8d | AQ1: Secondary Class E | AR1: Secondary Subclass 1e | AS1: Secondary Subclass 2e | AT1: Secondary Class F | AU1: Secondary Subclass 1f | AV1: Secondary Subclass 2f | AW1: Secondary Subclass 3f
A2: Patents listed in Schedule A of Final Judgment, to be dedicated to the public:
A3: 1927Airc | B3: 1718815 | C3: DP | D3: 8391 | E3: 9307 | F3: Auditorium Ventillating Corp.
A4: 1927Airc | B4: 1977315 | C4: DP | D4: 8518 | E4: 11246 | F4: Auditorium Ventillating Corp.
A5: 1927Airc | B5: 1670656 | C5: DP | D5: 8540 | E5: 11932 | F5: Auditorium Conditioning Corp. | G5: RE 20088
A6: 1927Airc | B6: 1737661 | C6: DP | D6: 8572 | E6: 9468 | F6: Auditorium Ventillating Corp.
A7: 1927Airc | B7: 1817384 | C7: DP | D7: 8614 | E7: 10077 | F7: Auditorium Ventillating Corp.
A8: 1927Airc | B8: 1840565 | C8: DP | D8: 8614 | E8: 10238 | F8: Auditorium Ventillating Corp.
A9: 1927Airc | B9: 1819643 | C9: DP | D9: 8734 | E9: 10728 | F9: Cooling and Air Conditioning Corp. | G9: RE 18831
A10: 1927Airc | B10: 1751805 | C10: DP | D10: 8778 | E10: 9580 | F10: Auditorium Ventillating Corp.
A11: 1927Airc | B11: 1751806 | C11: DP | D11: 8804 | E11: 9580 | F11: Cooling and Air Conditioning Corp.
A12: 1927Airc | B12: 1902563 | C12: DP | D12: 8819 | E12: 10672 | F12: Carrier Engineering Corp.
A13: 1927Airc | B13: 1749763 | C13: DP | D13: 8986 | E13: 9930 | F13: Cooling and Air Conditioning Corp. | G13: RE 17998
A14: 1927Airc | B14: 1878618 | C14: DP | D14: 9408 | E14: 12765 | F14: Auditorium Conditioning Corp. | G14: RE 20944
A15: 1927Airc | B15: 1863576 | C15: DP | D15: 9457 | E15: 10399 | F15: American Blower Corp.
A16: 1927Airc | B16: 1863577 | C16: DP | D16: 9457 | E16: 10399 | F16: American Blower Corp.
A17: 1927Airc | B17: 1863578 | C17: DP | D17: 9457 | E17: 10399 | F17: American Blower Corp.
A18: 1927Airc | B18: 1863579 | C18: DP | D18: 9457 | E18: 10399 | F18: American Blower Corp.
A19: 1927Airc | B19: 2112685 | C19: DP | D19: 9533 | E19: 12506 | F19: Auditorium Conditioning Corp.
A20: 1927Airc | B20: 2110164 | C20: DP | D20: 9772 | E20: 12485 | F20: McDonald
A21: 1927Airc | B21: 1846875 | C21: DP | D21: 9924 | E21: 10280 | F21: Audifren Refrigerating Machine Co.
A22: 1927Airc | B22: 1904468 | C22: DP | D22: 9958 | E22: 11918 | F22: Auditorium Conditioning Corp. | G22: RE 20069
A23: 1927Airc | B23: 1895444 | C23: DP | D23: 9999 | E23: 10623 | F23: American Blower Corp.
A24: 1927Airc | B24: 1983023 | C24: DP | D24: 10240 | E24: 11295 | F24: Auditorium Ventillating Corp.
A25: 1927Airc | B25: 2110203 | C25: DP | D25: 10324 | E25: 12485 | F25: Auditorium Conditioning Corp.
A26: 1927Airc | B26: 2131725 | C26: DP | D26: 10504 | E26: 12695 | F26: Auditorium Conditioning Corp.
A27: 1927Airc | B27: 1955406 | C27: DP | D27: 10576 | E27: 11064 | F27: Auditorium Ventillating Corp.
A28: 1927Airc | B28: 2009529 | C28: DP | D28: 10616 | E28: 11533 | F28: Auditorium Conditioning Corp.
A29: 1927Airc | B29: 1956707 | C29: DP | D29: 10753 | E29: 13836 | F29: Auditorium Conditioning Corp. | G29: RE 21946
A30: 1927Airc | B30: 2249856 | C30: DP | D30: 10945 | E30: 13717 | F30: Auditorium Conditioning Corp.
A31: 1927Airc | B31: 2202946 | C31: DP | D31: 11430 | E31: 13304 | F31: Carrier
A32: 1927Airc | B32: 2150505 | C32: DP | D32: 11431 | E32: 12856 | F32: Auditorium Conditioning Corp.
A33: 1927Airc | B33: 2105692 | C33: DP | D33: 11459 | E33: 12436 | F33: Auditorium Conditioning Corp.
A34: 1927Airc | B34: 2213350 | C34: DP | D34: 12550 | E34: 13395 | F34: Auditorium Conditioning Corp.
A35: 1927Airc | B35: 2259780 | C35: DP | D35: 12745 | E35: 13808 | F35: Auditorium Conditioning Corp.
A38: Notes
A39: Vaughan (pp. 56): "The Auditorium Conditioning Corporation was organized as a patent-holding company by two leading manufacturers of such equipment. Other companies became licensees upon payment of fees and royalties, and one of them also assigned an air-conditioning patent. In addition, Auditorium purchased numerous patents from others until it had at least 40 by 1943. A consent decree in 1945 dissolved the patent-holding company, prohibited price fixing and price discrimination, forbade suits for patent infringement or enforcement of license agreements, and dedicated the patents involved to the public."
A43: Firms: Carrier Engineering Corporation, Cooling & Air Conditioning Corporation, American Blower Corporation, and York Ice Machinery Corporation, Auditorium Conditioning Corporation (patent holding company).
A44: Foreign firms: No
A45: Start year: 1927
A46: End year: 1945 (consent decree)
A47: Grantbacks: Yes (by the further terms of the agreements referred to…both Carrier Engineering Corporation and Cooling & Air Conditioning Corporation agreed to assign all future air conditioning patents)
A48: Independent licensing:
A49: Open licensing:
A50: Number of licensees: 7
A51: Compulsory licensing: DP
A52: Patent holding company: Yes (Auditorium Conditioning Corporation)
... A60: Pool members (added patents):
A61: Carrier Engineering Corporation | B61: 1927
A62: Cooling & Air Conditioning Corporation (Sturtevant) | B62: 1927
A63: American Blower | B63: 1933
A64: York | B64: 1933
A67: Licensees (did not add patents):
A68: Ross Industries | B68: 1933
A69: Frick Company | B69: 1936
A70: Westinghouse Electric & Mfg. Co. | B70: 1937
A71: Buffalo Forge Company | B71: 1938
A72: Clarage Fan Company | B72: 1938
A73: The Trane Company | B73: 1940
A74: U.S. Air Conditioning Company | B74: 1943

Sheet 1927Flur
A1: PoolID | B1: Listed under | C1: Patent | D1: Serial No. | E1: Application Date | F1: Application Date II | G1: Grant Date | H1: Assignee (if not, inventor name) | I1: Inventor Name | J1: Filed in country | K1: Filing date | L1: Comment
A2: 1921Flur | B2: Schedule A | C2: 1197705 | E2: 3401 | G2: 4638 | H2: General Electric Company | I2: Roy Winne
A3: 1921Flur | B3: Schedule A | C3: 1201738 | E3: 3679 | G3: 4673 | H3: General Electric Company | I3: John W. Janvier
A4: 1921Flur | B4: Schedule A | C4: 1203343 | E4: 4085 | G4: 4687 | H4: General Electric Company | I4: Dale C. Hughes
A5: 1921Flur | B5: Schedule A | C5: 1205002 | E5: 2852 | G5: 4701 | H5: General Electric Company | I5: John T. Marshall, by executrix Eliza T. Marshall
A6: 1921Flur | B6: Schedule A | C6: 1206333 | E6: 3717 | G6: 4715 | H6: Cooper Hewitt Electric Company | I6: Frederick G. Keyes
A7: 1921Flur | B7: Schedule A | C7: 1206686 | E7: 3115 | G7: 4715 | H7: General Electric Company | I7: John T. Fagan
A8: 1921Flur | B8: Schedule A | C8: 1210620 | E8: 3988 | G8: 4750 | H8: General Electric Company | I8: John T. Fagan
A9: 1921Flur | B9: Schedule A | C9: 1212793 | E9: 3384 | G9: 4764 | H9: General Electric Company | I9: Fred C. March
A10: 1921Flur | B10: Schedule A | C10: 1213852 | E10: 3860 | G10: 4778 | H10: General Electric Company | I10: John T. Fagan, Cleveland H. Quackenbush
A11: 1921Flur | B11: Schedule A | C11: 1213975 | D11: (O) 35768 (Di) 79001 | E11: 4191 | F11: 4430 | G11: 4778 | H11: General Electric Company | I11: John B. Taylor
A12: 1921Flur | B12: Schedule A | C12: 1223958 | E12: 3198 | G12: 4862 | H12: General Electric Company | I12: Emil Geisel
A13: 1921Flur | B13: Schedule A | C13: 1227659 | E13: 4085 | G13: 4897 | H13: General Electric Company | I13: Cleveland H. Quackenbush, James C. Smedley
A14: 1921Flur | B14: Schedule A | C14: 1229474 | E14: 3156 | G14: 4911 | H14: James M. Richardson | I14: Harrie B. Kenyon
A15: 1921Flur | B15: Schedule A | C15: 1229538 | E15: 3394 | G15: 4911 | H15: James M. Richardson | I15: Harvey H. Slater
A16: 1921Flur | B16: Schedule A | C16: 1230869 | E16: 2502 | G16: 4925 | H16: General Electric Company | I16: William D. Coolidge
A17: 1921Flur | B17: Schedule A | C17: 1231416 | E17: 4401 | G17: 4925 | H17: General Electric Company | I17: Harry H. Needham
A18: 1921Flur | B18: Schedule A | C18: 1234060 | E18: 3407 | G18: 4946 | H18: General Electric Company | I18: George M. J. Mackay
A19: 1921Flur | B19: Schedule A | C19: 1237210 | E19: 3787 | G19: 4974 | H19: General Electric Company | I19: Irving Langmuir
A20: 1921Flur | B20: Schedule A | C20: 1237611 | E20: 3694 | G20: 4981 | H20: Cooper Hewitt Electric Company | I20: Robert B. Brownlee
A21: 1921Flur | B21: Schedule A | C21: 1237653 | E21: 3680 | G21: 4981 | H21: Cooper Hewitt Electric Company | I21: Frederick G. Keyes
A22: 1921Flur | B22: Schedule A | C22: 1238575 | E22: 3438 | G22: 4988 | H22: General Electric Company | I22: Oskar Schlüter
A23: 1921Flur | B23: Schedule A | C23: 1239413 | E23: 3641 | G23: 4995 | H23: General Electric Company | I23: George M. J. Mackay
... A33: 1921Flur | B33: Schedule A | C33: 1268647 | E33: 3650 | G33: 5268 | H33: General Electric Company | I33: William Lloyd van Keuren
A34: 1921Flur | B34: Schedule A | C34: 1269510 | D34: (O) 793567 (Di) 818835 | E34: 3564 | F34: 3699 | G34: 5275 | I34: James M. Richardson
A35: 1921Flur | B35: Schedule A | C35: 1269520 | E35: 4491 | G35: 5275 | H35: General Electric Company | I35: Fritz Blau
A36: 1921Flur | B36: Schedule A | C36: 1270843 | E36: 3829 | G36: 5296 | H36: Cooper Hewitt Electric Company | I36: Frederick G. Keyes
A37: 1921Flur | B37: Schedule A | C37: 1270856 | E37: 3830 | G37: 5296 | H37: Cooper Hewitt Electric Company | I37: Roy D. Mailey
A38: 1921Flur | B38: Schedule A | C38: 1271483 | D38: (O) 789165 (Di) 154608 | E38: 3534 | F38: 4820 | G38: 5296 | H38: General Electric Company | I38: Irving Langmuir
A39: 1921Flur | B39: Schedule A | C39: 1273629 | E39: 3991 | G39: 5317 | H39: General Electric Company | I39: Irving Langmuir
A40: 1921Flur | B40: Schedule A | C40: 1273758 | E40: 4285 | G40: 5317 | H40: General Electric Company | I40: Colin G. Fink, Walter F. Koerner
A41: 1921Flur | B41: Schedule A | C41: 1275926 | E41: 4334 | G41: 5338 | H41: General Electric Company | I41: Dale C. Hughes
A42: 1921Flur | B42: Schedule A | C42: 1284648 | E42: 4197 | G42: 5429 | H42: General Electric Company | I42: Frederic W. Gill
A43: 1921Flur | B43: Schedule A | C43: 1288916 | E43: 3840 | G43: 5471 | H43: General Electric Company | I43: Frederick G. Keyes
A44: 1921Flur | B44: Schedule A | C44: 1289993 | E44: 5030 | G44: 5478 | H44: General Electric Company | I44: Roy E. Winne
A45: 1921Flur | B45: Schedule A | C45: 1291209 | E45: 4542 | G45: 5492 | H45: Deutsche Gasglühlicht Aktiengesellschaft (Auergesellschaft) | I45: Franz Skaupy
A46: 1921Flur | B46: Schedule A | C46: 1292482 | E46: 3694 | G46: 5506 | H46: Cooper Hewitt Electric Company | I46: Frederick G. Keyes
A47: 1921Flur | B47: Schedule A | C47: 1293441 | E47: 5117 | G47: 5513 | H47: Western Electric Company | I47: William G. Houskeeper
A48: 1921Flur | B48: Schedule A | C48: 1297879 | E48: 4850 | G48: 5555 | H48: General Electric Company | I48: Charles F. Lorenz
A49: 1921Flur | B49: Schedule A | C49: 1298533 | E49: 4513 | G49: 5562 | H49: General Electric Company | I49: James E. Marshall
A50: 1921Flur | B50: Schedule A | C50: 1298569 | E50: 4778 | G50: 5562 | H50: General Electric Company | I50: Robert Le Rossignol
A51: 1921Flur | B51: Schedule A | C51: 1301079 | E51: 5279 | G51: 5583 | H51: General Electric Company | I51: William L. Van Keuren
A52: 1921Flur | B52: Schedule A | C52: 1306259 | E52: 4399 | F52: (RN) 1919/5/2 | G52: 5639 | H52: Cooper Hewitt Electric Company | I52: Frederick G. Keyes
A53: 1921Flur | B53: Schedule A | C53: 1306643 | E53: 4919 | G53: 5639 | H53: General Electric Company | I53: Alfred Swan
A54: 1921Flur | B54: Schedule A | C54: 1306912 | D54: (O) 811003 (Di) 18674 | E54: 3660 | F54: 4109 | G54: 5646 | H54: Cooper Hewitt Electric Company | I54: Frederick G. Keyes
A55: 1921Flur | B55: Schedule A | C55: 1308907 | E55: 4306 | G55: 5667 | H55: Cooper Hewitt Electric Company | I55: Frederick G. Keyes
A56: 1921Flur | B56: Schedule A | C56: 1312513 | E56: 4512 | G56: 5702 | H56: General Electric Company | I56: Ralph L. Beach
A57: 1921Flur | B57: Schedule A | C57: 1313337 | E57: 4532 | G57: 5709 | H57: General Electric Company | I57: Erich Schingscholl
A58: 1921Flur | B58: Schedule A | C58: 1315783 | E58: 4778 | G58: 5730 | H58: General Electric Company | I58: Robert Le Rossignol
A59: 1921Flur | B59: Schedule A | C59: 1317492 | E59: 4759 | G59: 5751 | I59: Lodewijk Hamburger, Dirk Lely, Jr.
A60: 1921Flur | B60: Schedule A | C60: 1320874 | E60: 4619 | G60: 5786 | H60: General Electric Company | I60: Irving Langmuir
A61: 1921Flur | B61: Schedule A | C61: 1326121 | E61: 5275 | G61: 5835 | H61: General Electric Company | I61: William L. Van Keuren
A62: 1921Flur | B62: Schedule A | C62: 1331085 | E62: 4257 | G62: 5891 | H62: General Electric Company | I62: John H. Anderson
A63: 1921Flur | B63: Schedule A | C63: 1331937 | E63: 4250 | F63: (RN) 1919/11/29 | G63: 5898 | H63: General Electric Company | I63: Matt Luckiesh, Don A. Dewey
A64: 1921Flur | B64: Schedule A | C64: 1339998 | D64: (O) 832121 (Di) 190512 | E64: 3757 | F64: 5001 | G64: 5975 | H64: General Electric Company | I64: Daniel K. Wright
A65: 1921Flur | B65: Schedule A | C65: 1342993 | E65: 4343 | G65: 6003 | H65: General Electric Company | I65: Colin G. Fink
A66: 1921Flur | B66: Schedule A | C66: 1357724 | E66: 4763 | G66: 6150 | H66: General Electric Company | I66: John E. Randall, Leroy T. Reser
A67: 1921Flur | B67: Schedule A | C67: 1359134 | E67: 5312 | G67: 6164 | H67: Hygrade Engineering Co. Inc. | I67: Miner P. Wetmore
A68: 1921Flur | B68: Schedule A | C68: 1360152 | D68: (O) 175868 (Di) 256351 | E68: 4919 | F68: 5386 | G68: 6171 | H68: General Electric Company | I68: Alfred Swan
A69: 1921Flur | B69: Schedule A | C69: 1361652 | E69: 5963 | G69: 6185 | H69: Hygrade Engineering Co. Inc. | I69: Miner P. Wetmore
A70: 1921Flur | B70: Schedule A | C70: 1375920 | E70: 5947 | G70: 6304
A71: 1921Flur | B71: Schedule A | C71: 1386880 | E71: 5871 | G71: 6430 | H71: General Electric Company | I71: Charles F. Lorenz
A72: 1921Flur | B72: Schedule A | C72: 1393550 | E72: 4416 | G72: 6493 | H72: General Electric Company | I72: Irving Langmuir
A73: 1921Flur | B73: Schedule A | C73: 1401664 | E73: 4771 | G73: 6570 | H73: General Electric Company | I73: Ralph Beman
A74: 1921Flur | B74: Schedule A | C74: 1403727 | E74: 5549 | G74: 6591 | H74: General Electric Company | I74: William Paul Zabel, Lylburn Eugene Reakes
A75: 1921Flur | B75: Schedule A | C75: 1410499 | E75: 4799 | G75: 6654 | H75: General Electric Company | I75: Aladar Pacz
A76: 1921Flur | B76: Schedule A | C76: 1410665 | E76: 6384 | G76: 6661 | H76: Patent-Treuhand-Gesellschaft für-Elektrische Glühlampen mbH | I76: Karl Finckh
A77: 1921Flur | B77: Schedule A | C77: 1419816 | E77: 5218 | G77: 6738 | H77: General Electric Company | I77: Leon Cammen
A78: 1921Flur | B78: Schedule A | C78: 1423338 | E78: 6100 | G78: 6773 | H78: General Electric Company | I78: Clemens A. Laise
A79: 1921Flur | B79: Schedule A | C79: 1423956 | E79: 5557 | G79: 6780 | H79: General Electric Company | I79: Loris Edwin Mitchell, Arthur James White
A80: 1921Flur | B80: Schedule A | C80: 1424067 | E80: 5923 | G80: 6780 | H80: General Electric Company | I80: Ralph Beman
A81: 1921Flur | B81: Schedule A | C81: 1427870 | E81: 5279 | G81: 6822 | H81: General Electric Company | I81: William L. Van Keuren
A82: 1921Flur | B82: Schedule A | C82: 1430118 | E82: 6034 | G82: 6843 | H82: Patent-Treuhand-Gesellschaft für-Elektrische Glühlampen mbH | I82: Robert Le Rossignol
... A87: 1921Flur | B87: Schedule A | C87: 1464101 | E87: 5788 | G87: 7158 | H87: General Electric Company | I87: Matt Luckiesh
A88: 1921Flur | B88: Schedule A | C88: 1468073 | E88: 5858 | F88: (RN) 1923/1/24 | G88: 7200 | H88: General Electric Company | I88: Aladar Pacz
A89: 1921Flur | B89: Schedule A | C89: 1468084 | E89: 5496 | G89: 7200 | H89: General Electric Company | I89: Frederick W. Salz
A90: 1921Flur | B90: Schedule A | C90: 1477618 | E90: 6017 | G90: 7291 | H90: Hygrade Engineering Co. Inc. | I90: Miner R. Wetmore
A91: 1921Flur | B91: Schedule A | C91: 1491436 | E91: 5611 | G91: 7417 | H91: General Electric Company | I91: Royal F. Strickland
A92: 1921Flur | B92: Schedule A | C92: 1496457 | E92: 5676 | F92: (RN) 1924/4/23 | G92: 7459 | H92: General Electric Company | I92: Gorton R. Fonda
A93: 1921Flur | B93: Schedule A | C93: 1498908 | E93: 4040 | G93: 7480 | H93: General Electric Company | I93: Colin G. Fink
A94: 1921Flur | B94: Schedule A | C94: 1508242 | E94: 7022 | G94: 7557 | H94: General Electric Company | I94: Arthur Partzsch
A95: 1921Flur | B95: Schedule A | C95: 1531265 | E95: 6424 | G95: 7753 | H95: General Electric Company | I95: Philip K. Devers
A96: 1921Flur | B96: Schedule A | C96: 1536833 | E96: 6836 | G96: 7795 | H96: General Electric Company | I96: John T. Fagan, Francis J. Rippl
A97: 1921Flur | B97: Schedule A | C97: 1539672 | E97: 6116 | G97: 7816 | H97: Naamlooze Vennootschap Philips Gloeilampenfabrieken | I97: Gilles Holst
A98: 1921Flur | B98: Schedule A | C98: 1540537 | E98: 6538 | G98: 7823 | H98: General Electric Company | I98: William R. Burrows
A99: 1921Flur | B99: Schedule A | C99: 1541596 | E99: 7612 | G99: 7830 | H99: General Electric Company | I99: Franz Skaupy, Fritz Koret
A100: 1921Flur | B100: Schedule A | C100: 1542390 | E100: 6399 | G100: 7837 | H100: General Electric Company | I100: William G. Houskeeper
A101: 1921Flur | B101: Schedule A | C101: 1546352 | E101: 6398 | G101: 7865 | H101: General Electric Company | I101: Francis J. Rippl
A102: 1921Flur | B102: Schedule A | C102: 1546353 | E102: 6398 | G102: 7865 | H102: General Electric Company | I102: Francis Rippl, Frank J. Malloy
A103: 1921Flur | B103: Schedule A | C103: 1547304 | E103: 6535 | G103: 7879 | H103: Lubrigaiters Limited | I103: Thoms James Dennison
A104: 1921Flur | B104: Schedule A | C104: 1547395 | E104: 6543 | G104: 7879 | H104: General Electric Company | I104: Samuel L. Hoyt
... A116: 1921Flur | B116: Schedule A | C116: 1576221 | E116: 5769 | G116: 8103 | H116: General Electric Company | I116: Francis J. Rippl
A117: 1921Flur | B117: Schedule A | C117: 1588179 | E117: 6451 | G117: 8194 | H117: General Electric Company | I117: Ernst Friederich | J117: Germany | K117: 4423
A118: 1921Flur | B118: Schedule A | C118: 1591113 | E118: 7547 | G118: 8222 | H118: Cooper Hewitt Electric Company | I118: Leroy J. Buttolph
A119: 1921Flur | B119: Schedule A | C119: 1591833 | E119: 7228 | G119: 8222 | H119: General Electric Company | I119: Vincent G. Jarman
A120: 1921Flur | B120: Schedule A | C120: 1591910 | E120: 6048 | G120: 8222 | H120: General Electric Company | I120: Robert S. Burnap
A121: 1921Flur | B121: Schedule A | C121: 1591911 | E121: 6048 | G121: 8222 | H121: General Electric Company | I121: Cromwell A. B. Halvorson, Jr.
A122: 1921Flur | B122: Schedule A | C122: 1594057 | E122: 7547 | G122: 8243 | H122: General Electric Company | I122: Gorton R. Fonda
A123: 1921Flur | B123: Schedule A | C123: 1597439 | D123: (O) 589249 (Di) 3220 | E123: 6836 | F123: 7689 | G123: 8271 | H123: General Electric Company | I123: John T. Fagan, Francis J. Rippl
A124: 1921Flur | B124: Schedule A | C124: 1600072 | E124: 7760 | G124: 8292 | H124: General Electric Company | I124: Franz Skaupy, Georg Gaidies | J124: Germany | K124: 7495
...

Sheet 1928Rail
A1: PoolID | B1: Patent | C1: Type of Compulsory Licensing | D1: Application Date | E1: Grant Date | F1: Assignee (Inventor) | G1: Primary Class A | H1: Primary Subclass | I1: Secondary Subclass 1a | J1: Secondary Subclass 2a | K1: Secondary Subclass 3a | L1: Secondary Subclass 4a | M1: Secondary Subclass 5a | N1: Secondary Subclass 6a | O1: Secondary Subclass 7a | P1: Secondary Subclass 8a | Q1: Secondary Subclass 9a | R1: Secondary Subclass 10a | S1: Secondary Class B | T1: Secondary Subclass 1b | U1: Secondary Subclass 2b | V1: Secondary Subclass 3b | W1: Secondary Subclass 4b | X1: Secondary Subclass 5b | Y1: Secondary Subclass 6b | Z1: Secondary Class C | AA1: Secondary Subclass 1c | AB1: Secondary Subclass 2c | AC1: Secondary Subclass 3c | AD1: Secondary Subclass 4c | AE1: Secondary Subclass 5c | AF1: Secondary Subclass 6c | AG1: Secondary Subclass 7c | AH1: Secondary Class D | AI1: Secondary Subclass 1d | AJ1: Secondary Subclass 2d | AK1: Secondary Subclass 3d | AL1: Secondary Subclass 4d | AM1: Secondary Subclass 5d | AN1: Secondary Subclass 6d | AO1: Secondary Subclass 7d | AP1: Secondary Subclass 8d | AQ1: Secondary Class E | AR1: Secondary Subclass 1e | AS1: Secondary Subclass 2e | AT1: Secondary Class F | AU1: Secondary Subclass 1f | AV1: Secondary Subclass 2f | AW1: Secondary Subclass 3f
A3: These patents were listed in the opinion:
A4: 1928Rail | B4: 1641416 | C4: DP | D4: 8455 | E4: 8649 | F4: Rail Joint Company
A5: 1928Rail | B5: 1788225 | C5: DP | D5: 9006 | E5: 9867 | F5: Woodings-Verona
A6: 1928Rail | B6: 1829247 | C6: DP | D6: 9159 | E6: 10161 | F6: Rail Joint Company
A7: 1928Rail | B7: 1833550 | C7: DP | D7: 9749 | E7: 10189 | F7: Rail Joint Company
A9: Patents listed in Exhibit A of the consent decree:
A10: 1928Rail | B10: 1208698 | C10: DP | D10: 4455 | E10: 4729 | F10: Rail Joint (Thomson)
A11: 1928Rail | B11: 1374782 | C11: DP | D11: 6226 | E11: 6311 | F11: Rail Joint (Thomson) | G11: Re 15773
A12: 1928Rail | B12: 1659776 | C12: DP | D12: 7596 | E12: 8817 | F12: McKenna Process Company (Langford)
A13: 1928Rail | B13: 1547854 | C13: DP | D13: 7680 | E13: 7879 | F13: Woodings (Woodings)
A14: 1928Rail | B14: 1562423 | C14: DP | D14: 7721 | E14: 7991 | F14: Langford | G14: Re 17561, 17596, 18213, 19638
A15: 1928Rail | B15: 1732650 | C15: DP | D15: 8232 | E15: 10014 | F15: McKenna Process Company (Langford) | G15: Re 18011
A16: 1928Rail | B16: 1808466 | C16: DP | D16: 8232 | E16: 10014 | F16: McKenna Process Company (Langford) | G16: Re 18165
A17: 1928Rail | B17: 1712506 | C17: DP | D17: 8517 | E17: 9356 | F17: McKenna Process Company (Langford)
A18: 1928Rail | B18: 1724031 | C18: DP | D18: 8517 | E18: 9356 | F18: McKenna Process Company (Langford)
A19: 1928Rail | B19: 1788225 | C19: DP | D19: 9006 | E19: 9867 | F19: Woodings (Woodings)
A20: 1928Rail | B20: 1829247 | C20: DP | D20: 9159 | E20: 10161 | F20: Rail Joint (Thomson)
A21: 1928Rail | B21: 1808467 | C21: DP | D21: 9231 | E21: 10014 | F21: McKenna Process Company (Langford)
A22: 1928Rail | B22: 1808468 | C22: DP | D22: 9231 | E22: 10014 | F22: McKenna Process Company (Langford) | G22: Re 20874
A23: 1928Rail | B23: 1858401 | C23: DP | D23: 9234 | E23: 10364 | F23: McKenna Process Company (Langford)
A24: 1928Rail | B24: 1799382 | C24: DP | D24: 9253 | E24: 9958 | F24: Langford (Rail Joint Company)
A25: 1928Rail | B25: 1804792 | C25: DP | D25: 9267 | E25: 9993 | F25: McKenna Process Company (Langford)
A26: 1928Rail | B26: 1757774 | C26: DP | D26: 9443 | E26: 9622 | F26: McKenna Process Company (Langford) | G26: Re 17963
A27: 1928Rail | B27: 1836032 | C27: DP | D27: 9992 | E27: 10210 | F27: McKenna Process Company (Langford)
A28: 1928Rail | B28: 2134449 | C28: DP | D28: 11933 | E28: 12716 | F28: Langford
A29: 1928Rail | B29: 2134450 | C29: DP | D29: 11933 | E29: 12716 | F29: Langford
A31: Patents listed in Exhibit B of the consent decree:
A32: 1928Rail | B32: 1833026 | C32: DP | D32: 7026 | E32: 10189 | F32: McKenna Process Company (Langford)
A33: 1928Rail | B33: 1799380 | C33: DP | D33: 9215 | E33: 9958 | F33: McKenna Process Company (Langford) | G33: Re 18568
A34: 1928Rail | B34: 1814835 | C34: DP | D34: 9611 | E34: 10056 | F34: McKenna Process Company (Langford)
A35: 1928Rail | B35: 1865194 | C35: DP | D35: 9611 | E35: 10406 | F35: McKenna Process Company (Langford)
A36: 1928Rail | B36: 1759458 | C36: DP | D36: 9722 | E36: 10504 | F36: McKenna Process Company (Langford)
A37: 1928Rail | B37: 1799381 | C37: DP | D37: 9722 | E37: 10504 | F37: McKenna Process Company (Langford)
A38: 1928Rail | B38: 1842412 | C38: DP | D38: 9722 | E38: 10504 | F38: McKenna Process Company (Langford)
A39: 1928Rail | B39: 1883982 | C39: DP | D39: 9807 | E39: 10525 | F39: McKenna Process Company (Langford)
A40: 1928Rail | B40: 1890687 | C40: DP | D40: 9876 | E40: 10574 | F40: McKenna Process Company (Langford)
A41: 1928Rail | B41: 1836033 | C41: DP | D41: 10024 | E41: 10210 | F41: McKenna Process Company (Langford)
A42: 1928Rail | B42: 2034043 | C42: DP | D42: 11021 | E42: 11764 | F42: McKenna Process Company (Langford)
A43: 1928Rail | B43: 2034044 | C43: DP | D43: 11199 | E43: 11764 | F43: McKenna Process Company (Langford)
A44: 1928Rail | B44: 2034045 | C44: DP | D44: 11199 | E44: 11764 | F44: McKenna Process Company (Langford)
A45: 1928Rail | B45: 2034046 | C45: DP | D45: 11399 | E45: 11764 | F45: McKenna Process Company (Langford)
A46: 1928Rail | B46: 2060996 | C46: DP | D46: 11443 | E46: 12009 | F46: McKenna Process Company (Langford)
A48: Patents listed in Exhibit C of the consent decree:
A50: 1928Rail | B50: 1641416 | C50: DP | D50: 8455 | E50: 8649 | F50: Rail Joint (Disbrow)
A51: 1928Rail | B51: 1833550 | C51: DP | D51: 9749 | E51: 10189 | F51: Rail Joint (Armstrong)
A52: 1928Rail | B52: 1948102 | C52: DP | D52: 9754 | E52: 11008 | F52: Faries
A55: Notes
A56: Vaughan (p. 55): "Three companies-Rail Joint, Woodings-Verona, and McKenna-each owned patents pertaining to the design of rail joint bars and also patents on the process of re-forming. The three companies aided each other in securing such patents and exchanged information concerning them. Beginning about 1928, they pooled their patents through cross-licensing agreements and sublicensed seven other companies to use some or all of them. A consent judgment of 1944 enjoined these objectionable practices and directed these companies to dedicate certain patents to the public."
A58: Firms: Rail Joint Company, Woodings-Verona, and McKenna Process Company.
A59: Foreign firms: No
A60: Start year: 1928
A61: End year: 1944 (consent decree).
A62: Grantbacks:
A63: Independent licensing:
A64: Open licensing:
A65: Number of licensees: 10
A66: Compulsory licensing: Yes, RAND and DP.
A67: Patent holding company: No
... A71: Pool members:
A72: Woodings-Verona | B72: 1928
A73: Rail Joint Company | B73: 1928
A74: McKenna Process Company | B74: 1929
A77: Licensees (did not add patents):
A78: Illinois Rail Joint Company | B78: 1931
A79: Tredegar Company | B79: 10139
A80: Rail Joint Reforming Company | B80: 10141
A81: Mississippi Valley Structural Steel Company | B81: 10149
A82: Mohawk Equipment Company | B82: 10160
A83: Ray O. Shaffer | B83: 10168
A84: Texas Rail Joint Company | B84: 10183
A85: Poole & McGonigle | B85: 11389
A86: Youngstown Steel Car Company | B86: 11719
A87: Blatchford Corporation | B87: 10531
A89: Notes from Complaint:
A90: The afforesaid offenses were intended to be effectuated and were effectuated by divers means and methods involving agreement, among,…to use such pooled patents to harass non-licensed companies by threats of infringement suits, by instituting infringement suits, by instituting suits, by attempting to induce railroads to refrain from having worn bars reformed by non-licensed companies" (p. 10).
A92: Notes
A93: Source: U.S. v. Rail Joint Co. et al., In the District Court of the United States for the Northern District of Illinois, Eastern Division. Civil Action No. 43-C-1295. September 20, 1944.
A94: Additonal source: McKenna Process Company of Illinois, Appellee, v. Blatchford Corporation, Appellant, Gen. No. 9,464, APPELLATE COURT OF ILLINOIS, SECOND DISTRICT, 304 Ill. App. 101; 25 N.E.2d 916; 1940 Ill. App. LEXIS 921.
A95: Open pool: Appendix D of the opinion lists licenses beginning 1931.
A96: No evidence or reference to prior litigation.
A97: Firms: Rail Joint Company, Poor & Company, Woodings-Verona Tool Works, Fred Poor, Victor C. Armstrong, and Emanuel Woodings. McKenna is not listed here but listed in the additional case.
A98: Initial Firms: McKenna Process Company and Rail Joint Company.
A99: No evidence for or against grantbacks.
A100: Independent licensing: Rail Joint seems to have entered into a bunch of contracts with outside firms.
A102: On September 12, 1931, the McKenna Process Company of Illinois, as the owner of a large number of patents issued in name of George Langford for the process of reforming worn rail joint bars, granted an exclusive license [***2] under said patents to the Rail Joint Company of New York with power to grant sublicenses. On the same date, by a separate contract, the Rail Joint Company of New York granted a sublicense of all the Langford patents to the McKenna Process Company of Illinois, and on the same date, and by another separate contract, the Rail Joint Company of [*104] New York granted a sublicense to the McKenna Process Company of certain patents owned by the Rail Joint Company.
... A106: All of the four "existing" contracts between the Blatchford Corporation and the railroads had called for a tonnage rate of $ 13, and each of them [***4] was, on or about August 1, 1933, by mutual agreement, renewed for a year at a price of $ 14.30. The Blatchford Corporation insists that this was merely an exercise by the railroad company of its option to renew for one year and did not take it out of the class of contracts designated as "existing" contracts and that it was not liable to the McKenna Process Company for an increase in royalties from $ 1 to $ 2. The McKenna Process Company insists that the increase in price to the railroads to an amount above $ 13 per ton had the effect of new and different contracts which abrogated the old "existing" contracts, and that henceforth the Blatchford Corporation was liable for a royalty of $ 2 per ton. This controversy is evidenced by correspondence between the parties, until the suit was started.

Sheet 1930Cabl
A1: PoolID | B1: Patent | C1: Type of Compulsory Licensing | D1: Application Date | E1: Grant Date | F1: Assignee (Inventor) | G1: sequence | H1: Primary Class A | I1: Primary Subclass | J1: Secondary Subclass 1a | K1: Secondary Subclass 2a | L1: Secondary Subclass 3a | M1: Secondary Subclass 4a | N1: Secondary Subclass 5a | O1: Secondary Subclass 6a | P1: Secondary Subclass 7a | Q1: Secondary Subclass 8a | R1: Secondary Subclass 9a | S1: Secondary Subclass 10a | T1: Secondary Class B | U1: Secondary Subclass 1b | V1: Secondary Subclass 2b | W1: Secondary Subclass 3b | X1: Secondary Subclass 4b | Y1: Secondary Subclass 5b | Z1: Secondary Subclass 6b | AA1: Secondary Class C | AB1: Secondary Subclass 1c | AC1: Secondary Subclass 2c | AD1: Secondary Subclass 3c | AE1: Secondary Subclass 4c | AF1: Secondary Subclass 5c | AG1: Secondary Subclass 6c | AH1: Secondary Subclass 7c | AI1: Secondary Class D | AJ1: Secondary Subclass 1d | AK1: Secondary Subclass 2d | AL1: Secondary Subclass 3d | AM1: Secondary Subclass 4d | AN1: Secondary Subclass 5d | AO1: Secondary Subclass 6d | AP1: Secondary Subclass 7d | AQ1: Secondary Subclass 8d | AR1: Secondary Class E | AS1: Secondary Subclass 1e | AT1: Secondary Subclass 2e | AU1: Secondary Class F | AV1: Secondary Subclass 1f | AW1: Secondary Subclass 2f | AX1: Secondary Subclass 3f
A2: Patents listed in United States v. General Cable Corp., CCH 1948-49 Trade Cases 62,300 (S.D.N.Y. Civil No. 40-76; Complaint, 1947; Consent Judgement, 1948):
A4: Schedule A of final judgment - Pirelli patents as to which all defendants have certain rights:
A5: 1930Cabl | B5: 1962059 | C5: RR | D5: 7914 | E5: 11113 | F5: Emanueli | G5: 1
A6: 1930Cabl | B6: 1964907 | C6: RR | D6: 8474 | E6: 11141 | F6: Emanueli | G6: 1
A7: 1930Cabl | B7: 1869308 | C7: RR | D7: 8627 | E7: 10434 | F7: Emanueli | G7: 1
A8: 1930Cabl | B8: 2133398 | C8: RR | D8: 9246 | E8: 12709 | F8: Puritz | G8: 1
A9: 1930Cabl | B9: 2133399 | C9: RR | D9: 9246 | E9: 12709 | F9: Puritz | G9: 1
A10: 1930Cabl | B10: 2081880 | C10: RR | D10: 9273 | E10: 12198 | F10: Emanueli | G10: 1
A11: 1930Cabl | B11: 2133382 | C11: RR | D11: 9273 | E11: 12709 | F11: Emanueli | G11: 1
A12: 1930Cabl | B12: 1883648 | C12: RR | D12: 9324 | E12: 10518 | F12: Emanueli | G12: 1
A13: 1930Cabl | B13: 1895983 | C13: RR | D13: 9391 | E13: 10623 | F13: Emanueli | G13: 1
A14: 1930Cabl | B14: 1900600 | C14: RR | D14: 9391 | E14: 10658 | F14: Emanueli | G14: 1
A15: 1930Cabl | B15: 1947929 | C15: RR | D15: 9391 | E15: 11008 | F15: Emanueli | G15: 1
A16: 1930Cabl | B16: 1957995 | C16: RR | D16: 9391 | E16: 11085 | F16: Emanueli | G16: 1
... A49: 1930Cabl | B49: 2244392 | C49: RR | D49: 12899 | E49: 13668 | F49: Emanueli | G49: 1
A51: Others patents as to which General Cable Corporation has rights:
A52: 1930Cabl | B52: 2071102 | C52: RR | D52: 7109 | E52: 12100 | F52: Atkinson (General Cable) | G52: 2
A53: 1930Cabl | B53: 1920903 | C53: RR | D53: 7858 | E53: 10805 | F53: Haanen | G53: 2
A54: 1930Cabl | B54: 1836570 | C54: RR | D54: 7862 | E54: 10210 | F54: Boyle | G54: 2
A55: 1930Cabl | B55: 1837375 | C55: RR | D55: 7943 | E55: 10217 | F55: Saurman | G55: 2
A56: 1930Cabl | B56: 1878169 | C56: RR | D56: 8135 | E56: 10490 | F56: Myers | G56: 2
A57: 1930Cabl | B57: 1868962 | C57: RR | D57: 8217 | E57: 10434 | F57: Atkinson | G57: 2
A58: 1930Cabl | B58: 1878094 | C58: RR | D58: 8386 | E58: 10490 | F58: Atkinson | G58: 2
A59: 1930Cabl | B59: 1929509 | C59: RR | D59: 8653 | E59: 10875 | F59: Miller | G59: 2
A60: 1930Cabl | B60: 2068624 | C60: RR | D60: 8837 | E60: 12072 | F60: Atkinson (General Cable) | G60: 2
A61: 1930Cabl | B61: 1948964 | C61: RR | D61: 8897 | E61: 11015 | F61: Gay | G61: 2
A62: 1930Cabl | B62: 1971626 | C62: RR | D62: 9055 | E62: 11197 | F62: Simmons (General Cable) | G62: 2
A63: 1930Cabl | B63: 1965540 | C63: RR | D63: 9135 | E63: 11141 | F63: Atkinson | G63: 2
... A91: 1930Cabl | B91: 2310201 | C91: RR | D91: 13049 | E91: 14284 | F91: Cox (General Cable) | G91: 2
A92: 1930Cabl | B92: 2665328 | C92: RR | D92: 15909 | E92: 18267 | F92: Atkinson & McGrath | G92: 2 | H92: SN 763001
A93: 1930Cabl | B93: 2678863 | C93: RR | D93: 15909 | E93: 18400 | F93: Atkinson (General Cable) | G93: 2 | H93: SN 763002
A94: 1930Cabl | B94: 2615074 | C94: RR | D94: 15919 | E94: 17826 | F94: Bronovicki (General Cable) | G94: 2 | H94: SN 765708
A96: Other patents as to which General Electric Company has rights:
A97: 1930Cabl | B97: 2093305 | C97: RR | D97: 7255 | E97: 12310 | F97: Buck (GE) | G97: 3
A98: 1930Cabl | B98: 1819881 | C98: RR | D98: 8422 | E98: 10091 | F98: Eby (GE) | G98: 3
A99: 1930Cabl | B99: 1905691 | C99: RR | D99: 8440 | E99: 10707 | F99: Eby (GE) | G99: 3
A100: 1930Cabl | B100: 1819882 | C100: RR | D100: 8630 | E100: 10091 | F100: Eby (GE) | G100: 3
A101: 1930Cabl | B101: 1853882 | C101: RR | D101: 8771 | E101: 10329 | F101: Roper | G101: 3
A102: 1930Cabl | B102: 1853883 | C102: RR | D102: 8771 | E102: 10329 | F102: Roper | G102: 3
A103: 1930Cabl | B103: 1833798 | C103: RR | D103: 8904 | E103: 10189 | F103: Shanklin (GE) | G103: 3
A104: 1930Cabl | B104: 1933312 | C104: RR | D104: 8943 | E104: 10896 | F104: Clark (GE) | G104: 3
A105: 1930Cabl | B105: 1902487 | C105: RR | D105: 8972 | E105: 10672 | F105: Calvert (GE) | G105: 3
A106: 1930Cabl | B106: 1896841 | C106: RR | D106: 8986 | E106: 10630 | F106: Eby (GE) | G106: 3
A107: 1930Cabl | B107: 1933313 | C107: RR | D107: 9000 | E107: 10896 | F107: Clark (GE) | G107: 3
A108: 1930Cabl | B108: 1933347 | C108: RR | D108: 9043 | E108: 10896 | F108: Shanklin (GE) | G108: 3
... A196: 1930Cabl | B196: 2401595 | C196: RR | D196: 14371 | E196: 15495 | F196: Wetherill (GE) | G196: 3
A197: 1930Cabl | B197: 2531156 | C197: RR | D197: 15082 | E197: 17126 | F197: Piercy (GE) | G197: 3 | H197: SN 588742
A199: 1930Cabl | B199: SN 607833 | C199: RR | D199: 15186 | F199: Flynn (GE)
A201: Other patents as to which The Okonite-Callender Cable Company, Incorporated has rights:
A202: 1930Cabl | B202: 1874235 | C202: RR | D202: 9231 | E202: 10469 | F202: Branthwaite (Okonite-Callender) | G202: 4
A203: 1930Cabl | B203: 1931592 | C203: RR | D203: 9680 | E203: 10889 | F203: Stevens (Okonite-Callender) | G203: 4
A204: 1930Cabl | B204: 2015063 | C204: RR | D204: 10071 | E204: 11589 | F204: Bennet (Okonite-Callender) | G204: 4
A205: 1930Cabl | B205: 1886786 | C205: RR | D205: 10158 | E205: 10539 | F205: Branthwaite (Okonite-Callender) | G205: 4
A206: 1930Cabl | B206: 1885045 | C206: RR | D206: 10203 | E206: 10525 | F206: Bennet (Okonite-Callender) | G206: 4
A207: 1930Cabl | B207: 1926666 | C207: RR | D207: 10258 | E207: 10847 | F207: Bennet (Okonite-Callender) | G207: 4
A208: 1930Cabl | B208: 1879867 | C208: RR | D208: 10287 | E208: 10497 | F208: Bennet (Okonite-Callender) | G208: 4
A209: 1930Cabl | B209: 1947454 | C209: RR | D209: 10287 | E209: 11008 | F209: Bennet (Okonite-Callender) | G209: 4
A210: 1930Cabl | B210: 1980370 | C210: RR | D210: 10287 | E210: 11274 | F210: Bennet (Okonite-Callender) | G210: 4
A211: 1930Cabl | B211: 1947455 | C211: RR | D211: 10289 | E211: 11008 | F211: Bennet (Okonite-Callender) | G211: 4
A212: 1930Cabl | B212: 1959354 | C212: RR | D212: 10387 | E212: 11099 | F212: Everest (Okonite-Callender) | G212: 4
A213: 1930Cabl | B213: 1947481 | C213: RR | D213: 10472 | E213: 11008 | F213: Meyer (Okonite-Callender) | G213: 4
... A277: 1930Cabl | B277: 2399849 | C277: RR | D277: 15014 | E277: 15467 | F277: Bennet | G277: 4
A279: Pending Applications
A280: 1930Cabl | B280: 2597222 | C280: RR | D280: 16079 | E280: 17672 | F280: Bennett (Okonite-Callender) | G280: 4 | H280: SN 1446
A281: 1930Cabl | B281: 2457437 | C281: RR | D281: 14831 | E281: 16433 | F281: Bennett (Okonite-Callender) | G281: 4 | H281: SN 548688
A282: 1930Cabl | B282: 2516747 | C282: RR | D282: 15216 | E282: 17007 | F282: Bennett (Okonite-Callender) | G282: 4 | H282: SN 613257
A283: 1930Cabl | B283: 2532477 | C283: RR | D283: 15324 | E283: 17140 | F283: Bennett (Okonite-Callender) | G283: 4 | H283: SN 635344
A284: 1930Cabl | B284: 2501305 | C284: RR | D284: 15481 | E284: 16881 | F284: Bennett (Okonite-Callender) | G284: 4 | H284: SN 671177
A285: 1930Cabl | B285: 2493909 | C285: RR | D285: 15487 | E285: 16811 | F285: Bennett (Okonite-Callender) | G285: 4 | H285: SN 672968
A286: 1930Cabl | B286: 2457438 | C286: RR | D286: 15544 | E286: 16433 | F286: Bennett (Okonite-Callender) | G286: 4 | H286: SN 685574
A287: 1930Cabl | B287: 2555840 | C287: RR | D287: 15604 | E287: 17322 | F287: Bennett (Okonite-Callender) | G287: 4 | H287: SN 698576
A288: 1930Cabl | B288: 2476953 | C288: RR | D288: 15811 | E288: 16643 | F288: Bennett (Okonite-Callender) | G288: 4 | H288: SN 741931
A290: 1930Cabl | B290: 1447 | C290: RR | D290: 16079
A291: 1930Cabl | B291: 1448 | C291: RR | D291: 16079
A292: 1930Cabl | B292: 2430 | C292: RR | D292: 16085
A293: 1930Cabl | B293: 463186 | C293: RR | D293: 14176
A294: 1930Cabl | B294: 535832 | C294: RR | D294: 14746
A295: 1930Cabl | B295: 549764 | C295: RR | D295: 14838
A296: 1930Cabl | B296: 586590 | C296: RR | D296: 15069
A297: 1930Cabl | B297: 631688 | C297: RR | D297: 15308
A298: 1930Cabl | B298: 673205 | C298: RR | D298: 15489
A299: 1930Cabl | B299: 674356 | C299: RR | D299: 15495
A300: 1930Cabl | B300: 679605 | C300: RR | D300: 15517
A301: 1930Cabl | B301: 685573 | C301: RR | D301: 15544
... A303: 1930Cabl | B303: 740358 | C303: RR | D303: 15804
A306: Other Patents as to which Phelps Dodge Copper Products Corporations Has Rights:
A307: 1930Cabl | B307: 1950608 | C307: RR | D307: 8890 | E307: 11029 | F307: Hanson (Habirshaw) | G307: 5
A308: 1930Cabl | B308: 1959526 | C308: RR | D308: 8905 | E308: 11099 | F308: Del Mar (Habirshaw) | G308: 5
A309: 1930Cabl | B309: 1892663 | C309: RR | D309: 9224 | E309: 10595 | F309: Del Mar (Habirshaw) | G309: 5
A310: 1930Cabl | B310: 2038894 | C310: RR | D310: 9974 | E310: 11806 | F310: Del Mar (Habirshaw) | G310: 5
A311: 1930Cabl | B311: 1944003 | C311: RR | D311: 10240 | E311: 10973 | F311: Del Mar (Habirshaw) | G311: 5
A312: 1930Cabl | B312: 1944004 | C312: RR | D312: 10302 | E312: 10973 | F312: Del Mar (Habirshaw) | G312: 5
A313: 1930Cabl | B313: 2031014 | C313: RR | D313: 10340 | E313: 11736 | F313: Staples (Habirshaw) | G313: 5
A314: 1930Cabl | B314: 2057454 | C314: RR | D314: 10340 | E314: 11974 | F314: Staples (Habirshaw) | G314: 5
A315: 1930Cabl | B315: 1980388 | C315: RR | D315: 10608 | E315: 11274 | F315: Del Mar (Habirshaw) | G315: 5
A316: 1930Cabl | B316: 1944005 | C316: RR | D316: 10644 | E316: 10973 | F316: Del Mar (Habirshaw) | G316: 5
A317: 1930Cabl | B317: 2145092 | C317: RR | D317: 11589 | E317: 12807 | F317: Mitchell (Phelps Dodge) | G317: 5
A318: 1930Cabl | B318: 2190017 | C318: RR | D318: 12585 | E318: 13192 | F318: Del Mar (Phelps Dodge) | G318: 5
... A325: 1930Cabl | B325: 2425851 | C325: RR | D325: 15044 | E325: 15936 | F325: Wyatt (Phelps Dodge) | G325: 5
...

Sheet 1930Wate
A1: PoolID | B1: Patent | C1: Type of Compulsory Licensing | D1: Serial No. | E1: Application Date | F1: Application Date II | G1: Grant Date | H1: Assignee (if not, inventor name) | I1: Inventor Name | J1: Filed in country | K1: Filing date | L1: Comment
A2: Patents listed in Appendix A of Final Judgment, RR:
A3: 1930Wate | B3: 2012194 | C3: RR | E3: 8557 | G3: 11554 | H3: The Permutit Company | I3: Walter J. Hughes
A4: 1930Wate | B4: 1976439 | C4: RR | E4: 9029 | G4: 11239 | H4: General Water Treatment Corporation | I4: Andrew J. Dotterweich
A5: 1930Wate | B5: 2003760 | C5: RR | E5: 9558 | G5: 11477 | H5: The Permutit Company | I5: Orland R. Sweeney, Thomas B. Clark
A6: 1930Wate | B6: 2003739 | C6: RR | E6: 9784 | G6: 11477 | H6: The Permutit Company | I6: Thomas B. Clark
A7: 1930Wate | B7: 2003757 | C7: RR | E7: 9864 | G7: 11477 | H7: The Permutit Company | I7: Eric Pick
A8: 1930Wate | B8: 1980161 | C8: RR | E8: 9952 | G8: 11274 | H8: The Permutit Company | I8: Samuel B. Applebaum
A9: 1930Wate | B9: 2088104 | C9: RR | E9: 9957 | G9: 12261 | H9: The Duro Company | I9: Arthur C. Zimmerman
A10: 1930Wate | B10: 1996136 | C10: RR | E10: 9981 | G10: 11414 | H10: The Duro Company | I10: Arthur C. Zimmerman
A11: 1930Wate | B11: 2111169 | C11: RR | E11: 10037 | G11: 12492 | H11: The Permutit Company | I11: Thomas B. Clark
A12: 1930Wate | B12: 2071997 | C12: RR | E12: 10048 | G12: 12107 | H12: The Permutit Company | I12: Francis Norwood Bard
A13: 1930Wate | B13: 2003762 | C13: RR | E13: 10143 | G13: 11477 | H13: The Permutit Company | I13: Edward T. Turner
A14: 1930Wate | B14: 2146983 | C14: RR | E14: 10378 | G14: 12828 | H14: The Permutit Company | I14: Eric Pick
A15: 1930Wate | B15: 2052515 | C15: RR | E15: 10612 | G15: 11925 | H15: The Permutit Company | I15: Eric Pick
A16: 1930Wate | B16: 2059645 | C16: RR | E16: 10700 | G16: 11995 | I16: Karl P. McElroy
A17: 1930Wate | B17: 2139299 | C17: RR | E17: 10762 | G17: 12758 | H17: The Permutit Company | I17: William McAfee Bruce, Ray Riley
A18: 1930Wate | B18: 2051155 | C18: RR | E18: 10984 | G18: 11918 | H18: The Permutit Company | I18: Eugene Staegemann
A19: 1930Wate | B19: 2021672 | C19: RR | E19: 10990 | G19: 11645 | I19: Charles H. Spaulding
A20: 1930Wate | B20: 1977781 | C20: RR | E20: 10993 | G20: 11253 | H20: The Permutit Company | I20: Eugene Staegemann
A21: 1930Wate | B21: 2061714 | C21: RR | E21: 11220 | G21: 12016 | H21: The Permutit Company | I21: Eric Pick
A22: 1930Wate | B22: 2067302 | C22: RR | E22: 11245 | G22: 12065 | H22: The Permutit Company | I22: Eric Pick
A23: 1930Wate | B23: 2065962 | C23: RR | E23: 11247 | G23: 12051 | H23: The Permutit Company | I23: Herbert L. Bowers
A24: 1930Wate | B24: 2036634 | C24: RR | E24: 11256 | G24: 11785 | H24: The Permutit Company | I24: Alexander Campbell Inch | J24: Great Britain | K24: 10898
A25: 1930Wate | B25: 2071990 | C25: RR | E25: 11317 | G25: 12107 | H25: The Permutit Company | I25: Howard L. Tiger
A26: 1930Wate | B26: 2191063 | C26: RR | E26: 11332 | G26: 13199 | H26: N.V. Octroolen-Maatschappij "Activit" | I26: Pieter Smit | J26: Netherlands | K26: 10976
A27: 1930Wate | B27: 2205635 | C27: RR | E27: 11332 | G27: 13325 | H27: N.V. Octroolen-Maatschappij "Activit" | I27: Pieter Smit
A28: 1930Wate | B28: 2076443 | C28: RR | E28: 11344 | G28: 12149 | H28: The Permutit Company | I28: William McAfee Bruce
A29: 1930Wate | B29: 2091002 | C29: RR | E29: 11364 | G29: 12289 | H29: The Permutit Company | I29: George A. Lewis
A30: 1930Wate | B30: 2061715 | C30: RR | E30: 11379 | G30: 12016 | H30: The Permutit Company | I30: Eric Pick
A31: 1930Wate | B31: 2190853 | C31: RR | E31: 11455 | G31: 13199 | H31: The Permutit Company | I31: William Vaughan
A32: 1930Wate | B32: 2069564 | C32: RR | E32: 11534 | G32: 12086 | H32: The Permutit Company | I32: Howard L. Tiger, Paul C. Goetz
A33: 1930Wate | B33: 2061722 | C33: RR | E33: 11585 | G33: 12016 | H33: The Permutit Company | I33: Howard L. Tiger
A34: 1930Wate | B34: 2076321 | C34: RR | E34: 11610 | G34: 12149 | H34: The Permutit Company | I34: Eric Pick
A35: 1930Wate | B35: 2112476 | C35: RR | E35: 11628 | G35: 12506 | H35: The Permutit Company | I35: Herbert L. Bowers, Ray Riley
A36: 1930Wate | B36: 2170065 | C36: RR | E36: 11635 | G36: 13017 | H36: The Permutit Company | I36: Ray Riley
A37: 1930Wate | B37: 2099623 | C37: RR | E37: 11645 | G37: 12373 | H37: The Permutit Company | I37: Ray Riley, William McAfee Bruce
A38: 1930Wate | B38: 2122824 | C38: RR | E38: 11648 | G38: 12604 | H38: The Permutit Company | I38: Eric Pick
A39: 1930Wate | B39: 2076322 | C39: RR | E39: 11689 | G39: 12149 | H39: The Permutit Company | I39: Eric Pick
A40: 1930Wate | B40: 2127314 | C40: RR | E40: 11788 | G40: 12646 | I40: Charles H. Spaulding
A41: 1930Wate | B41: 2098893 | C41: RR | E41: 11934 | G41: 12366 | H41: The Permutit Company | I41: Eugene Staegemann, deceased, by Jessie L. Staegemann
A42: 1930Wate | B42: 2139227 | C42: RR | E42: 11943 | G42: 12758 | H42: The Permutit Company | I42: Paul C. Goetz
A43: 1930Wate | B43: 2114576 | C43: RR | E43: 12016 | G43: 12527 | H43: The Permutit Company | I43: Edward P. Schinman
A44: 1930Wate | B44: 2240171 | C44: RR | E44: 12023 | G44: 13633 | H44: The Permutit Company | I44: Norman E. Brice, Charles M. Guldner
A45: 1930Wate | B45: 2198874 | C45: RR | E45: 12129 | G45: 13269 | H45: The Permutit Company | I45: Eric Leighton Holmes | J45: Great Britain | K45: 11767
A46: 1930Wate | B46: 2127310 | C46: RR | E46: 12197 | G46: 12646 | H46: The Permutit Company | I46: Ray Riley
A47: 1930Wate | B47: 2204062 | C47: RR | E47: 12244 | G47: 13311 | H47: The Permutit Company | I47: Samuel B. Applebaum
A48: 1930Wate | B48: 2204097 | C48: RR | E48: 12249 | G48: 13311 | H48: The Permutit Company | I48: James M. Montgomery
A49: 1930Wate | B49: 2179246 | C49: RR | E49: 12310 | G49: 13094 | H49: The Permutit Company | I49: Samuel B. Applebaum
A50: 1930Wate | B50: 2180320 | C50: RR | E50: 12311 | G50: 13101 | I50: Ernest A. Hansen
A51: 1930Wate | B51: 2241873 | C51: RR | E51: 12334 | G51: 13647 | H51: The Permutit Company | I51: Joseph D. Yoder
A52: 1930Wate | B52: 2170975 | C52: RR | E52: 12368 | G52: 13024 | H52: The Permutit Company | I52: Eric Pick
A53: 1930Wate | B53: 2244188 | C53: RR | E53: 12370 | G53: 13668 | I53: Harry M. Danner
A54: 1930Wate | B54: 2260971 | C54: RR | E54: 12377 | G54: 13815 | H54: The Permutit Company | I54: Paul C. Goetz
A55: 1930Wate | B55: 2227520 | C55: RR | E55: 12521 | G55: 13521 | H55: The Permutit Company | I55: Howard L. Tiger
A56: 1930Wate | B56: 2204072 | C56: RR | E56: 12563 | G56: 13311 | H56: The Permutit Company | I56: John G. Dean
A57: 1930Wate | B57: 2397575 | C57: RR | E57: 12639 | G57: 15432 | H57: The Permutit Company | I57: Howard L. Tiger, Paul C. Goetz
A58: 1930Wate | B58: 2241887 | C58: RR | E58: 12682 | G58: 13647 | H58: The Permutit Company | I58: Eric Pick
A59: 1930Wate | B59: 2240163 | C59: RR | E59: 12691 | G59: 13633 | H59: The Permutit Company | I59: Eric Pick
A60: 1930Wate | B60: 2155964 | C60: RR | E60: 12699 | G60: 12898 | H60: The Permutit Company | I60: Herbert L. Bowers, Norman E. Brice
A61: 1930Wate | B61: 2272026 | C61: RR | E61: 12701 | G61: 13913 | I61: Charles H. Spaulding
A62: 1930Wate | B62: 2240119 | C62: RR | E62: 12724 | G62: 13633 | H62: The Permutit Company | I62: James M. Montgomery, Eric Pick
A63: 1930Wate | B63: 2281194 | C63: RR | E63: 12776 | G63: 13997 | H63: The Permutit Company | I63: Eric Leighton Holmes, Lucie Evelyn Holmes, William George Prescott | J63: Great Britain | K63: 12418
A64: 1930Wate | B64: 2179271 | C64: RR | E64: 12872 | G64: 13094 | H64: The Permutit Company | I64: Eric Pick
A65: 1930Wate | B65: 2295714 | C65: RR | E65: 12892 | G65: 14137 | H65: The Permutit Company | I65: Bradford J. Clark
A66: 1930Wate | B66: 2240164 | C66: RR | E66: 12916 | G66: 13633 | H66: The Permutit Company | I66: Eric Pick
A67: 1930Wate | B67: 2240182 | C67: RR | E67: 12965 | G67: 13633 | H67: The Permutit Company | I67: Charles M. Guldner, Eric Pick | J67: Great Britain | K67: 12659
A68: 1930Wate | B68: 2259717 | C68: RR | E68: 12993 | G68: 13808 | I68: Egon Zentner | J68: Czechoslovakia | K68: 11947
A69: 1930Wate | B69: 2328323 | C69: RR | E69: 13000 | G69: 14487 | H69: The Permutit Company | I69: Herbert L. Bowers, Eric Pick
A70: 1930Wate | B70: 2264139 | C70: RR | E70: 13017 | G70: 13843 | H70: The Permutit Company | I70: James M. Montgomery, William W. Aultman
A71: 1930Wate | B71: 2226743 | C71: RR | E71: 13133 | G71: 13514 | H71: The Permutit Company | I71: Ray Riley
A72: 1930Wate | B72: 2347318 | C72: RR | E72: 13133 | G72: 14725 | H72: The Permutit Company | I72: William Brewster Gurney
A73: 1930Wate | B73: 2366898 | C73: RR | E73: 13133 | G73: 14984 | H73: The Permutit Company | I73: William Brewster Gurney
A74: 1930Wate | B74: 2267841 | C74: RR | E74: 13314 | G74: 13878 | H74: The Permutit Company | I74: Ray Riley
A75: 1930Wate | B75: 2428418 | C75: RR | E75: 13333 | G75: 15985 | H75: The Permutit Company | I75: Paul C. Goetz, Howard L. Tiger
A76: 1930Wate | B76: 2401924 | C76: RR | E76: 13354 | G76: 15502 | H76: The Permutit Company | I76: Paul C. Goetz
A77: 1930Wate | B77: 2240116 | C77: RR | E77: 13356 | G77: 13633 | H77: The Permutit Company | I77: Eric Leighton Holmes | J77: Great Britain | K77: 12879
A78: 1930Wate | B78: 2355402 | C78: RR | E78: 13616 | G78: 14830 | H78: The Permutit Company | I78: Sidney Sussman
A79: 1930Wate | B79: 2360195 | C79: RR | E79: 13626 | G79: 14893 | H79: The Permutit Company | I79: Wesley E. Brittin
A80: 1930Wate | B80: 2370772 | C80: RR | E80: 13707 | G80: 15040 | H80: The Permutit Company | I80: Herbert L. Bowers
A81: 1930Wate | B81: 2364775 | C81: RR | E81: 13717 | G81: 14956 | H81: The Permutit Company | I81: Norman E. Brice
A82: 1930Wate | B82: 2393269 | C82: RR | E82: 13789 | G82: 15362 | H82: The Permutit Company | I82: Willem Rudolfs, Harry W. Gehm
A83: 1930Wate | B83: 2361235 | C83: RR | E83: 13896 | G83: 14907 | H83: The Permutit Company | I83: Eric Pick
A84: 1930Wate | B84: 2392105 | C84: RR | E84: 13971 | G84: 15341 | H84: The Permutit Company | I84: Sidney Sussman
A85: 1930Wate | B85: 2351835 | C85: RR | E85: 14034 | G85: 14781 | H85: The Permutit Company | I85: Eric Pick
A86: 1930Wate | B86: 2442989 | C86: RR | E86: 14046 | G86: 16230 | H86: The Permutit Company | I86: Sidney Sussman
A87: 1930Wate | B87: 2442584 | C87: RR | E87: 14067 | G87: 16223 | H87: The Permutit Company | I87: Calvin Calmon
A88: 1930Wate | B88: 2393249 | C88: RR | E88: 14127 | G88: 15362 | H88: The Permutit Company | I88: Eric Leighton Holmes | J88: Great Britain | K88: 13767
A89: 1930Wate | B89: 2422054 | C89: RR | E89: 14222 | G89: 15866 | H89: The Permutit Company | I89: Howard L. Tiger
A90: 1930Wate | B90: 2382334 | C90: RR | E90: 14393 | G90: 15201 | H90: The Permutit Company | I90: Ray Riley, Frederick C. Nachod
A91: 1930Wate | B91: 2371427 | C91: RR | E91: 14545 | G91: 15047 | H91: The Permutit Company | I91: John Gilbert Dean, Randall Helligman, Ray Riley
A92: 1930Wate | B92: 2372391 | C92: RR | E92: 14545 | G92: 15061 | H92: The Permutit Company | I92: Eric Pick
A93: 1930Wate | B93: 2431251 | C93: RR | E93: 14642 | G93: 16027 | H93: The Permutit Company | I93: Eric Leighton Holmes | J93: Great Britain | K93: 14279
A94: 1930Wate | B94: 2469472 | C94: RR | E94: 14684 | G94: 16566 | H94: The Permutit Company | I94: Frederick C. Nachod, William Wood
A95: 1930Wate | B95: 2472616 | C95: RR | E95: 14875 | G95: 16594 | H95: The Permutit Company | I95: William Geroge Prescott, Ewart Ingham Akeroyd, Eric Leighton Holmes | J95: Great Britain 11/12/1943
A96: 1930Wate | B96: 2494784 | C96: RR | E96: 14960 | G96: 16818 | H96: The Permutit Company | I96: Howard L. Tiger
A97: 1930Wate | B97: 2512053 | C97: RR | E97: 14962 | G97: 16972 | H97: The Permutit Company | I97: Calvin Calmon
A98: 1930Wate | B98: 2518956 | C98: RR | E98: 15167 | G98: 17028 | H98: The Permutit Company | I98: Sidney Sussman
A99: 1930Wate | B99: 2447135 | C99: RR | E99: 15511 | G99: 16300 | H99: The Permutit Company | I99: Eric Pick, Joseph J. Carlson
A100: 1930Wate | B100: 2463304 | C100: RR | E100: 15511 | G100: 16496 | H100: The Permutit Company | I100: Eric Pick
...

Sheet 1931Fuel
A1: PoolID | B1: Patent | C1: Type of Compulsory Licensing | D1: Serial No. | E1: Application Date | F1: Application Date II | G1: Grant Date | H1: Assignee (if not, inventor name) | I1: Inventor Name | J1: Filed in country | K1: Filing date | L1: Comment
A2: Patents listed in Exhibit A of final judgment, RR:
A3: 1931Fuel | B3: 1807340 | C3: RR | E3: 8828 | G3: 10007 | H3: American Bosch Magneto Corporation | I3: John F. Martin, Frank E Watts
A4: 1931Fuel | B4: 1805874 | C4: RR | E4: 9283 | G4: 10000 | H4: American Bosch Magneto Corporation | I4: Gustave J. Lang, Joseph F. Drennan, Barthold E. Schlesinger
A5: 1931Fuel | B5: 1891369 | C5: RR | E5: 9366 | G5: 10581 | H5: American Bosch Magneto Corporation | I5: Leslie F. Curtis
A6: 1931Fuel | B6: 1810367 | C6: RR | E6: 9520 | G6: 10028 | H6: American Bosch Magneto Corporation | I6: John F. Martin
A7: 1931Fuel | B7: 1818721 | C7: RR | E7: 9520 | G7: 10084 | H7: American Bosch Magneto Corporation | I7: Gustave J. Lang, John F. Martin
A8: 1931Fuel | B8: 1887522 | C8: RR | E8: 9552 | G8: 10546 | H8: American Bosch Magneto Corporation | I8: Wolfgang E. Schwarzman
A9: 1931Fuel | B9: 1890305 | C9: RR | E9: 9577 | G9: 10567 | H9: American Bosch Magneto Corporation | I9: Wolfgang E. Schwarzman
A10: 1931Fuel | B10: 1890306 | C10: RR | E10: 9577 | G10: 10567 | H10: American Bosch Magneto Corporation | I10: Wolfgang E. Schwarzman
A11: 1931Fuel | B11: 1818693 | C11: RR | E11: 9624 | G11: 10084 | H11: American Bosch Magneto Corporation | I11: Frank S. Coe
A12: 1931Fuel | B12: 1887320 | C12: RR | E12: 9724 | G12: 10539 | H12: American Bosch Magneto Corporation | I12: John F. Martin
A13: 1931Fuel | B13: 1890518 | C13: RR | E13: 9724 | G13: 10574 | H13: American Bosch Magneto Corporation | I13: Gustave J. Lang, John F. Martin
A14: 1931Fuel | B14: 1837231 | C14: RR | E14: 9754 | G14: 10217 | H14: American Bosch Magneto Corporation | I14: Arthur T. Murray, John F. Martin
... A59: 1931Fuel | B59: 1979317 | C59: RR | E59: 10674 | G59: 11267 | H59: United American Bosch Corporation | I59: Leslie F. Curtis
A60: 1931Fuel | B60: 1979453 | C60: RR | E60: 10674 | F60: (RN) 1934/4/28 | G60: 11267 | H60: United American Bosch Corporation | I60: William F. Cotter, Marion E. Bond
A61: 1931Fuel | B61: 1980038 | C61: RR | E61: 10674 | G61: 11267 | H61: United American Bosch Corporation | I61: William F. Cotter, Marion E. Bond
A62: 1931Fuel | B62: 1935610 | C62: RR | E62: 10695 | G62: 10917 | H62: United American Bosch Corporation | I62: Louis Beeh, Wolfgang E. Schwarzmann
A63: 1931Fuel | B63: 1951744 | C63: RR | E63: 10710 | G63: 11036 | H63: United American Bosch Corporations | I63: Hermann Waker
A64: 1931Fuel | B64: 1938655 | C64: RR | E64: 10728 | G64: 10938 | H64: United American Bosch Corporation | I64: Robert H. Gibson
A65: 1931Fuel | B65: 1968930 | C65: RR | E65: 10738 | G65: 11176 | H65: United American Bosch Corporation | I65: William F. Cotter, Ludvig P. Kongsted
A66: 1931Fuel | B66: 1944687 | C66: RR | E66: 10739 | G66: 10980 | H66: United American Bosch Corporation | I66: Ken L. Henderson
A67: 1931Fuel | B67: 1950986 | C67: RR | E67: 10746 | G67: 11029 | H67: United American Bosch Corporation | I67: Ludvig P. Kongsted
A68: 1931Fuel | B68: 1952321 | C68: RR | E68: 10746 | G68: 11043 | H68: United American Bosch Corporation | I68: Gustave J. Lang, Louis Beeh, John F. Martin
A69: 1931Fuel | B69: 2005098 | C69: RR | E69: 10779 | G69: 11491 | H69: United American Bosch Corporation | I69: Carl August Mayer
A70: 1931Fuel | B70: 1969866 | C70: RR | E70: 10781 | G70: 11183 | H70: United American Bosch Corporation | I70: Julius E. Wild, Wolfgang E. Schwarzmann
A71: 1931Fuel | B71: 1944590 | C71: RR | E71: 10794 | G71: 10980 | H71: United American Bosch Corporation | I71: Louis Beeh
A72: 1931Fuel | B72: 1954088 | C72: RR | E72: 10821 | G72: 11057 | H72: United American Bosch Corporation | I72: John F. Martin, Hermann Waker
... A123: 1931Fuel | B123: 2239650 | C123: RR | E123: 13227 | G123: 13626 | H123: American Bosch Corporation | I123: John F. Martin, William D. Crocker
A124: 1931Fuel | B124: 2250809 | C124: RR | D124: (O) 324778 - 2239650 (Di) 384483 | E124: 13227 | F124: 13594 | G124: 13724 | H124: American Bosch Corporation | I124: John F. Martin, William D. Crocker
A125: 1931Fuel | B125: 2250682 | C125: RR | E125: 13278 | G125: 13724 | H125: American Bosch Corporation | I125: Wolfgang E. Schwarzmann
A126: 1931Fuel | B126: 2243416 | C126: RR | E126: 13284 | G126: 13661 | H126: American Bosch Corporation | I126: William D. Crocker
A127: 1931Fuel | B127: 2243418 | C127: RR | E127: 13284 | G127: 13661 | H127: American Bosch Corporation | I127: William D. Crocker
A128: 1931Fuel | B128: 2240804 | C128: RR | E128: 13297 | G128: 13640 | H128: American Bosch Corporation | I128: Wolfgang E. Schwarzmann
A129: 1931Fuel | B129: 2269651 | C129: RR | E129: 13385 | G129: 13892 | H129: American Bosch Corporation | I129: William D. Crocker
A130: 1931Fuel | B130: 2246901 | C130: RR | E130: 13476 | G130: 13689 | H130: American Bosch Corporation | I130: Wolfgang E. Schwarzmann
A131: 1931Fuel | B131: 2253201 | C131: RR | E131: 13490 | G131: 13745 | H131: American Bosch Corporation | I131: Wolfgang E. Schwarzmann, Charles Strniste
A132: 1931Fuel | B132: 2267396 | C132: RR | E132: 13497 | G132: 13871 | H132: American Bosch Corporation | I132: William D. Crocker
A133: 1931Fuel | B133: 2259229 | C133: RR | E133: 13546 | G133: 13801 | H133: American Bosch Corporation | I133: Wolfgang E. Schwarzmann
A134: 1931Fuel | B134: 2286301 | C134: RR | E134: 13573 | G134: 14046 | H134: American Bosch Corporation | I134: Ben G. Parsons
A135: 1931Fuel | B135: 2286302 | C135: RR | E135: 13573 | G135: 14046 | H135: American Bosch Corporation | I135: Ben G. Parsons
A136: 1931Fuel | B136: 2298652 | C136: RR | E136: 13630 | G136: 14165 | H136: American Bosch Corporation | I136: Wolfgang E. Schwarzmann, Charles Strniste
... A154: 1931Fuel | B154: 2394234 | C154: RR | E154: 14547 | G154: 15376 | H154: American Bosch Corporation | I154: William D. Crocker, Frank S. Coe
A155: 1931Fuel | B155: 2441922 | C155: RR | D155: 511002 | E155: 14568 | G155: 16209 | H155: American Bosch Corporation | I155: Wolfgang E. Schwarzmann, Edward M. Bach
A156: 1931Fuel | B156: 2393900 | C156: RR | E156: 14572 | G156: 15369 | H156: American Bosch Corporation | I156: Charles E. Guertin
A157: 1931Fuel | B157: 2436797 | C157: RR | E157: 14605 | G157: 16132 | H157: Deschamps Fuel Injection Corporation | I157: Desire J. Deschamps, Douglas C. Clarke, Frank E. Ferguson
A158: 1931Fuel | B158: 2395629 | C158: RR | E158: 14721 | G158: 15397 | H158: American Bosch Corporation | I158: Ludvig P. Kongsted
A159: 1931Fuel | B159: 2420407 | C159: RR | E159: 14740 | G159: 15838 | H159: American Bosch Corporation | I159: Oscar L. Bachman
A160: 1931Fuel | B160: 2434492 | C160: RR | D160: (O) 557710 (Di) 611788 | E160: 14890 | F160: 15208 | G160: 16083 | H160: American Bosch Corporation | I160: Alvah O. Ericksberg
A161: 1931Fuel | B161: 2434511 | C161: RR | E161: 14890 | G161: 16083 | H161: American Bosch Corporation | I161: Joseph T. Osterman, Alvah O. Ericksberg
A162: 1931Fuel | B162: 2380607 | C162: RR | E162: 14994 | G162: 15187 | H162: American Bosch Corporation | I162: Carl H. Nystrom
A163: 1931Fuel | B163: 2449397 | C163: RR | D163: 575418 | E163: 15006 | G163: 16328 | H163: American Bosch Corporation | I163: Richard W. Lamphere
A164: 1931Fuel | B164: 2503406 | C164: RR | D164: 575873 | E164: 15008 | G164: 16902 | H164: American Bosch Corporation | I164: Joseph T. Osterman, Alvah O. Ericksberg
A165: 1931Fuel | B165: 2485913 | C165: RR | D165: 575874 | E165: 15008 | G165: 16734 | H165: American Bosch Corporation | I165: Joseph T. Osterman
A166: 1931Fuel | B166: 2531202 | C166: RR | D166: 591914 | E166: 15099 | G166: 17126 | H166: Deschamps Fuel Injection Corporation | I166: Desire J. Deschamps | L166: See Packet for Ownership Details
A167: 1931Fuel | B167: 2544561 | C167: RR | D167: 598754 | E167: 15137 | G167: 17231 | H167: American Bosch Corporation | I167: Wolfgang E. Meyer
A168: 1931Fuel | B168: 2467531 | C168: RR | D168: 603170 | E168: 15160 | G168: 16545 | H168: American Bosch Corporation | I168: Richard W. Lamphere, Joseph T. Osterman
A169: 1931Fuel | B169: 2429806 | C169: RR | E169: 15233 | G169: 16006 | H169: Deschamps Fuel Injection Corporation | I169: Desire J. Deschamps
A170: 1931Fuel | B170: 2441277 | C170: RR | D170: 622223 | E170: 15261 | G170: 16202 | H170: American Bosch Corporation | I170: Richard W. Lamphere
A171: 1931Fuel | B171: 2508524 | C171: RR | D171: 635371 | E171: 15324 | G171: 16944 | H171: American Bosch Corporation | I171: Gregor L. Lang
A172: 1931Fuel | B172: 2567753 | C172: RR | D172: 652137 | E172: 15404 | G172: 17420 | H172: American Bosch Corporation | I172: Heraclio Alfaro
A173: 1931Fuel | B173: 1964948 | C173: RR | H173: The American Brass Company | I173: Walter R. Hibbard, Ellsworth T. Candee | L173: Content Does Not Match; Dates Do Not Match; Patent # Also Regresses; Probably an Error
A175: 1931Fuel | B175: Exhibit A | D175: 503470 | E175: 14510
A176: 1931Fuel | B176: Exhibit A | D176: 575872 | E176: 15008
A177: 1931Fuel | B177: Exhibit A | D177: 587160 | E177: 15072
A178: 1931Fuel | B178: Exhibit A | D178: 590941 | E178: 15093
A179: 1931Fuel | B179: Exhibit A | D179: 615578 | E179: 15229
A180: 1931Fuel | B180: Exhibit A | D180: 618635 | E180: 15244
A181: 1931Fuel | B181: Exhibit A | D181: 618745 | E181: 15244
A182: 1931Fuel | B182: Exhibit A | D182: 618746 | E182: 15244
A183: 1931Fuel | B183: Exhibit A | D183: 621463 | E183: 15258
A185: Notes
A186: Vaughan (p. 158): "According to a complaint of 1942, American Bosch Corporation and certain foreign companies exchanged patent licenses and divided sales territories relating to these products. A consent decree of the same date cancelled various agreements; required unrestricted licenses for certain patented products without conditions, except the payment of a reasonable royalty after the war; and enjoined American Bosch from transferring patent rights except with the court's approval."
A188: Firms: American Bosch Corporation, Robert Bosch, GMBH (German firm), CAV Bosch (UK firm), Ateliers de Construction Lavalette (French firm).
A189: Foreign firms: Yes.
A190: Start year: 1931
A191: End year: 1942 (consent decree)
A192: Grantbacks: Yes (Complaint, p. 16: "in addition to those products described in (e) above, manufacturer by Robert Bosch should be manufactured in American Territory, Robert Bosch should offer American Bosch, on terms to be agreed upon, the exclusive manufacturing rights for the American Territory as to such product")
A193: Independent licensing:
A194: Open licensing: No
A195: Number of licensees: 0
A196: Compulsory licensing: RR
A197: Patent holding company: No
... A213: Pool members (added patents):
A214: American Bosch Corporation | B214: 1931
A215: Robert Bosch GMBH (German) | B215: 1931
A216: CAV Bosch (UK) | B216: 1931
A217: Ateliers de Construction Lavelette (France) | B217: 1931
A219: License restrictions
A220: Prevented US domestic competition: "that Robert Bosch should impede and suppress competition by American companies in opposition to American Bosch in the business of manufacturing and selling fuel injection equipment by, among other means, (1) causing distributors and service stations throughout the world which handle fuel injection equipment manufactured by Robert Bosch and American Bosch, to refuse to distribute and service fuel injection equipment manufactured in the United States by companies competitive with American Bosch; and (2) waiving minimum royalties payable to Robert Bosch under a Diesel engine license granted a Diesel engine manufacturer in the United States, so long as the Diesel engine manufacturer should equip his entire production of Diesel engines exclusively with American Bosch fuel injection equipment" (complaint, p. 10-11).

Sheet 1931Mill
A1: PoolID | B1: Patent | C1: Licensing Type | D1: Application Date | E1: Grant Date | F1: Assignee (Inventor)
A2: Patents listed in Exhibit B of final judgment (owned by Cincinnati Grinders, Inc.):
A3: 1931Mill | B3: 2076859 | C3: RR | D3: 11473 | E3: 12156 | F3: Nenninger
A4: 1931Mill | B4: 2076865 | C4: RR | D4: 11684 | E4: 12156 | F4: Romaine
A5: 1931Mill | B5: 2076944 | C5: RR | D5: 10879 | E5: 12156 | F5: Howe
A6: 1931Mill | B6: 2079717 | C6: RR | D6: 11344 | E6: 12184 | F6: Roehm et al.
A7: 1931Mill | B7: 2083774 | C7: RR | D7: 11455 | E7: 12219 | F7: Campbell
A8: 1931Mill | B8: 2085303 | C8: RR | D8: 10374 | E8: 12233 | F8: Ernst
A9: 1931Mill | B9: 2089099 | C9: RR | D9: 11695 | E9: 12268 | F9: Roehm et al.
A10: 1931Mill | B10: 2090992 | C10: RR | D10: 11389 | E10: 12289 | F10: Archea
A11: 1931Mill | B11: 2091000 | C11: RR | D11: 11773 | E11: 12289 | F11: Hoier
A12: 1931Mill | B12: 2101544 | C12: RR | D12: 11773 | E12: 12394 | F12: Isler
A13: 1931Mill | B13: 2101712 | C13: RR | D13: 12080 | E13: 12394 | F13: Johansen
A14: 1931Mill | B14: 2107063 | C14: RR | D14: 12157 | E14: 12450 | F14: Roehm
... A46: 1931Mill | B46: 2257849 | C46: RR | D46: 13228 | E46: 13794 | F46: Martellotti
A47: 1931Mill | B47: 2260098 | C47: RR | E47: 13808 | F47: Blood
A48: 1931Mill | B48: 2263635 | C48: RR | E48: 13843 | F48: Larsen
A49: 1931Mill | B49: 2275783 | C49: RR | E49: 13948 | F49: Martellotti
A50: 1931Mill | B50: 2280760 | C50: RR | E50: 13990 | F50: Martellotti
A51: 1931Mill | B51: 2281774 | C51: RR | E51: 14004 | F51: Larsen
A52: 1931Mill | B52: 2289110 | C52: RR | E52: 14067 | F52: Ernst et al.
A53: 1931Mill | B53: 2290590 | C53: RR | E53: 14081 | F53: Hawlet et al.
A54: 1931Mill | B54: 2302575 | C54: RR | E54: 14200 | F54: Romaine at al.
A55: 1931Mill | B55: 2308688 | C55: RR | E55: 14263 | F55: Hassman
A56: 1931Mill | B56: 2308708 | C56: RR | E56: 14263 | F56: Nenninger and Hassman
A57: 1931Mill | B57: 2308728 | C57: RR | E57: 14263 | F57: Vancil and Trible
A58: 1931Mill | B58: 2320353 | C58: RR | E58: 14396 | F58: Ernst & Martellotti
... A126: 1931Mill | B126: 2660985 | C126: RR | E126: 18232 | F126: Ernst
A128: Patents listed in Exhibit B final judgment (owned by Kearney-Trecker):
A129: 1931Mill | B129: 2077434 | C129: RR | D129: 11553 | E129: 12163 | F129: Parsons
A130: 1931Mill | B130: 2077435 | C130: RR | D130: 11599 | E130: 12163 | F130: Parsons
A131: 1931Mill | B131: 2078859 | C131: RR | D131: 11404 | E131: 12170 | F131: Lapham
A132: 1931Mill | B132: 2081288 | C132: RR | D132: 11458 | E132: 12198 | F132: Armitage
A133: 1931Mill | B133: 2085272 | C133: RR | D133: 11525 | E133: 12233 | F133: Pohl
A134: 1931Mill | B134: 2085888 | C134: RR | D134: 10554 | E134: 12240 | F134: Armitage
A135: 1931Mill | B135: 2110173 | C135: RR | D135: 10619 | E135: 12485 | F135: Pohl et al.
A136: 1931Mill | B136: 2115058 | C136: RR | D136: 11166 | E136: 12534 | F136: Armitage
A137: 1931Mill | B137: 2118357 | C137: RR | D137: 11744 | E137: 12562 | F137: Parsons et al.
A138: 1931Mill | B138: 2118358 | C138: RR | D138: 11996 | E138: 12562 | F138: Parsons et al.
A139: 1931Mill | B139: 2141263 | C139: RR | D139: 11655 | E139: 12779 | F139: Curtis
A140: 1931Mill | B140: 2153424 | C140: RR | D140: 12333 | E140: 12877 | F140: MacRae
... A154: 1931Mill | B154: 2242445 | C154: RR | D154: 12103 | E154: 13654 | F154: Armitage
A155: 1931Mill | B155: 2244413 | C155: RR | E155: 13668 | F155: Armitage
A156: 1931Mill | B156: 2244985 | C156: RR | E156: 13675 | F156: Armitage et al.
A157: 1931Mill | B157: 2263404 | C157: RR | E157: 13836 | F157: Armitage et al.
A158: 1931Mill | B158: 2275241 | C158: RR | E158: 13941 | F158: Armitage et al.
A159: 1931Mill | B159: 2293880 | C159: RR | E159: 14116 | F159: Armitage et al.
A160: 1931Mill | B160: 2319480 | C160: RR | E160: 14382 | F160: Saving et al.
A161: 1931Mill | B161: 2332684 | C161: RR | E161: 14543 | F161: Armitage
A162: 1931Mill | B162: 2335304 | C162: RR | E162: 14578 | F162: Parsons
A163: 1931Mill | B163: 2335305 | C163: RR | E163: 14578 | F163: Parsons
A164: 1931Mill | B164: 2337223 | C164: RR | E164: 14599 | F164: Armitage
A165: 1931Mill | B165: 2339102 | C165: RR | E165: 14620 | F165: Parsons
A166: 1931Mill | B166: 2340210 | C166: RR | E166: 14634 | F166: Armitage et al.
... A226: 1931Mill | B226: 2657616 | C226: RR | E226: 17900 | F226: Armitage et al.
A228: Notes
A229: Vaughan (pp. 126): "A complaint of 1954 charged three companies with license agreements by which they divided manufacturing fields among themselves, refused licenses to other except upon restrictive terms, refrained from patent infringement suits against each other, and required similar immunity from their assignees and licensees. A consent decree of the same date enjoined these restrictive practices, required these companies to grant licenses on a reasonable royalty basis and to provide specifications and drawings for five years upon application of any licensee."
A231: Firms: Cincinnati Milling Machine Company (initial firm), Kearney & Trecker Corporation (later added to pool), Cincinnati Grinders (a patent holding company), Ingersoll Milling Machine (initial firm) Company, Vickers.
A232: Foreign firms: No.
A233: Start year: 1931 (Complaint, p. 4).
A234: End year: 1954 (final judgment).
A235: Grantbacks: No evidence of.
A236: Independent licensing:
A237: Open licensing: No. "To refuse to grant licenses under the aforesaid patents to others, except upon restrictive terms and condition" (Complaint, p. 5).
A238: Number of licensees: 2 (Vickers and Kent-Owens Machine Company).
A239: Compulsory licensing: RAND licensing on patents listed in Exhibit B (p. 5 of final judgment).
A240: Patent holding company: Yes: "Cincinnati Grinders, a wholly owned subsidiary of defendant Cincinnait, is not an operating company, but is utliized by defendant Cincinnati as a patent holding coporation" (Complaint, p. 2).
... A249: Licensees (who didn’t added patents):
A250: Vickers | B250: 12570
A251: Kent-Owens Machine Company | B251: 13291
A253: Pool members:
A254: Cincinnati Milling Machine Company | B254: 10065
A255: Ingersoll | B255: 10065
A256: Kearney | B256: 10879

Sheet 1932Phar
A1: PoolID | B1: Patent | C1: Type of Compulsory Licensing | D1: Serial No. | E1: Application Date | F1: Application Date II | G1: Grant Date | H1: Assignee (if not, inventor name) | I1: Inventor Name | J1: Filed in country | K1: Filing date | L1: Comment
A2: Patents listed in Exhibit C of Final Judgment (royalty-free licensing):
A3: 1932Phar | B3: 2021872 | C3: RF | E3: 10058 | G3: 11645 | H3: Merck & Co. | I3: Randolph T. Major, William L. Ruigh
A4: 1932Phar | B4: 2049442 | C4: RF | E4: 10420 | G4: 11904 | H4: Merck & Co. | I4: Thomas Haegland
A5: 1932Phar | B5: 2044800 | C5: RF | E5: 10764 | G5: 11862 | H5: Merck & Co. | I5: Randolph T. Major, William L. Ruigh
A6: 1932Phar | B6: 2044801 | C6: RF | E6: 10764 | F6: 10842 | G6: 11862 | H6: Merck & Co. | I6: Randolph T. Major, William L. Ruigh
A7: 1932Phar | B7: 2104726 | C7: RF | E7: 11094 | G7: 12429 | H7: Merck & Co. | I7: Carl R. Addinall, Randolph T. Major
A8: 1932Phar | B8: 2104753 | C8: RF | E8: 11275 | G8: 12429 | H8: Merck & Co. | I8: Randolph T. Major, Albert B. Boese
A9: 1932Phar | B9: 2089197 | C9: RF | E9: 11361 | G9: 12275 | H9: Merck & Co. | I9: William H. Engels, John Weijlard
A10: 1932Phar | B10: 2164316 | C10: RF | E10: 11367 | G10: 12968 | H10: Merck & Co. | I10: William H. Engels
A11: 1932Phar | B11: 2209769 | C11: RF | E11: 11421 | G11: 13360 | H11: Merck & Co. | I11: William H. Engels, John Weijlard
A12: 1932Phar | B12: 2118054 | C12: RF | E12: 11509 | G12: 12562 | H12: Merck & Co. | I12: Randolph T. Major, Howard T. Bonnett
A13: 1932Phar | B13: 2135521 | C13: RF | E13: 11660 | G13: 12730 | H13: Merck & Co. | I13: Randolph T. Major, Howard T. Bonnett
A14: 1932Phar | B14: 2072913 | C14: RF | E14: 11771 | G14: 12121 | H14: Merck & Co. | I14: John Weijlard
A15: 1932Phar | B15: 2176113 | C15: RF | E15: 11771 | G15: 13073 | H15: Merck & Co. | I15: John Weijlard
A16: 1932Phar | B16: 2168379 | C16: RF | E16: 11892 | G16: 13003 | H16: Merck & Co. | I16: John Weijlard, Joseph R. Stevens
A17: 1932Phar | B17: 2088590 | C17: RF | E17: 11899 | G17: 12268 | H17: Merck & Co. | I17: William H. Engels, Harold J. Becker
A18: 1932Phar | B18: 2163643 | C18: RF | E18: 11906 | G18: 12961 | H18: Merck & Co. | I18: Alphonse Walti
... A61: 1932Phar | B61: 2372690 | C61: RF | E61: 13468 | G61: 15068 | H61: Merck & Co. | I61: Eric T. Stiller
A63: Patents listed in Exhibit D of Final Judgment, RF licensing:
A64: 1932Phar | B64: 1935529 | C64: RF | E64: 9509 | G64: 10910 | I64: Otto von Keussler, Daniel Peters | J64: Germany | K64: 9150
A65: 1932Phar | B65: 1941647 | C65: RF | E65: 9696 | G65: 10959 | I65: Otto Wolfes | J65: Germany | K65: 9367
A66: 1932Phar | B66: 1894162 | C66: RF | E66: 9969 | G66: 10602 | I66: Otto Dalmer, Claus Diehl | J66: Germany | K66: 9624
A67: 1932Phar | B67: 2098954 | C67: RF | E67: 10960 | G67: 12373 | H67: Merck & Co. | I67: Otto Dalmer, Claus Diehl, Hartmann Pieper | J67: Germany | K67: 10595
A68: 1932Phar | B68: 2086562 | C68: RF | E68: 11128 | G68: 12247 | H68: Merck & Co. | I68: Willy Heinrich Küssner | J68: Germany | K68: 10765
A69: 1932Phar | B69: 2114306 | C69: RF | D69: (O) 731464 (Di) 96969 | E69: 11128 | F69: 11920 | G69: 12527 | H69: Merck & Co. | I69: Willy Heinrich Küssner | J69: Germany | K69: 10765
A70: 1932Phar | B70: 2085009 | C70: RF | E70: 11148 | G70: 12233 | H70: Merck & Co. | I70: Otto Dalmer, John Niemann | J70: Germany | K70: 10827
A71: 1932Phar | B71: 2145249 | C71: RF | D71: (O) 734510 (Di) 101410 | E71: 11148 | F71: 11949 | G71: 12814 | H71: Merck & Co. | I71: Otto Dalmer, John Niemann | J71: Germany | K71: 10827
A72: 1932Phar | B72: 2094000 | C72: RF | E72: 11215 | G72: 12324 | H72: Merck & Co. | I72: Otto Dalmer, Fritz von Werder | J72: Germany | K72: 10857
A73: 1932Phar | B73: 2133977 | C73: RF | D73: (O) 744168 - 2094000 (Di) 128160 | E73: 11215 | F73: 12111 | G73: 12716 | H73: Merck & Co. | I73: Otto Dalmer, Fritz von Werder | J73: Germany | K73: 10857
A74: 1932Phar | B74: 2078237 | C74: RF | E74: 11247 | G74: 12170 | H74: Merck & Co. | I74: Otto Dalmer, Hermann Wieters | J74: Germany | K74: 10882
A75: 1932Phar | B75: 2119527 | C75: RF | E75: 11340 | G75: 12576 | H75: Merck & Co. | I75: Otto Dalmer, Fritz von Werder | J75: Germany | K75: 10979
A76: 1932Phar | B76: 2149279 | C76: RF | E76: 11508 | G76: 12849 | H76: Merck & Co. | I76: Otto Dalmer, Eugen Walter | J76: Germany | K76: 11145
A77: 1932Phar | B77: 2370015 | C77: RF | D77: (O) 49822 (Co) 373602 | E77: 11640 | F77: 13522 | G77: 15026 | H77: Merck & Co. | I77: Otto Dalmer, Claus Diehl, Hartmann Pieper | J77: Germany | K77: 10797
A78: 1932Phar | B78: 2370015 | C78: RF | D78: (O) 49822 (Co) 373602 | E78: 11640 | F78: 13522 | G78: 15026 | H78: Merck & Co. | I78: Otto Dalmer, Claus Diehl, Hartmann Pieper | J78: Germany | K78: 10797
A79: 1932Phar | B79: 2145907 | C79: RF | E79: 11653 | G79: 12821 | H79: Merck & Co. | I79: Otto Wolfes | J79: Germany | K79: 11288
A80: 1932Phar | B80: 2127547 | C80: RF | E80: 11829 | G80: 12653 | H80: Merck & Co. | I80: Otto Wolfes, Otto Hromatka | J80: Germany | K80: 11474
A81: 1932Phar | B81: 2163629 | C81: RF | E81: 11905 | G81: 12961 | H81: Merck & Co. | I81: Bernhard Rapp, Friedrich K. Russow | J81: Germany | K81: 11547
A82: 1932Phar | B82: 2182791 | C82: RF | D82: (O) 101430 (Di) 101429 | E82: 11949 | F82: 11949 | G82: 13129 | H82: Merck & Co. | I82: Otto Dalmer, Claus Diehl | J82: Germany | K82: 10569
A83: 1932Phar | B83: 2182792 | C83: RF | D83: (O) 101429 (Di) 101430 | E83: 11949 | F83: 11949 | G83: 13129 | H83: Merck & Co. | I83: Otto Dalmer, Claus Diehl | J83: Germany | K83: 10569
A84: 1932Phar | B84: 2189830 | C84: RF | E84: 12011 | G84: 13192 | H84: Merck & Co. | I84: Otto Zima | J84: Germany | K84: 11651
A85: 1932Phar | B85: 2190167 | C85: RF | E85: 12011 | G85: 13192 | H85: Merck & Co. | I85: Otto Zima | J85: Germany | K85: 11701
A86: 1932Phar | B86: 2170127 | C86: RF | E86: 12110 | G86: 13017 | H86: Merck & Co. | I86: Otto Dalmer, Fritz von Werder | J86: Germany | K86: 11760
A87: 1932Phar | B87: 2221828 | C87: RF | E87: 12149 | G87: 13472 | H87: Merck & Co. | I87: Otto Wolfes, Otto Hromatka | J87: Germany | K87: 11803
A88: 1932Phar | B88: 2189778 | C88: RF | E88: 12249 | G88: 13192 | H88: Merck & Co. | I88: Otto Dalmer, Kurt Heyns | J88: Germany | K88: 11887
A89: 1932Phar | B89: 2190377 | C89: RF | E89: 12249 | G89: 13192 | H89: Merck & Co. | I89: Otto Dalmer, Kurt Heyns | J89: Germany | K89: 11887
A90: 1932Phar | B90: 2176063 | C90: RF | E90: 12290 | G90: 13073 | H90: Merck & Co. | I90: Otto Dalmer, Claus Diehl, Eugen Walter | J90: Germany | K90: 11932
A91: 1932Phar | B91: 2160867 | C91: RF | E91: 12319 | G91: 12940 | H91: Merck & Co. | I91: Otto Hromatka | J91: Germany | K91: 11957
A92: 1932Phar | B92: 2235638 | C92: RF | E92: 12331 | G92: 13591 | H92: Merck & Co. | I92: Otto Hromatka | J92: Germany | K92: 11970
A93: 1932Phar | B93: 2259925 | C93: RF | D93: (O) 171480 (Co) 251598 | E93: 12354 | F93: 12801 | G93: 13808 | H93: Merck & Co. | I93: Otto Dalmer, Claus Diehl, Hartmann Pieper | J93: Germany | K93: 10595 | L93: continuation in part - alluded to in the passage
A94: 1932Phar | B94: 2235862 | C94: RF | E94: 12465 | G94: 13598 | H94: Merck & Co. | I94: Otto Zima | J94: Germany | K94: 12106
A95: 1932Phar | B95: 2235884 | C95: RF | E95: 12597 | G95: 13598 | H95: Merck & Co. | I95: Walter John, Otto Dalmer | J95: Germany | K95: 12235
A96: 1932Phar | B96: 2259936 | C96: RF | E96: 12625 | G96: 13808 | H96: Merck & Co. | I96: Fritz Jung | J96: Germany | K96: 12264
A97: 1932Phar | B97: 2235661 | C97: RF | E97: 12647 | G97: 13591 | H97: Merck & Co. | I97: Otto Wolfes, Otto Hromatka | J97: Germany | K97: 11474
A98: 1932Phar | B98: 2212531 | C98: RF | E98: 12702 | G98: 13388 | H98: Merck & Co. | I98: Fritz von Werder | J98: Germany | K98: 12340
A99: 1932Phar | B99: 2212532 | C99: RF | E99: 12702 | G99: 13388 | H99: Merck & Co. | I99: Fritz von Werder | J99: Germany | K99: 12340
A100: 1932Phar | B100: 2259925 | C100: RF | E100: 12801 | G100: 13808 | H100: Merck & Co. | I100: Otto Dalmar, Claus Diehl, Hartmann Pieper | J100: Germany | K100: 10595
A101: 1932Phar | B101: 2289761 | C101: RF | E101: 12801 | G101: 14074 | H101: Merck & Co. | I101: Claus Diehl | J101: Germany | K101: 12443
A102: 1932Phar | B102: 2183553 | C102: RF | E102: 12806 | G102: 13136 | I102: Franz Erich Eidmann | J102: Germany | K102: 12446
A103: 1932Phar | B103: 2229573 | C103: RF | E103: 12878 | G103: 13535 | H103: Merck & Co. | I103: Fritz Jung | J103: Germany | K103: 12542
A104: 1932Phar | B104: 2229574 | C104: RF | E104: 12878 | G104: 13535 | H104: Merck & Co. | I104: Fritz Jung | J104: Germany | K104: 12549
A105: 1932Phar | B105: 2354317 | C105: RF | E105: 12912 | G105: 14816 | H105: Merck & Co. | I105: Otto Hromatka | J105: Germany | K105: 12552
A106: 1932Phar | B106: 2274449 | C106: RF | E106: 12915 | G106: 13934 | H106: Merck & Co. | I106: Walter John, Philipp Günther | J106: Germany | K106: 12552
A107: 1932Phar | B107: 2230659 | C107: RF | E107: 13023 | G107: 13549 | H107: Merck & Co. | I107: Fritz von Werder | J107: Germany | K107: 12689
A108: 1932Phar | B108: 2245147 | C108: RF | E108: 13112 | G108: 13675 | H108: Merck & Co. | I108: Walter John, Philipp Günther | J108: Germany | K108: 12758
A109: 1932Phar | B109: 2358286 | C109: RF | E109: 13119 | G109: 14865 | H109: Merck & Co. | I109: Otto Hromatka | J109: Germany | K109: 12814
A110: 1932Phar | B110: 2358287 | C110: RF | D110: (O) 307265 (Di) 395444 | E110: 13119 | F110: 13661 | G110: 14865 | H110: Merck & Co. | I110: Otto Hromatka | J110: Germany | K110: 12814
A111: 1932Phar | B111: 2422625 | C111: RF | D111: 308827 | E111: 13129 | G111: 15873 | H111: vested in the Attorney General of the United States | I111: Walter John | J111: Germany | K111: 12963 | L111: patent expires 1959/6/29
A112: 1932Phar | B112: 2296677 | C112: RF | E112: 13187 | G112: 14144 | H112: Merck & Co. | I112: Wilhelm Küssner | J112: Germany | K112: 12771
A113: 1932Phar | B113: 2359311 | C113: RF | E113: 13663 | G113: 14886 | H113: Merck & Co. | I113: Otto Hromatka | J113: Germany | K113: 13331
A114: 1932Phar | B114: 2345605 | C114: RF | E114: 13690 | G114: 14704 | H114: Merck & Co. | I114: Walter John, Philipp Günther | J114: Germany | K114: 12758
A115: 1932Phar | B115: 2343773 | C115: RF | E115: 13713 | G115: 14737 | H115: Merck & Co. | I115: Otto Hromatka | J115: Germany | K115: 12814
A116: 1932Phar | B116: 2392534 | C116: RF | D116: 403046 | E116: 13713 | G116: 15348 | H116: vested in the Alien Property Custodian | I116: Otto von Keussler | J116: Poland | K116: 13289
A119: 1932Phar | B119: Exhibit C - Subdivision 1 | D119: 380668
A120: 1932Phar | B120: Exhibit D - Subdivision 1 | D120: 331454
A121: 1932Phar | B121: Exhibit D - Subdivision 1 | D121: 346569
A122: 1932Phar | B122: Exhibit D - Subdivision 1 | D122: 377673
A123: 1932Phar | B123: Exhibit D - Subdivision 2 | D123: 227388 | E123: 12659
A124: 1932Phar | B124: Exhibit D - Subdivision 2 | D124: 256387 | E124: 12828
A125: 1932Phar | B125: Exhibit D - Subdivision 2 | D125: 266140 | E125: 12878
A126: 1932Phar | B126: Exhibit D - Subdivision 2 | D126: 304389 | E126: 13101
A127: 1932Phar | B127: Exhibit D - Subdivision 2 | D127: 344564 | E127: 13339
A128: 1932Phar | B128: Exhibit D - Subdivision 2 | D128: 346568 | E128: 13350
A129: 1932Phar | B129: Exhibit D - Subdivision 2 | D129: 373603 | E129: 13522
A130: 1932Phar | B130: Exhibit D - Subdivision 2 | D130: 375363 | E130: 13535
A131: 1932Phar | B131: Exhibit D - Subdivision 2 | D131: 387542 | E131: 13612
A133: 1932Phar | B133: Exhibit C - Subdivision 3 | D133: 6482 | E133: 11367
A134: 1932Phar | B134: Exhibit C - Subdivision 3 | D134: 24908 | E134: 11477
A135: 1932Phar | B135: Exhibit C - Subdivision 3 | D135: 30149 | E135: 11509
... A165: 1932Phar | B165: Exhibit C - Subdivision 3 | D165: 327993 | E165: 13244
A169: Notes
A170: Vaughan (pp. 157-58): "Another government complaint, in 1943, charged that Merck and Company entered into an agreement with E. Merck Chemical Works of Germany for a division of world markets and an exchange of patents and technological information for pharmaceutical products. A consent decree in 1945 enjoined Merck from giving Merck of Germany any control over its affairs and from exchanging patents with it upon condition of refraining from competition. It further required Merch to license about sixty patents royalty-free and to surrender for license by the alien property custodian its rights to fifty patents formerly owned by the German company."
A172: Firms: Merck & Co., E. Merck (German firm).
A173: Foreign firms: Yes.
A174: Start year: 1932
A175: End year: 1945 (consent decree)
A176: Grantbacks: Yes (Complaint, p. 8: "it was also provided therein that the parties should mutually exchange information and experience regarding their respective processes and improvements relating to designated present products and to future products")
A177: Independent licensing:
A178: Open licensing: No
A179: Number of licensees: 0
...

Sheet 1932Rail
A1: PoolID | B1: Patent | D1: Application Date | E1: Grant Date | F1: Assignee (Inventor) | G1: Primary Class A | H1: Primary Subclass | I1: Secondary Subclass 1a | J1: Secondary Subclass 2a | K1: Secondary Subclass 3a | L1: Secondary Subclass 4a | M1: Secondary Subclass 5a | N1: Secondary Subclass 6a | O1: Secondary Subclass 7a | P1: Secondary Subclass 8a | Q1: Secondary Subclass 9a | R1: Secondary Subclass 10a | S1: Secondary Class B | T1: Secondary Subclass 1b | U1: Secondary Subclass 2b | V1: Secondary Subclass 3b | W1: Secondary Subclass 4b | X1: Secondary Subclass 5b | Y1: Secondary Subclass 6b | Z1: Secondary Class C | AA1: Secondary Subclass 1c | AB1: Secondary Subclass 2c | AC1: Secondary Subclass 3c | AD1: Secondary Subclass 4c | AE1: Secondary Subclass 5c | AF1: Secondary Subclass 6c | AG1: Secondary Subclass 7c | AH1: Secondary Class D | AI1: Secondary Subclass 1d | AJ1: Secondary Subclass 2d | AK1: Secondary Subclass 3d | AL1: Secondary Subclass 4d | AM1: Secondary Subclass 5d | AN1: Secondary Subclass 6d | AO1: Secondary Subclass 7d | AP1: Secondary Subclass 8d | AQ1: Secondary Class E | AR1: Secondary Subclass 1e | AS1: Secondary Subclass 2e | AT1: Secondary Class F | AU1: Secondary Subclass 1f | AV1: Secondary Subclass 2f | AW1: Secondary Subclass 3f
A2: Symington-Gould Corporation patents dedicated to the public (from Final Judgment):
A3: 1932Rail | B3: 2094557 | C3: DP | D3: 10225 | E3: 12324 | F3: Couch (Symington-Gould Corp.)
A4: 1932Rail | B4: 2047192 | C4: DP | D4: 10280 | E4: 11883 | F4: Couch (Symington)
A5: 1932Rail | B5: 2146200 | C5: DP | D5: 10392 | E5: 12821 | F5: Barrows (Symington-Gould Corp.)
A6: 1932Rail | B6: 2205369 | C6: DP | D6: 10392 | E6: 13318 | F6: Barrows (Symington-Gould Corp.)
A7: 1932Rail | B7: 2137151 | C7: DP | D7: 10451 | E7: 12737 | F7: Barrows (Symington-Gould Corp.)
A8: 1932Rail | B8: 2084542 | C8: DP | D8: 10798 | E8: 12226 | F8: Townsend (Symington-Gould Corp.)
A9: 1932Rail | B9: 2084543 | C9: DP | D9: 10884 | E9: 12226 | F9: Townsend (Symington-Gould Corp.)
A10: 1932Rail | B10: 2102102 | C10: DP | D10: 10959 | E10: 12401 | F10: Townsend (Symington-Gould Corp.)
A11: 1932Rail | B11: 2067471 | C11: DP | D11: 11205 | E11: 12065 | F11: Barrows (Symington-Gould Corp.)
A12: 1932Rail | B12: 2108653 | C12: DP | D12: 11263 | E12: 12464 | F12: Couch (Symington-Gould Corp.)
A13: 1932Rail | B13: 2100181 | C13: DP | D13: 11285 | E13: 12380 | F13: Barrows (Symington-Gould Corp.)
A15: Universal Railway Devices Corporation patents forced to be licensed (from Final Judgment):
A16: 1932Rail | B16: 1913076 | C16: RR | D16: 9076 | E16: 10749 | F16: Hall (Universal Attachment Co.)
A17: 1932Rail | B17: 2199339 | C17: RR | D17: 12514 | E17: 13269 | F17: Hall (Universal Railway)
A20: Notes
A21: Vaughan (pp. 192): "Symington-Gould Corporation and Universal Railway Devices Company, owners of patents on railway springs and plates, granted exclusive licenses to American Locomotive. This licensee in turn granted sublicenses to Baldwin Locomotive, Crucible Steel, and five other manufacturers of such products. Symington-Gould acted as the agent for getting orders for these springs and plates from railways and others...Consents judgments in 1947 enjoined these restrictive practices, ordered Symington-Gould to assign claims under eleven patents to the public, and ordered Universal Railway Devices to license its patents and spring plates, until 1947, at reasonable royalties."
A22: Reissue 18266 is patent 1727886
A24: Firms: American Locomotive Company (initial firm, formally Railway Steel Spring Company), Symington Gould Company (initial firm), Universal Railway Devices Company.
A25: Foreign firms: No.
A26: Start year: 1932 (Complaint, p. 8).
A27: End year: 1947 (final judgment).
A28: Grantbacks: Yes; Universal and Symington-Gould filed for patents after 1932
A29: Independent licensing:
A30: Open licensing: unclear but many licensees.
A31: Number of licensees: 9 (American Spiral Spring & Manufacturing Co., American Steel Foundaries, Baldwin Locomotive Works, Crucible Steel Company of America, Fort Pitt Spring Company, Pittsburgh Spring & Steel Company, Pittsburgh Steel Foundry Corporation, Railway & Industrial Spring Association)
A32: Compulsory licensing: Dedicated to public (Symington) and compulsory RAND licensing (Universal).
... A41: Licensees (who didn’t added patents):
A42: American Spriral Spring & Manufacturing Co. | B42: 1937
A43: American Steel Foundries | B43: 1937
A44: Baldwin Locomotive Works | B44: 1937
A45: Crucible Steel Company of America | B45: 1937
A46: Fort Pitt Spring Company | B46: 1937
A47: Pittsburgh Spring & Steel Company | B47: 1937
A48: Union Spring & Manufacturing Company | B48: 1937
A49: Pittsburgh Steel Foundry Corporation | B49: 1937
A50: Railway & Industrial Spring Association | B50: 1937
A52: Pool members (added patents):
A53: Railway Steel Spring Company | B53: 10498
A54: Symington Company | B54: 10498
A55: Universal Draft Gear Attachment Company | B55: 11021

Sheet 1932Text
A1: PoolID | B1: Patent | C1: Type of Compulsory Licensing | D1: Serial No. | E1: Application Date | F1: Application Date II | G1: Grant Date | H1: Assignee (if not, inventor name) | I1: Inventor Name | J1: Filed in country | K1: Filing date | L1: Comment | M1: sequence
A2: Patents listed in Schedule A of Final Judgment, RR:
A3: 1932Text | B3: 2042834 | C3: RR | D3: (A) 322643 (Co) 703318 | E3: 9100 | F3: 10946 | G3: 11841 | H3: Berkshire Knitting Mills | I3: William Donald Eaches | M3: 1
A4: 1932Text | B4: 1907247 | C4: RR | E4: 9590 | G4: 10714 | H4: Berkshire Knitting Mills | I4: Hugo Hemmerich | M4: 1
A5: 1932Text | B5: 1915929 | C5: RR | E5: 9737 | G5: 10770 | H5: Chipman Knitting Mills | I5: Benjamin Haytock, Jr. | M5: 1
A6: 1932Text | B6: 1970935 | C6: RR | E6: 10206 | G6: 11190 | H6: Berkshire Knitting Mills | I6: Hugo Hemmerich | M6: 1
A7: 1932Text | B7: 2032476 | C7: RR | E7: 10239 | G7: 11750 | H7: Berkshire Knitting Mills | I7: Gustav Gastrich | M7: 1
A8: 1932Text | B8: 1992666 | C8: RR | E8: 10301 | G8: 11379 | H8: Berkshire Knitting Mills | I8: Hugo Hemmerich | M8: 1
A9: 1932Text | B9: 2055457 | C9: RR | E9: 10354 | G9: 11953 | H9: Berkshire Knitting Mills | I9: Gustav Gastrich | M9: 1
A10: 1932Text | B10: 2003777 | C10: RR | E10: 10603 | G10: 11477 | H10: Berkshire Knitting Mills | I10: Hans Westkott
A11: 1932Text | B11: 1992667 | C11: RR | E11: 10781 | G11: 11379 | H11: Berkshire Knitting Mills | I11: Alfred E. Ischinger
A12: 1932Text | B12: 2097763 | C12: RR | E12: 11106 | G12: 12359 | H12: Berkshire Knitting Mills | I12: Hugo Hemmerich
A13: 1932Text | B13: 2057199 | C13: RR | E13: 11156 | G13: 11974 | H13: Berkshire Knitting Mills | I13: Joseph D. Marks
A14: 1932Text | B14: 2113805 | C14: RR | E14: 11445 | G14: 12520 | H14: Berkshire Knitting Mills | I14: Hugo Hemmerich
A15: 1932Text | B15: 2091169 | C15: RR | E15: 11632 | G15: 12289 | H15: Berkshire Knitting Mills | I15: Ferdinand K. Thun
A16: 1932Text | B16: 2270853 | C16: RR | E16: 12797 | G16: 13906 | H16: Berkshire Knitting Mills | I16: William E. Sheeler
A17: 1932Text | B17: 2233112 | C17: RR | E17: 12894 | G17: 13570 | H17: Berkshire Knitting Mills | I17: William E. Sheeler
A18: 1932Text | B18: 2279346 | C18: RR | E18: 12965 | G18: 13983 | H18: Berkshire Knitting Mills | I18: William E. Sheeler
A19: 1932Text | B19: 2297028 | C19: RR | E19: 13100 | G19: 14151 | H19: Berkshire Knitting Mills | I19: William E. Sheeler
A20: 1932Text | B20: 2338075 | C20: RR | E20: 13586 | G20: 14606 | H20: Berkshire Knitting Mills | I20: Hugo Hemmerich
A21: 1932Text | B21: 2334008 | C21: RR | E21: 13692 | G21: 14557 | H21: Berkshire Knitting Mills | I21: Alfred E. Ischinger
A22: 1932Text | B22: 2305218 | C22: RR | E22: 13695 | G22: 14228 | H22: Berkshire Knitting Mills | I22: Hugo Hemmerich
A24: Patents listed in Schedule B of Final Judgment, RF:
A25: 1932Text | B25: 2001676 | C25: RF | E25: 10146 | G25: 11456 | H25: Textile Machine Works | I25: Gustav Gastrich | M25: 2
A26: 1932Text | B26: 2042149 | C26: RF | E26: 10405 | G26: 11834 | H26: Textile Machine Works | I26: Gustav Gastrich | M26: 2
A27: 1932Text | B27: 2021598 | C27: RF | E27: 10493 | G27: 11645 | H27: Textile Machine Works | I27: Gustav Gastrich | M27: 2
A28: 1932Text | B28: 2002888 | C28: RF | E28: 10617 | G28: 11470 | H28: Textile Machine Works | I28: Gustav Gastrich
A29: 1932Text | B29: 2002888 | C29: RF | D29: Re.19662 (2002888) | E29: 10617 | F29: 11479 | G29: 11540 | H29: Textile Machine Works | I29: Gustav Gastrich
A30: 1932Text | B30: 1965034 | C30: RF | E30: 10623 | G30: 11141 | H30: Textile Machine Works | I30: Gustav Gastrich
A31: 1932Text | B31: 1983128 | C31: RF | E31: 10623 | G31: 11295 | H31: Textile Machine Works | I31: Gustav Gastrich
A32: 1932Text | B32: 2077557 | C32: RF | E32: 10660 | G32: 12163 | H32: Textile Machine Works | I32: Gustav Gastrich
A33: 1932Text | B33: 2035876 | C33: RF | E33: 10745 | G33: 11778 | H33: Textile Machine Works | I33: Gustav Gastrich
A34: 1932Text | B34: 2087572 | C34: RF | E34: 11026 | G34: 12254 | H34: Textile Machine Works | I34: Gustav Gastrich
A35: 1932Text | B35: 2055458 | C35: RF | E35: 11072 | G35: 11953 | H35: Textile Machine Works | I35: Gustav Gastrich
A36: 1932Text | B36: 2119575 | C36: RF | D36: (O) 722245 - 2055458 (Di) 93566 | E36: 11072 | F36: 11900 | G36: 12576 | H36: Textile Machine Works | I36: Gustav Gastrich
A37: 1932Text | B37: 2181836 | C37: RF | E37: 11451 | G37: 13115 | H37: Quaker Hosiery Company | I37: Otto F. Smetana
A38: 1932Text | B38: 2246246 | C38: RF | E38: 11912 | G38: 13682 | H38: Textile Machine Works | I38: Gustav Gastrich
A39: 1932Text | B39: 2178319 | C39: RF | E39: 12145 | G39: 13087 | H39: Textile Machine Works | I39: Gottlob Bitzer
A40: 1932Text | B40: 2223252 | C40: RF | E40: 12424 | G40: 13479 | H40: Textile Machine Works | I40: Herbert Erich Haehnel
A41: 1932Text | B41: 2259974 | C41: RF | D41: (O) 183656 (Di) 355888 | E41: 12424 | F41: 13401 | G41: 13808 | H41: Textile Machine Works | I41: Herbert Erich Haehnel
A42: 1932Text | B42: 2167248 | C42: RF | E42: 12468 | G42: 12989 | I42: Wesley R. McCurdy, John W. Boyle
A44: Patents listed in Schedule C of Final Judgment, RR:
A45: 1932Text | B45: 1920435 | C45: RR | E45: 9542 | G45: 10805 | H45: Schletter & Zander, Inc. | I45: Emil Richter | M45: 2
A46: 1932Text | B46: 2049887 | C46: RR | E46: 9555 | G46: 11904 | H46: Textile Machine Works | I46: Rudolph Anke | M46: 2
A47: 1932Text | B47: 1959403 | C47: RR | E47: 9696 | G47: 11099 | H47: Textile Machine Works | I47: Fred Autem | M47: 2
A48: 1932Text | B48: 1959732 | C48: RR | E48: 9727 | G48: 11099 | H48: Textile Machine Works | I48: Christian F. Meyer | M48: 2
A49: 1932Text | B49: 2015106 | C49: RR | E49: 9835 | G49: 11589 | H49: Textile Machine Works | I49: Gustav Gastrich | M49: 2
A50: 1932Text | B50: 1910352 | C50: RR | E50: 9908 | G50: 10735 | H50: Textile Machine Works | I50: William H. Moyer | M50: 2
A51: 1932Text | B51: 1960227 | C51: RR | E51: 9916 | G51: 11099 | H51: Textile Machine Works | I51: Max Krissiep | M51: 2
A52: 1932Text | B52: 1971725 | C52: RR | E52: 9959 | G52: 11197 | H52: Textile Machine Works | I52: Emil Max Müller, Emil Richter | M52: 2
A53: 1932Text | B53: 1938207 | C53: RR | E53: 10009 | G53: 10931 | H53: Textile Machine Works | I53: Gottlob Bitzer | M53: 2
A54: 1932Text | B54: 1937084 | C54: RR | E54: 10070 | G54: 10924 | H54: Textile Machine Works | I54: Henry Janssen | M54: 2
A55: 1932Text | B55: 1940237 | C55: RR | E55: 10112 | G55: 10945 | H55: Textile Machine Works | I55: Julius Bareiss | M55: 2
A56: 1932Text | B56: 1937539 | C56: RR | E56: 10118 | G56: 10931 | H56: Textile Machine Works | I56: Melchior Zwicky | M56: 2
... A61: 1932Text | B61: 1941296 | C61: RR | E61: 10176 | G61: 10952 | H61: Textile Machine Works | I61: Gustav Gastrich | M61: 2
A62: 1932Text | B62: 1941296 | C62: RR | D62: Re.19843 (1941296) | E62: 10176 | F62: 11576 | G62: 11722 | H62: Textile Machine Works | I62: Gustav Gastrich | M62: 2
A63: 1932Text | B63: 2004219 | C63: RR | E63: 10190 | G63: 11484 | H63: Textile Machine Works | I63: Max Richter | M63: 2
A64: 1932Text | B64: 1949854 | C64: RR | E64: 10288 | G64: 11022 | H64: Textile Machine Works | I64: Fred Autem | M64: 2
A65: 1932Text | B65: 1931051 | C65: RR | E65: 10291 | G65: 10882 | H65: Textile Machine Works | I65: Fred Autem | M65: 2
A66: 1932Text | B66: 1977676 | C66: RR | E66: 10339 | G66: 11253 | H66: Textile Machine Works | I66: Gustav Gastrich | M66: 2
A67: 1932Text | B67: 2044539 | C67: RR | E67: 10357 | G67: 11855 | H67: Textile Machine Works | I67: Christian F. Meyer, Melchior Zwicky | M67: 2
A68: 1932Text | B68: 2042149 | C68: RR | E68: 10405 | G68: 11834 | H68: Textile Machine Works | I68: Gustav Gastrich | M68: 2
A69: 1932Text | B69: 1998364 | C69: RR | E69: 10426 | G69: 11428 | H69: Textile Machine Works | I69: Gustav Gastrich | M69: 2
A70: 1932Text | B70: 2018460 | C70: RR | E70: 10455 | G70: 11617 | H70: Textile Machine Works | I70: Christian F. Meyer | M70: 2
A71: 1932Text | B71: 2030944 | C71: RR | E71: 10477 | G71: 11736 | H71: Textile Machine Works | I71: Paul Schmidt | M71: 2
A72: 1932Text | B72: 2034990 | C72: RR | E72: 10486 | G72: 11771 | H72: Textile Machine Works | I72: Emil Richter | M72: 2
A73: 1932Text | B73: 2021598 | C73: RR | E73: 10493 | G73: 11645 | H73: Textile Machine Works | I73: Gustav Gastrich | M73: 2
A74: 1932Text | B74: 2033301 | C74: RR | E74: 10500 | G74: 11757 | H74: Textile Machine Works | I74: Emil Richter, Paul Schmidt | M74: 2
... A77: 1932Text | B77: 2080223 | C77: RR | E77: 10591 | G77: 12184 | H77: Textile Machine Works | I77: Gustav Gastrich | M77: 2
A78: 1932Text | B78: 2007798 | C78: RR | E78: 10599 | G78: 11512 | H78: Textile Machine Works | I78: Gustav Gastrich
A79: 1932Text | B79: 2002888 | C79: RR | E79: 10617 | G79: 11470 | H79: Textile Machine Works | I79: Gustav Gastrich
A80: 1932Text | B80: 2002888 | C80: RR | D80: Re.19662(2002888) | E80: 10617 | F80: 11479 | G80: 11540 | H80: Textile Machine Works | I80: Gustav Gastrich
A81: 1932Text | B81: 1965034 | C81: RR | E81: 10623 | G81: 11141 | H81: Textile Machine Works | I81: Gustav Gastrich
A82: 1932Text | B82: 1983128 | C82: RR | E82: 10623 | G82: 11295 | H82: Textile Machine Works | I82: Gustav Gastrich
A83: 1932Text | B83: 1928283 | C83: RR | E83: 10653 | G83: 10861 | H83: Berkshire Knitting Mills | I83: John George Ennis
A84: 1932Text | B84: 2077557 | C84: RR | E84: 10660 | G84: 12163 | H84: Textile Machine Works | I84: Gustav Gastrich
A85: 1932Text | B85: 1964462 | C85: RR | E85: 10669 | G85: 11134 | H85: Textile Machine Works | I85: Gustav Gastrich
A86: 1932Text | B86: 2051636 | C86: RR | E86: 10678 | G86: 11918 | H86: Textile Machine Works | I86: Gustav Gastrich
A87: 1932Text | B87: 2003766 | C87: RR | E87: 10689 | G87: 11477 | H87: Textile Machine Works | I87: Melchior Zwicky
A88: 1932Text | B88: 1941419 | C88: RR | E88: 10693 | G88: 10952 | H88: Textile Machine Works | I88: Max Richter
A89: 1932Text | B89: 2014114 | C89: RR | E89: 10693 | G89: 11575 | H89: Textile Machine Works | I89: Emil Max Müller
A90: 1932Text | B90: 1965656 | C90: RR | E90: 10697 | G90: 11148 | H90: Textile Machine Works | I90: Max Krissiep, Herman Staub
A91: 1932Text | B91: 1984068 | C91: RR | D91: (O) 666282 (Di) 724486 | E91: 10697 | F91: 11085 | G91: 11302 | H91: Textile Machine Works | I91: Max Krissiep, Herman Staub
A92: 1932Text | B92: 2010624 | C92: RR | E92: 10702 | G92: 11540 | H92: Textile Machine Works | I92: Friedrich Max Clauss
A93: 1932Text | B93: 2013883 | C93: RR | E93: 10702 | G93: 11575 | H93: Textile Machine Works | I93: Gustav Gastrich
A94: 1932Text | B94: 2090883 | C94: RR | E94: 10707 | G94: 12289 | I94: Edward R. Ammon
A95: 1932Text | B95: 2005070 | C95: RR | E95: 10716 | G95: 11491 | H95: Textile Machine Works | I95: Gottlob Bitzer
A96: 1932Text | B96: 1978454 | C96: RR | E96: 10745 | G96: 11260 | H96: Textile Machine Works | I96: Gustav Gastrich
A97: 1932Text | B97: 2016742 | C97: RR | D97: (O) 673985 (Di) 748840 | E97: 10745 | F97: 11248 | G97: 11603 | H97: Textile Machine Works | I97: Gustav Gastrich
A98: 1932Text | B98: 2035876 | C98: RR | E98: 10745 | G98: 11778 | H98: Textile Machine Works | I98: Gustav Gastrich
A99: 1932Text | B99: 2202521 | C99: RR | E99: 10767 | G99: 13297 | H99: Textile Machine Works | I99: Gustav Gastrich
A100: 1932Text | B100: 1978259 | C100: RR | E100: 10804 | G100: 11253 | H100: Textile Machine Works | I100: Gustav Gastrich
A101: 1932Text | B101: 1990988 | C101: RR | E101: 10809 | G101: 11365 | H101: Textile Machine Works | I101: Gustav Gastrich
A102: 1932Text | B102: 2092806 | C102: RR | E102: 10830 | G102: 12310 | H102: Textile Machine Works | I102: Samuel Edward Kalbach, Max Poeschmann
A103: 1932Text | B103: 2009968 | C103: RR | E103: 10833 | G103: 11533 | H103: Textile Machine Works | I103: Gustav Gastrich
A104: 1932Text | B104: 1966247 | C104: RR | E104: 10849 | G104: 11148 | H104: Textile Machine Works | I104: Henry Janssen
A105: 1932Text | B105: 1978086 | C105: RR | E105: 10849 | G105: 11253 | H105: Textile Machine Works | I105: Henry Janssen
A106: 1932Text | B106: 2060620 | C106: RR | E106: 10849 | G106: 12002 | H106: Textile Machine Works | I106: Henry Janssen
A107: 1932Text | B107: 2059806 | C107: RR | E107: 10878 | G107: 11995 | H107: Textile Machine Works | I107: Max Richter
A108: 1932Text | B108: 2142168 | C108: RR | E108: 10892 | G108: 12786 | H108: Textile Machine Works | I108: Rudolph Anke
...

Sheet 1933Hydr
A1: PoolID | B1: Patent | C1: Compulsory Licensing Type | D1: Application Date | E1: Grant Date | F1: Assignee (Inventor) | G1: Primary Class A | H1: Primary Subclass | I1: Secondary Subclass 1a | J1: Secondary Subclass 2a | K1: Secondary Subclass 3a | L1: Secondary Subclass 4a | M1: Secondary Subclass 5a | N1: Secondary Subclass 6a | O1: Secondary Subclass 7a | P1: Secondary Subclass 8a | Q1: Secondary Subclass 9a | R1: Secondary Subclass 10a | S1: Secondary Class B | T1: Secondary Subclass 1b | U1: Secondary Subclass 2b | V1: Secondary Subclass 3b | W1: Secondary Subclass 4b | X1: Secondary Subclass 5b | Y1: Secondary Subclass 6b | Z1: Secondary Class C | AA1: Secondary Subclass 1c | AB1: Secondary Subclass 2c | AC1: Secondary Subclass 3c | AD1: Secondary Subclass 4c | AE1: Secondary Subclass 5c | AF1: Secondary Subclass 6c | AG1: Secondary Subclass 7c | AH1: Secondary Class D | AI1: Secondary Subclass 1d | AJ1: Secondary Subclass 2d | AK1: Secondary Subclass 3d | AL1: Secondary Subclass 4d | AM1: Secondary Subclass 5d | AN1: Secondary Subclass 6d | AO1: Secondary Subclass 7d | AP1: Secondary Subclass 8d | AQ1: Secondary Class E | AR1: Secondary Subclass 1e | AS1: Secondary Subclass 2e | AT1: Secondary Class F | AU1: Secondary Subclass 1f | AV1: Secondary Subclass 2f | AW1: Secondary Subclass 3f
A2: Patents listed in the opinion:
A3: 1933Hydr | B3: 1907947 | D3: 7804 | E3: 10721 | F3: Alta Vista (Gage) | G3: 417 | H3: 401 | S3: 91 | T3: 313
